<?xml version='1.0' encoding='utf-8'?>
<?xml-stylesheet type="text/xsl" href="/static/rss.xsl"?>
<feed
    xmlns="http://www.w3.org/2005/Atom" xml:lang="en">
    <id>https://www.skysports.com/manchester-united-news</id>
    <title>Manchester United News - Latest News &amp; Highlights</title>
    <updated>2024-06-07T11:24:45+00:00</updated>
    <link href="https://www.skysports.com/manchester-united-news" rel="alternate"/>
    <generator uri="https://lkiesow.github.io/python-feedgen" version="1.0.0">python-feedgen</generator>
    <subtitle>Manchester United News - Latest News &amp; Highlights - Made with love by RSSHub(https://github.com/DIYgod/RSSHub)</subtitle>
    <entry>
        <id>https://www.skysports.com/football/news/11095/13147159/roy-keane-man-found-guilty-of-assaulting-ex-manchester-united-captain-with-headbutt</id>
        <title>男子在英超比赛中用头撞基恩被判有罪</title>
        <updated>2024-06-06T09:00:00+00:00</updated>
        <link href="https://www.skysports.com/football/news/11095/13147159/roy-keane-man-found-guilty-of-assaulting-ex-manchester-united-captain-with-headbutt"/>
        <summary type="html">&lt;p&gt;一名男子因在英超比赛中头撞罗伊·基恩而被判有罪。&lt;/p&gt;&lt;p&gt;43 岁的斯科特·劳 (Scott Law) 来自埃塞克斯郡沃尔瑟姆修道院 (Waltham Abbey)，他被指控于去年 9 月 3 日袭击了前曼联队长。&lt;/p&gt;&lt;p&gt;这场对抗发生在阿森纳在酋长球场以 3-1 击败曼联时，基恩当时正在酋长球场担任评论员。&lt;/p&gt;&lt;p&gt;社交媒体上的视频似乎显示米卡·理查兹介入。基恩说，他对这场冲突感到「震惊」。&lt;/p&gt;&lt;p&gt;劳对普通袭击指控不认罪，他告诉法庭，基恩在「玩笑变得更具攻击性」后告诉他「在外面见他」。&lt;/p&gt;&lt;p&gt;&lt;em&gt;更多内容敬请关注...&lt;/em&gt;&lt;/p&gt;&lt;p&gt;&lt;em&gt;这是一个正在更新的突发新闻报道，更多细节将很快发布。&lt;/em&gt;&lt;/p&gt;&lt;p&gt;&lt;em&gt;天空体育为您带来实时更新。&lt;/em&gt;&lt;/p&gt;&lt;p&gt;&lt;em&gt;天空体育是您值得信赖的突发体育新闻头条和实时更新的来源。&lt;/em&gt;&lt;/p&gt;&lt;p&gt;&lt;em&gt;访问 skysports.com 或天空体育应用程序了解所有&lt;a href="https://eur01.safelinks.protection.outlook.com/?url=https%3A%2F%2Fwww.skysports.com%2Fnews-wire&amp;amp;data=04%7C01%7Cdaniel.boswell%40sky.uk%7C6fe776ba0f9f4fcb424d08d87b418a6a%7C68b865d5cf184b2b82a4a4eddb9c5237%7C0%7C0%7C637394868788947996%7CUnknown%7CTWFpbGZsb3d8eyJWIjoiMC4wLjAwMDAiLCJQIjoiV2luMzIiLCJBTiI6Ik1haWwiLCJXVCI6Mn0%3D%7C1000&amp;amp;sdata=S3IIhiTAseQ8sAdHMNrTeKx34iSAfWYjmneZRylP7Uw%3D&amp;amp;reserved=0" target="_blank"&gt;突发体育新闻头条&lt;/a&gt;。&lt;a href="https://eur01.safelinks.protection.outlook.com/?url=https%3A%2F%2Fwww.skysports.com%2Fmore-sports%2Fnews%2F11095%2F10952996%2Fsky-sports-push-notifications-faq-how-to-receive-the-alerts-you-want&amp;amp;data=04%7C01%7Cdaniel.boswell%40sky.uk%7C6fe776ba0f9f4fcb424d08d87b418a6a%7C68b865d5cf184b2b82a4a4eddb9c5237%7C0%7C0%7C637394868788957988%7CUnknown%7CTWFpbGZsb3d8eyJWIjoiMC4wLjAwMDAiLCJQIjoiV2luMzIiLCJBTiI6Ik1haWwiLCJXVCI6Mn0%3D%7C1000&amp;amp;sdata=oUSdGmRTeiIOFzQoUQz0j5IOWaFrOTH4VFpEgUKAmRc%3D&amp;amp;reserved=0" target="_blank"&gt;来自天空体育应用程序的推送通知&lt;/a&gt;想要了解您喜爱的运动的最新资讯，您可以关注&lt;a href="https://eur01.safelinks.protection.outlook.com/?url=https%3A%2F%2Ftwitter.com%2FSkySportsNews&amp;amp;data=04%7C01%7Cdaniel.boswell%40sky.uk%7C6fe776ba0f9f4fcb424d08d87b418a6a%7C68b865d5cf184b2b82a4a4eddb9c5237%7C0%7C0%7C637394868788957988%7CUnknown%7CTWFpbGZsb3d8eyJWIjoiMC4wLjAwMDAiLCJQIjoiV2luMzIiLCJBTiI6Ik1haWwiLCJXVCI6Mn0%3D%7C1000&amp;amp;sdata=M1fyXyk3nrPuOxUqU%2BUMvjR6f30bzBd3MDdhr5eTAuA%3D&amp;amp;reserved=0" target="_blank"&gt;X 上的 @SkySportsNews&lt;/a&gt;获取最新更新，您现在也可以关注&lt;a href="https://www.whatsapp.com/channel/0029VaLuBby1SWsvuBCrf53l" target="_blank"&gt;天空体育的 WhatsApp 频道&lt;/a&gt;.&lt;/em&gt;&lt;/p&gt;</summary>
        <published>2024-06-06T09:00:00+00:00</published>
    </entry>
    <entry>
        <id>https://www.skysports.com/football/news/11095/13145477/man-utd-and-england-star-kobbie-mainoo-is-next-up-on-sky-sports-listen-and-subscribe-to-the-series</id>
        <title>Mainoo 是下一个 - 收听并订阅该系列</title>
        <updated>2024-06-06T08:00:00+00:00</updated>
        <link href="https://www.skysports.com/football/news/11095/13145477/man-utd-and-england-star-kobbie-mainoo-is-next-up-on-sky-sports-listen-and-subscribe-to-the-series"/>
        <summary type="html">&lt;p&gt;天空体育推出了新的 Next Up 系列 - 以下是如何聆听和阅读您需要了解的有关比赛下一位超级巨星的所有信息......&lt;/p&gt;&lt;p&gt;&lt;a href="https://www.skysports.com/football/story-telling/11096/13148353/next-up-how-kobbie-mainoo-became-manchester-uniteds-main-man"&gt;接下来是&lt;strong&gt;科比·麦努&lt;/strong&gt;&lt;/a&gt;，这位突然出现在现场的中场球员&lt;strong&gt;曼联&lt;/strong&gt;本赛季可能会出演&lt;strong&gt;英格兰&lt;/strong&gt;在这个夏天的&lt;strong&gt;欧元&lt;/strong&gt;.&lt;/p&gt;&lt;div class="sdc-site-outbrain sdc-site-outbrain--AR_5"&gt;
&lt;div class="OUTBRAIN"&gt;
&lt;/div&gt;
&lt;/div&gt;
&lt;p&gt;&lt;em&gt;天空体育&lt;/em&gt;与迈努的前教练进行了交谈，讲述了他从曼彻斯特郊区的青年足球到曼联中场核心的旅程——包括一路上与曼城的短暂接触。&lt;/p&gt;&lt;ul&gt;&lt;li&gt;&lt;a href="https://podfollow.com/essentialfootball/episode/7213e818f82f2a2921871e65bc7ae2906e14ade0/view"&gt;&lt;strong&gt;收听并订阅 Next Up 播客&lt;/strong&gt;&lt;/a&gt;&lt;/li&gt;&lt;li&gt;&lt;a href="https://www.skysports.com/football/story-telling/11096/13148353/next-up-how-kobbie-mainoo-became-manchester-uniteds-main-man"&gt;&lt;strong&gt;下一篇：迈努如何成为曼联的主力&lt;/strong&gt;&lt;/a&gt;&lt;/li&gt;&lt;li&gt;&lt;strong&gt;&lt;a href="https://www.skysports.com/football/story-telling/11095/13141296/next-up-extraordinary-endrick-and-his-journey-to-real-madrid"&gt;下一篇：恩德里克不再是一个名字，他是一个现实&lt;/a&gt;&lt;/strong&gt;&lt;/li&gt;&lt;li&gt;&lt;strong&gt;&lt;a href="https://www.nowtv.com/watch-sky-sports-online?DCMP=ilc_skysports_nc_articlelink"&gt;通过 NOW 直播天空体育&lt;/a&gt; | &lt;a href="https://www.sky.com/tv/sports?dcmp=ssf.com_bul_shop"&gt;获取天空体育&lt;/a&gt;&lt;/strong&gt;&lt;/li&gt;&lt;/ul&gt; &lt;p&gt;&lt;a href="https://www.skysports.com/football/story-telling/11096/13148353/next-up-how-kobbie-mainoo-became-manchester-uniteds-main-man"&gt;在这里阅读 Mainoo 的故事&lt;/a&gt;和&lt;a href="https://podfollow.com/essentialfootball/episode/7213e818f82f2a2921871e65bc7ae2906e14ade0/view"&gt;收听 Next Up 播客&lt;/a&gt;.&lt;/p&gt;
&lt;p&gt;那么为何不&lt;a href="https://www.skysports.com/football/story-telling/11095/13141296/next-up-extraordinary-endrick-and-his-journey-to-real-madrid"&gt;回顾一下我们的个人资料&lt;strong&gt;恩德里克&lt;/strong&gt;&lt;/a&gt;这位 16 岁的前锋以约 6000 万欧元（5140 万英镑）的价格签约&lt;strong&gt;皇家马德里&lt;/strong&gt;现在准备在今年夏天迎来他的 18 岁生日，最终搬到伯纳乌。&lt;/p&gt;
&lt;p&gt;但迈努和恩德里克只是开始。&lt;em&gt;天空体育&lt;/em&gt;将会照亮一些即将席卷足球界的下一代球员。&lt;/p&gt;&lt;div class="ad ad--teads"&gt;
&lt;div class="sdc-site-au"&gt;
&lt;div&gt;&lt;/div&gt;
&lt;div class="sdc-site-au__teads" id="in-article-desktop"&gt;&lt;/div&gt;
&lt;/div&gt;
&lt;/div&gt;
&lt;p&gt;恩德里克的帕尔梅拉斯队友，&lt;strong&gt;埃斯特沃·威廉&lt;/strong&gt;- 谁将加入&lt;strong&gt;切尔西&lt;/strong&gt;- 是下一个，同时我们还将透露一些在欧洲杯和欧洲杯上值得关注的明星&lt;strong&gt;美洲杯&lt;/strong&gt;这个夏天。&lt;/p&gt;
&lt;p&gt;&lt;a href="https://pod.fo/e/241552"&gt;收听并订阅播客&lt;/a&gt;确保您不会错过任何事情，并务必阅读有关它们的所有内容&lt;em&gt;天空体育&lt;/em&gt;.&lt;/p&gt;
&lt;div&gt;&lt;/div&gt;</summary>
        <published>2024-06-06T08:00:00+00:00</published>
    </entry>
    <entry>
        <id>https://www.skysports.com/football/news/12709/13147048/jadon-sancho-wants-manchester-united-return-but-without-manager-erik-ten-hag-paper-talk</id>
        <title>文件：桑乔希望曼联回归，但没有十个女巫</title>
        <updated>2024-06-02T23:15:00+00:00</updated>
        <link href="https://www.skysports.com/football/news/12709/13147048/jadon-sancho-wants-manchester-united-return-but-without-manager-erik-ten-hag-paper-talk"/>
        <summary type="html">&lt;p&gt;周一报纸的头条新闻和转会传闻......&lt;/p&gt;&lt;p&gt;&lt;strong&gt;每日镜报&lt;/strong&gt;&lt;/p&gt;&lt;div class="sdc-site-outbrain sdc-site-outbrain--AR_5"&gt;
&lt;div class="OUTBRAIN"&gt;
&lt;/div&gt;
&lt;/div&gt;
&lt;p&gt;杰登·桑乔已经准备好回到曼联——但前提是埃里克·十·哈格今年夏天离开。&lt;/p&gt;&lt;p&gt;曼联可能会在今年夏天失去布鲁诺·费尔南德斯，据报道这位中场球员的经纪人正在与拜仁慕尼黑进行谈判。&lt;/p&gt;&lt;ul&gt;&lt;li&gt;&lt;a href="https://www.skysports.com/transfer-centre"&gt;&lt;strong&gt;换乘中心现场直播！&lt;/strong&gt;&lt;/a&gt;&lt;/li&gt;&lt;li&gt;&lt;strong&gt;&lt;a href="https://www.skysports.com/football/news/32461/13130980/efl-on-sky-sports-how-to-watch-your-championship-league-one-or-league-two-team-live-next-season"&gt;天空体育+ - 下赛季超过 1,000 场 EFL 比赛直播，无需支付额外费用&lt;/a&gt;&lt;/strong&gt;&lt;/li&gt;&lt;li&gt;&lt;a href="https://www.skysports.com/football/news/11677/13078979/now-sports-membership-qa-how-do-i-stream-sky-sports-is-it-instant-is-there-a-contract"&gt;&lt;strong&gt;您需要知道的一切 - 通过 NOW 直播天空体育&lt;/strong&gt;&lt;/a&gt;&lt;/li&gt;&lt;li&gt;&lt;strong&gt;&lt;a href="https://www.skysports.com/football/news/11095/13056245/sky-sports-on-whatsapp-how-to-follow-our-channel-for-the-latest-news-features-and-highlights" target="_blank"&gt;通过 WhatsApp 获取天空体育&lt;/a&gt; | &lt;a href="https://www.skysports.com/football/news/11677/12572660/download-the-sky-sports-app-premier-league-goals-f1-race-control-and-more-at-your-fingertips" target="_blank"&gt;下载天空体育应用程序&lt;/a&gt;&lt;/strong&gt;&lt;/li&gt;&lt;/ul&gt;&lt;p&gt;&lt;strong&gt;太阳&lt;/strong&gt;&lt;/p&gt;
&lt;p&gt;马德里竞技队正在成为以 2000 万英镑以上的价格签下西汉姆联中衞纳耶夫·阿盖德的热门人选。&lt;/p&gt;&lt;div class="ad ad--teads"&gt;
&lt;div class="sdc-site-au"&gt;
&lt;div&gt;&lt;/div&gt;
&lt;div class="sdc-site-au__teads" id="in-article-desktop"&gt;&lt;/div&gt;
&lt;/div&gt;
&lt;/div&gt;
&lt;p&gt;如果埃德森离开，曼城将引进 AC 米兰的超级门将迈克·麦格南。&lt;/p&gt;
&lt;p&gt;约翰·特克斯特请求英超联赛给予宽限期以拯救埃弗顿，同时仍共同拥有水晶宫。&lt;/p&gt;&lt;p&gt;卢卡斯·帕奎塔要求西汉姆联主帅大衞·莫耶斯让他缺席英超比赛，这导致他受到了罚球指控。&lt;/p&gt;&lt;p&gt;&lt;strong&gt;电讯报&lt;/strong&gt;&lt;/p&gt;&lt;p&gt;纽卡斯尔联队在错过托辛·阿达拉比奥约后，本周将尝试与伯恩茅斯中后衞劳埃德·凯利达成交易。&lt;/p&gt;
&lt;p&gt;多特蒙德超人队无视温布利酋长在冠军联赛决赛前与他们会面的直接要求，徒劳地试图阻止任何烟火表演。&lt;/p&gt;&lt;p&gt;杰克·格里利什正在为参加 2024 年欧洲杯英格兰队的位置而奋斗，而哈里·马奎尔则因严重伤病而无法参加德国杯揭幕战。&lt;/p&gt;&lt;p&gt;&lt;strong&gt;每日邮件&lt;/strong&gt;&lt;/p&gt;&lt;p&gt;SFA 已要求苏格兰俱乐部批准将董事会主要成员的薪水翻倍的提议。&lt;/p&gt;&lt;p&gt;&lt;strong&gt;每日快报&lt;/strong&gt;&lt;/p&gt;&lt;p&gt;伊加·斯瓦泰克（Iga Swiatek）在法网第四轮比赛中仅用了 40 分钟，就获得了惊人的每分钟 8,843 英镑的收入。&lt;/p&gt;
&lt;p&gt;&lt;strong&gt;监护人&lt;/strong&gt;&lt;/p&gt;&lt;p&gt;杰米·穆雷相信，对于他和他的兄弟安迪来说，「机不可失，时不再来」，要实现共同参加温布尔登男双比赛的目标，这可能是安迪在温布尔登的最后一次亮相。&lt;/p&gt;&lt;p&gt;&lt;strong&gt;时代&lt;/strong&gt;&lt;/p&gt;&lt;p&gt;曼联和曼城将获得欧足联的批准，在下个赛季与姐妹俱乐部（尼斯和赫罗纳）参加相同的欧洲赛事。&lt;/p&gt;
&lt;p&gt;西汉姆联队已经接近以 2550 万英镑的价格签下 18 岁的帕尔梅拉斯前锋路易斯·吉尔赫梅。&lt;/p&gt;&lt;p&gt;&lt;strong&gt;运动型&lt;/strong&gt;&lt;/p&gt;&lt;p&gt;卢卡·莫德里奇已经同意与皇马签订一份为期一年的新合同，让他在俱乐部效力到 2025 年。&lt;/p&gt;
&lt;p&gt;洛杉矶银河队正在与自由球员马科·罗伊斯进行高级谈判&lt;/p&gt;&lt;p&gt;&lt;strong&gt;苏格兰太阳报&lt;/strong&gt;&lt;/p&gt;&lt;p&gt;南安普顿主帅拉塞尔·马丁希望与马特·奥莱利重聚，但英超新人可能因价格过高而无法竞购凯尔特人中场。&lt;/p&gt;&lt;p&gt;如果桑德兰错过了他们的头号目标威尔·斯蒂尔，斯蒂芬·罗宾逊就会出现在桑德兰的攻击名单上。&lt;/p&gt;&lt;p&gt;&lt;strong&gt;日志&lt;/strong&gt;&lt;/p&gt;&lt;p&gt;本·多克（Ben Doak）即将在苏格兰首次亮相，史蒂夫·克拉克（Steve Clarke）承认他无法取代林登·戴克斯（Lyndon Dykes）。&lt;/p&gt;</summary>
        <published>2024-06-02T23:15:00+00:00</published>
    </entry>
    <entry>
        <id>https://www.skysports.com/football/news/12016/13145033/harry-maguire-exclusive-england-defender-on-lessons-learned-and-ambition-to-win-euro-2024-this-summer</id>
        <title>马奎尔：比赛就在瞬间获胜——我们要去那里赢得胜利</title>
        <updated>2024-05-31T08:00:00+00:00</updated>
        <link href="https://www.skysports.com/football/news/12016/13145033/harry-maguire-exclusive-england-defender-on-lessons-learned-and-ambition-to-win-euro-2024-this-summer"/>
        <summary type="html">&lt;p&gt;「这绝对意味着一切……」&lt;/p&gt;&lt;p&gt;当被问及今年夏天赢得欧洲杯对他意味着什么时，哈里·马奎尔微笑着回答。&lt;/p&gt;&lt;div class="sdc-site-outbrain sdc-site-outbrain--AR_5"&gt;
&lt;div class="OUTBRAIN"&gt;
&lt;/div&gt;
&lt;/div&gt;
&lt;p&gt;「我们已经很长一段时间没有举起奖杯了——但我们已经很接近了。」&lt;/p&gt;&lt;p&gt;很少有球员比这位曼联中后衞更能反思英格兰队在索斯盖特的带领下在最近几场比赛中取得的相对成功。&lt;/p&gt;&lt;ul&gt;&lt;li&gt;&lt;a href="https://www.skysports.com/football/news/19692/13137394/euro-2024-squad-lists-hosts-germany-france-netherlands-england-scotland-italy-and-more"&gt;&lt;strong&gt;2024 年欧洲杯阵容：谁将前往德国？&lt;/strong&gt;&lt;/a&gt;&lt;/li&gt;&lt;li&gt;&lt;strong&gt;&lt;a href="https://www.skysports.com/football/news/11095/13144651/gareth-southgate-stays-committed-to-england-amid-manchester-united-season-review"&gt;索斯盖特在曼联审查中仍致力于英格兰&lt;/a&gt;&lt;/strong&gt;&lt;/li&gt;&lt;li&gt;&lt;strong&gt;&lt;a href="https://www.skysports.com/football/news/11700/13136992/premier-league-2024-25-season-start-date-schedule-fixture-release-international-breaks-and-final-day"&gt;英超联赛 2024/25 赛季日期、赛程、赛程发布&lt;/a&gt;&lt;/strong&gt;&lt;/li&gt;&lt;li&gt;&lt;strong&gt;&lt;a href="https://www.nowtv.com/watch-sky-sports-online?DCMP=ilc_skysports_nc_articlelink"&gt;通过 NOW 直播英超联赛&lt;/a&gt;| &lt;a href="https://www.sky.com/tv/sports?dcmp=ssf.com_bul_shop"&gt;获取天空体育&lt;/a&gt;&lt;/strong&gt;&lt;/li&gt;&lt;/ul&gt;&lt;p&gt;马奎尔是英格兰过去三届世界杯的关键人物，他们进入了半决赛、决赛和四分之一决赛。&lt;/p&gt;
&lt;p&gt;但时间回到 2018 年俄罗斯世界杯之前，这是一个不同的英格兰。&lt;/p&gt;&lt;div class="ad ad--teads"&gt;
&lt;div class="sdc-site-au"&gt;
&lt;div&gt;&lt;/div&gt;
&lt;div class="sdc-site-au__teads" id="in-article-desktop"&gt;&lt;/div&gt;
&lt;/div&gt;
&lt;/div&gt;
&lt;p&gt;一个没有任何期望的英格兰，几乎是一种相信会发生的欢乐气氛&lt;em&gt;其他&lt;/em&gt;注定失败的比赛。&lt;/p&gt;
&lt;p&gt;「这是 2018 年的一个新团体」，马奎尔在与&lt;em&gt;天空体育新闻。&lt;/em&gt;&lt;/p&gt;&lt;p&gt;「加雷斯刚刚开始做一些事情——我们的期望可能只是小组出线，但我们在那场比赛中打得非常好，我们奠定了良好的基础。&lt;/p&gt;&lt;p&gt;「这对我来说是一段美好的时光，这段时期我可能在顶级足球比赛中提升了一个水平，那是一段美妙的时光。」&lt;/p&gt;&lt;p&gt;英格兰最终在半决赛中输给了克罗地亚，但正如马奎尔所暗示的那样，这场比赛产生了未经过滤的乐观情绪，并且对这支英格兰队的期望持续增长。&lt;/p&gt;
&lt;p&gt;现在他们将带着一系列令人印象深刻的比赛表现前往德国，他们的教练无疑是球员们信任的，同时也接受了比赛中最强球队之一的标签。&lt;/p&gt;&lt;p&gt;马奎尔解释道：「他做了很多小事，他知道让球队团结在一起、让每个人享受训练营、让每个人都想为自己的国家效力是多么重要——当然，事情就应该这样。」&lt;/p&gt;&lt;p&gt;「这是成为一名英格兰球员的好时机，我们觉得我们正处于一个美好的时刻，这是一场我期待的比赛——我们要去那里赢得胜利。」&lt;/p&gt; &lt;div class="ui-vendor-monterosa"&gt;
&lt;div class="ui-vendor-monterosa__inner" id="monterosa-widget-c2aaccc5-4007-4fb3-8dd3-474c9447ea32-7e8679fa-0e0d-439c-93a0-65d5b409a83a"&gt;
&lt;/div&gt;
&lt;section class="ui-consent-roadblock"&gt;
&lt;div class="ui-consent-roadblock-body"&gt;
&lt;span class="ui-consent-roadblock-body__title"&gt;罗莎山&lt;/span&gt;
&lt;span class="ui-consent-roadblock-body__description"&gt;此内容由提供&lt;span class="ui-consent-roadblock-body__vendor-title"&gt;罗莎山&lt;/span&gt;，可能使用 cookie 和其他技术。
                &lt;span class="ui-consent-roadblock-body__vendor-title"&gt;罗莎山&lt;/span&gt;cookie 或仅允许这些 cookie 一次。
                &lt;a href="https://www.skysports.com/football/news/12016/13145033/harry-maguire-exclusive-england-defender-on-lessons-learned-and-ambition-to-win-euro-2024-this-summer#privacy-options"&gt;隐私选项&lt;/a&gt;.
            &lt;/span&gt;
&lt;span class="ui-consent-roadblock-body__description"&gt;遗憾的是，我们无法验证您是否同意&lt;span class="ui-consent-roadblock-body__vendor-title"&gt;罗莎山&lt;/span&gt;饼干。
                &lt;span class="ui-consent-roadblock-body__vendor-title"&gt;罗莎山&lt;/span&gt;仅用于此会话的 cookie。&lt;/span&gt;
&lt;div class="ui-consent-roadblock-body__link-group"&gt;
&lt;a class="ui-consent-roadblock-body__link ui-consent-roadblock-permanently" href="https://www.skysports.com/football/news/12016/13145033/harry-maguire-exclusive-england-defender-on-lessons-learned-and-ambition-to-win-euro-2024-this-summer#"&gt;启用 Cookie&lt;/a&gt;
&lt;a class="ui-consent-roadblock-body__link ui-consent-roadblock-once" href="https://www.skysports.com/football/news/12016/13145033/harry-maguire-exclusive-england-defender-on-lessons-learned-and-ambition-to-win-euro-2024-this-summer#"&gt;允许 Cookie 一次&lt;/a&gt;
&lt;/div&gt;
&lt;/div&gt;
&lt;/section&gt;
&lt;/div&gt;
&lt;h3&gt;&lt;strong&gt;马奎尔：锦标赛足球就是「时刻」&lt;/strong&gt;&lt;/h3&gt;
&lt;p&gt;英格兰似乎具备了赢得比赛的基础。&lt;/p&gt;&lt;p&gt;「现在是成为一名英格兰球员的好时机」，马奎尔说。&lt;/p&gt;
&lt;p&gt;然而，如果说索斯盖特领导下的这支英格兰队有什么瑕疵的话——在最重要的场合、最重要的交锋中——他们也只是落后了一点。&lt;/p&gt;&lt;p&gt;不过，英格兰队还是值得同情的——在过去三场比赛中，他们输给了决赛选手（2018 年克罗地亚、2022 年法国）或最终获胜者（2021 年意大利）。&lt;/p&gt;&lt;p&gt;但如果这支英格兰队想要创造自己的遗产和历史——与之前令人痛苦的失利相比，他们这次如何能提供不同的结果呢？&lt;/p&gt;
&lt;p&gt;「我认为我们在这些锦标赛中输掉的所有三场比赛都可能以任何一种方式发生」，马奎尔说。&lt;/p&gt;&lt;p&gt;「参加锦标赛与参加联赛完全不同——它是建立在时刻的基础上的，你必须确保你在比赛中，让时刻占据主导地位。&lt;/p&gt;&lt;p&gt;「这就是你的大牌球员发挥并创造那些神奇时刻的地方。&lt;/p&gt;&lt;p&gt;「你只需要确保你能做到这一点并在当天表现出色，给自己一个去赢得胜利的机会。」&lt;/p&gt;&lt;h3&gt;&lt;strong&gt;裘德·贝林厄姆赢得欧洲杯&lt;/strong&gt;&lt;/h3&gt;
&lt;p&gt;这支英格兰队拥有众多球星，无论是队长哈里·凯恩、英超联赛四连冠得主菲尔·福登和凯尔·沃克，还是年轻的新星科比·迈努，他都成为了一名最佳球员。&lt;/p&gt;&lt;p&gt;但也许没有哪个英格兰球员比裘德·贝林厄姆对俱乐部的影响更大。&lt;/p&gt;&lt;p&gt;人们预计他需要时间在皇马适应，但他已经成为伯纳博的关键人物，打进 19 球并贡献 6 次助攻，帮助皇马重新夺回西甲冠军。&lt;/p&gt;&lt;p&gt;马奎尔说：「裘德是一位了不起的球员——一位真正的大领导者，一位伟大的个性，并且在球场上显然非常有才华。」&lt;/p&gt;
&lt;p&gt;「我对裘德的评价不高，他来到了英格兰，在一两次治疗后我就知道他会如何走。&lt;/p&gt;&lt;p&gt;「我回到了我的俱乐部，我告诉了他们所有关于他的事情，但他走了一条不同的道路，他在皇家马德里做得非常好。当他在那里签约时，我就知道他会的，希望这种情况能够持续下去。」&lt;/p&gt;&lt;p&gt;贝林厄姆在皇马的第一个赛季的数据相当令人印象深刻，正如马奎尔所说，他穿着一件专门的球衣。&lt;em&gt;STAT 体育&lt;/em&gt;背心收集大量数据来监控训练表现和工作量。&lt;/p&gt;
&lt;p&gt;随着统计数据越来越成为足球运动的重要组成部分，人们想知道足球运动员对统计数据的关注程度有多少。&lt;/p&gt;&lt;p&gt;马奎尔说：「是的，尤其是近年来，足球是关于数据的。&lt;/p&gt;&lt;p&gt;「我认为你会看到跑步统计数据——现在每个足球俱乐部都会对其进行分析到最小的细节——所以它是比赛的重要组成部分。&lt;/p&gt;&lt;p&gt;「我认为你可以看到你在赢得比赛中跑动的次数与你获胜的次数之间的关系，尤其是在曼联。每个足球俱乐部都会监控它，以最大限度地提高你的表现。」&lt;/p&gt;&lt;p&gt;&lt;em&gt;&lt;strong&gt;哈利·马奎尔以 GPS 表现数据公司 STATSports 大使的身份接受了天空体育新闻的采访。&lt;/strong&gt;&lt;/em&gt;&lt;/p&gt;&lt;h3&gt;英格兰 2024 年欧洲杯之前的赛程&lt;/h3&gt;&lt;p&gt;6 月 3 日星期一：&lt;strong&gt;英格兰 vs 波斯尼亚和黑塞哥维那&lt;/strong&gt;- 晚上 7.45 开始&lt;/p&gt;&lt;p&gt;6 月 7 日星期五：&lt;strong&gt;英格兰 vs 冰岛 -&lt;/strong&gt;晚上 7.45 开始&lt;/p&gt;&lt;p&gt;&lt;strong&gt;英格兰 2024 年欧洲杯赛程&lt;/strong&gt;&lt;/p&gt;&lt;p&gt;6 月 16 日星期日 - C 组：&lt;strong&gt;塞尔维亚 vs 英格兰&lt;/strong&gt;（Arena AufSchalke，盖尔森基兴 - 英国时间晚上 8 点开球）&lt;/p&gt;&lt;p&gt;6 月 20 日星期四 - C 组：&lt;strong&gt;丹麦 vs 英格兰&lt;/strong&gt;（法兰克福瓦尔德体育场 - 英国时间下午 5 点开球）&lt;/p&gt;&lt;p&gt;6 月 25 日星期二 - C 组：&lt;strong&gt;英格兰 vs 斯洛文尼亚&lt;/strong&gt;（科隆 RheinEnergieStadion - 英国时间晚上 8 点开球）&lt;/p&gt;&lt;h3&gt;&lt;strong&gt;2024 年欧洲杯关键日期&lt;/strong&gt;&lt;/h3&gt;&lt;p&gt;2024 年 6 月 14 日：2024 年欧洲杯揭幕战，安联球场（慕尼黑）&lt;br/&gt;6 月 30 日至 7 月 2 日：16 强&lt;br/&gt;7 月 5 日至 6 日：四分之一决赛&lt;br/&gt;2024 年 7 月 9 日至 10 日：半决赛&lt;br/&gt;2024 年 7 月 14 日：2024 年欧洲杯决赛，奥林匹克体育场（柏林）&lt;/p&gt;</summary>
        <published>2024-05-31T08:00:00+00:00</published>
    </entry>
    <entry>
        <id>https://www.skysports.com/football/news/12028/13141696/kieran-mckenna-why-ipswich-manager-was-in-demand-this-summer-and-linked-to-brighton-chelsea-and-manchester-united</id>
        <title>为什么伊普斯维奇的麦肯纳是炙手可热的主教练</title>
        <updated>2024-05-30T16:10:00+00:00</updated>
        <link href="https://www.skysports.com/football/news/12028/13141696/kieran-mckenna-why-ipswich-manager-was-in-demand-this-summer-and-linked-to-brighton-chelsea-and-manchester-united"/>
        <summary type="html">&lt;p&gt;基兰·麦肯纳 (Kieran McKenna) 今年夏天成为一名通缉犯——理由充分。&lt;/p&gt;&lt;p&gt;这位 38 岁的教练带领伊普斯维奇连续两年晋级 EFL，并在 22 年来首次在波特曼路征战英超联赛，并让数周的猜测尘埃落定。&lt;a href="https://digitalcms.cf.sky.com/story-manager/story/13141696"&gt;与俱乐部签订一份为期四年的新合同&lt;/a&gt;.&lt;/p&gt;&lt;div class="sdc-site-outbrain sdc-site-outbrain--AR_5"&gt;
&lt;div class="OUTBRAIN"&gt;
&lt;/div&gt;
&lt;/div&gt;
&lt;p&gt;&lt;em&gt;天空体育新闻&lt;/em&gt;透露麦肯纳是布莱顿空缺职位的候选人，&lt;a href="https://www.skysports.com/football/news/11667/13142093/kieran-mckenna-manchester-united-meet-with-representatives-of-ipswich-boss-amid-chelsea-interest"&gt;而曼联官员则会见了伊普斯维奇主帅的代表。&lt;/a&gt;&lt;/p&gt;&lt;ul&gt;&lt;li&gt;&lt;strong&gt;&lt;a href="https://www.skysports.com/football/news/11707/13144328/kieran-mckenna-signs-new-ipswich-town-contract-after-interest-from-man-utd-chelsea-and-brighton"&gt;伊普斯维奇主帅麦肯纳签下新的长期合同&lt;/a&gt;&lt;/strong&gt;&lt;/li&gt;&lt;li&gt;&lt;strong&gt;&lt;a href="https://www.skysports.com/football/news/21564/13130980/efl-on-sky-sports-how-to-watch-your-championship-league-one-or-league-two-team-live-next-season"&gt;如何观看你的 EFL 球队下赛季 20 次&lt;/a&gt;&lt;/strong&gt;&lt;/li&gt;&lt;li&gt;&lt;strong&gt;&lt;a href="https://www.skysports.com/football/news/11095/13128002/championship-2024-25-start-date-league-one-and-league-two-schedule-and-fixture-release"&gt;锦标赛、L1、L2 2024/25 赛季开始日期&lt;/a&gt;&lt;/strong&gt;&lt;/li&gt;&lt;li&gt;&lt;a href="https://www.sky.com/tv/sports?dcmp=articlelink"&gt;&lt;strong&gt;获取天空体育&lt;/strong&gt;&lt;/a&gt;&lt;strong&gt; | &lt;/strong&gt;&lt;a href="https://www.nowtv.com/watch-sky-sports-online?DCMP=ilc_skysports_nc_articlelink" target="_blank"&gt;&lt;strong&gt;通过 NOW 直播天空体育&lt;/strong&gt;&lt;/a&gt;&lt;/li&gt;&lt;/ul&gt;&lt;p&gt;伊普斯维奇知道这些联系，但没有收到任何俱乐部的正式联系。&lt;/p&gt;&lt;p&gt;麦肯纳也曾与接替切尔西的毛里西奥·波切蒂诺有关，但周日通过电话被告知俱乐部正在寻找其他人选。&lt;/p&gt;
&lt;p&gt;那么，为什么麦肯纳成为炙手可热的经理人呢？&lt;em&gt;天空体育&lt;/em&gt;看看原因...&lt;/p&gt;&lt;div class="ad ad--teads"&gt;
&lt;div class="sdc-site-au"&gt;
&lt;div&gt;&lt;/div&gt;
&lt;div class="sdc-site-au__teads" id="in-article-desktop"&gt;&lt;/div&gt;
&lt;/div&gt;
&lt;/div&gt;
&lt;ul&gt;&lt;li&gt;&lt;strong&gt;&lt;a href="https://www.skysports.com/football/news/11667/13142093/kieran-mckenna-manchester-united-meet-with-representatives-of-ipswich-boss-amid-chelsea-interest"&gt;曼联会见麦肯纳代表，讨论对伊普斯维奇主帅的兴趣&lt;/a&gt;&lt;/strong&gt;&lt;/li&gt;&lt;/ul&gt;&lt;h3&gt;统计数据怎么说...&lt;/h3&gt;
&lt;p&gt;伊普斯维奇的进攻风格在本赛季的英冠联赛中引起了许多人的注意。&lt;/p&gt;
&lt;p&gt;麦肯纳的球队最终成为分区最佳射手——尽管是升班马——在 46 场比赛中攻入 92 个进球。&lt;/p&gt;&lt;p&gt;伊普斯维奇也是第二梯队的定位球之王之一，只有卡迪夫城（21 个）的定位球进球数量比英超新援的 19 个进球还要多。&lt;/p&gt;&lt;p&gt;但真正让球迷们兴奋不已的是麦肯纳球队最后时刻进球的数量。&lt;/p&gt;&lt;p&gt;这意味着伊普斯维奇上赛季在失利的情况下赢下了 32 分——占他们总积分的三分之一。&lt;/p&gt;
&lt;h3&gt;麦肯纳如何获得双重晋升&lt;/h3&gt;&lt;p&gt;&lt;em&gt;天空体育的亚当·威廉姆斯：&lt;/em&gt;&lt;/p&gt;
&lt;p&gt;2021 年 12 月 16 日，伊普斯维奇确认 35 岁的曼联助理教练麦肯纳已被任命为新任主教练，合同为期三年半。&lt;/p&gt;&lt;p&gt;「基兰是谁？」&lt;/p&gt;&lt;p&gt;麦肯纳一开始说话轻声细语，但在与媒体的接触中却有条不紊、清晰而诚实，粉丝们很快就对麦肯纳离开更傲慢、有时甚至是专横的前任表示欢迎。&lt;/p&gt;&lt;p&gt;事实证明，在那个赛季剩余的时间里，升级是一项艰巨的任务，因为伊普斯维奇排名第 11，但麦肯纳已经在他执教的第一个完整赛季中打好了铁杆。&lt;/p&gt;
&lt;p&gt;弗雷迪·拉达波、多姆·鲍尔和莱夫·戴维斯将成为夏季引人瞩目的签约球员，从一开始，很明显，该赛季争夺联赛冠军的竞争将异常激烈。&lt;/p&gt;&lt;p&gt;普利茅斯始终保持着节奏，而伊普斯维奇、谢菲尔德星期三和巴恩斯利则试图跟上。&lt;/p&gt;&lt;p&gt;2 月 14 日与布里斯托尔流浪者队互交白卷，滑落至第四名后，可以理解的是，人们的想法转向了另一个令人失望的赛季，他们落后前两名 8 分。&lt;/p&gt;&lt;p&gt;但一月份的转会窗口已经引进了四名关键球员：乔治·赫斯特、哈里·克拉克、马西莫·隆戈和内森·布罗德海德。&lt;/p&gt;&lt;p&gt;回到第二级别联赛的感觉很好，随着本赛季的开始，许多球迷希望赢得的比赛多于输掉的比赛，并以此为契机，在过去 18 个月的良好工作基础上继续前进。&lt;/p&gt;
&lt;p&gt;但 46 场比赛之后，他们重返顶级联赛。&lt;/p&gt; &lt;h3&gt;麦肯纳的球员对他的评价&lt;/h3&gt;
&lt;p&gt;&lt;em&gt;伊普斯维奇后衞莱夫·戴维斯十一月向天空体育表示：&lt;/em&gt;&lt;/p&gt;&lt;p&gt;「从我进门的第一天起，他（麦肯纳）就告诉我他会帮助我提高比赛水平，而且他在进攻和防守方面都做得非常出色。」&lt;/p&gt;&lt;p&gt;现年 24 岁的戴维斯上赛季从利兹联队加盟伊普斯维奇，并帮助他们从英甲联赛晋级。&lt;/p&gt;&lt;p&gt;「我不认为我在最后三分之一有这样的能力，这绝对不是我的最强点，但现在我会说它是。&lt;/p&gt;&lt;p&gt;「他在训练中与我合作的方式，让我在进攻三区更加适应脚下的球，并寻找传球机会，而不是仅仅将球送入禁区并希望得到最好的结果。&lt;/p&gt;&lt;p&gt;「我在球队中的踢球方式比普通左后衞更先进。我前面没有人，我自己必须在这方面做很多事情。」&lt;/p&gt;&lt;p&gt;「但这就是我的工作。这就是我被引进的原因，他相信我能扮演这个角色——至少我希望他能这么做！」&lt;/p&gt;&lt;p&gt;「来到这里是我做出的最好选择之一。虽然降级了两个联赛，但这就是踢足球所必须要做的。如果你努力工作，回报就会到来。」&lt;/p&gt;&lt;p&gt;「这与基兰和马塞洛·贝尔萨麾下的训练类似。他们对训练都有很高的要求，他们都希望你努力工作，每天学习并不断进步。」&lt;/p&gt;
&lt;p&gt;&lt;em&gt;伊普斯维奇边锋韦斯·伯恩斯一月份对天空体育表示：&lt;/em&gt;&lt;/p&gt;&lt;p&gt;「老板总是说，只要我们百分百付出，坚持我们的原则并执行他给我们的比赛计划，那么他就会对此感到非常满意。&lt;/p&gt;&lt;p&gt;「他是一位非常出色的教练，我们对他所说的一切都百分百信任。这种信任已经带到了球场上，我们正在为他出色地执行它。我认为这就是我们取得今天成绩的原因。」&lt;/p&gt;&lt;p&gt;「我们是一支非常努力工作的球队，我认为努力工作在这个联盟中大有帮助。&lt;/p&gt;&lt;p&gt;「从他进来的第一天起，就有很多信息需要吸收。但你可以从外部看到我们作为一个球队和个人所取得的进步。他把我们所有人带到了一个新的水平，这&lt;/p&gt;&lt;p&gt;「对我个人来说，他只是简化了我的比赛，对于很多球员来说，这样做可以让他们得到更多。&lt;/p&gt;
&lt;p&gt;「我每周都会为球队带来他希望从我这里得到的关键东西。在系统中设定角色，只要我在比赛日执行它们，它就会有效。」&lt;/p&gt;&lt;p&gt;「我（2015 年）作为 9 号球员去了弗利特伍德，但我绝对不是 9 号球员。所以找到我的位置肯定帮助我进步。&lt;/p&gt;&lt;p&gt;「然后显然来到这里，老板进来了，他再次稍微调整了我的位置。这确实是我开始从中获得最好回报的地方。」&lt;/p&gt;
&lt;p&gt;&lt;em&gt;三月份从伊普斯维奇租借到天空体育的奥马里·哈钦森：&lt;/em&gt;&lt;/p&gt;&lt;p&gt;「我和主教练进行了交谈，第一次见到他就与他建立了良好的联系。我想，你知道，这可能是最适合我的地方。&lt;/p&gt;&lt;p&gt;「他在青训营待过，他知道年轻男孩们的表现。所以我认为他来到这里是理所当然的。&lt;/p&gt;&lt;p&gt;「有时，当你作为替补进入球队时，主教练会告诉你，我们需要一种不同的动力。一名技术娴熟的球员，能够盯防你的防守球员，并且能够双向进攻。&lt;/p&gt;&lt;p&gt;「就我个人而言，我很享受这一点。我喜欢娱乐观众，主教练给了你这种自由。」&lt;/p&gt;</summary>
        <published>2024-05-30T16:10:00+00:00</published>
    </entry>
    <entry>
        <id>https://www.skysports.com/football/news/11667/13144980/jadon-sanchos-borussia-dortmund-return-offers-chance-of-a-new-wembley-story-in-the-champions-league-final</id>
        <title>多特蒙德的杰登·桑乔的重塑</title>
        <updated>2024-05-30T10:00:00+00:00</updated>
        <link href="https://www.skysports.com/football/news/11667/13144980/jadon-sanchos-borussia-dortmund-return-offers-chance-of-a-new-wembley-story-in-the-champions-league-final"/>
        <summary type="html">&lt;p&gt;在温布利举行的冠军联赛决赛对于许多与多特蒙德队相关的人来说意义重大。 &lt;/p&gt;&lt;p&gt;对于周六对阵皇家马德里队的另一名多特蒙德队队员来说，体育场的情绪略有不同。&lt;/p&gt;&lt;div class="sdc-site-outbrain sdc-site-outbrain--AR_5"&gt;
&lt;div class="OUTBRAIN"&gt;
&lt;/div&gt;
&lt;/div&gt;
&lt;p&gt;在英格兰对阵意大利的欧洲杯决赛中，桑乔在第 120 分钟由索斯盖特替换上场，主罚点球。&lt;/p&gt;
&lt;p&gt;仅仅 12 天后，他以 7300 万英镑转会曼联的消息就得到了确认。&lt;/p&gt;&lt;p&gt;此后发生的事件意味着，尽管他在欧洲俱乐部足球最重要的比赛中再次获得了在温布利球场出局的权利，但他早已失去了在英格兰队的位置——而且不是在曼联，而是被租借回多特蒙德&lt;/p&gt;
&lt;p&gt;在此期间发生的事情取决于你问的是谁。&lt;/p&gt;&lt;div class="ad ad--teads"&gt;
&lt;div class="sdc-site-au"&gt;
&lt;div&gt;&lt;/div&gt;
&lt;div class="sdc-site-au__teads" id="in-article-desktop"&gt;&lt;/div&gt;
&lt;/div&gt;
&lt;/div&gt;
&lt;p&gt;桑乔从来都不是一个独行者，尽管有那些从深处绕回的跑动。&lt;/p&gt;
&lt;p&gt;其他人则指出他在到来之前就迟到的言论，以及态度可疑的低声议论。&lt;/p&gt;&lt;p&gt;这仍然是引人注目的，前多特蒙德主帅尤尔根·克洛普在离开利物浦时提到过这一点。 &lt;/p&gt;&lt;p&gt;但无论曼联的情况如何，桑乔也没有得到很好的反映，需要做出回应。&lt;/p&gt;
&lt;p&gt;他成名的俱乐部似乎直观地理解他们在帮助他展示才华、重新发现真实自我方面所扮演的角色。 &lt;/p&gt;&lt;p&gt;多特蒙德一开始让他放松下来，但他们让他恢复了状态。&lt;em&gt;力量的壮举&lt;/em&gt;在 14 场德甲比赛中打进 2 粒进球和 2 次助攻，但人们已经看到了曾经照亮他们球场的天才球员。&lt;/p&gt;
&lt;h3&gt;&lt;strong&gt;「我们忘记了他们也是人」&lt;/strong&gt;&lt;/h3&gt;&lt;p&gt;在与尤尔根·克林斯曼谈论此事时，他强调了人的方面。 &lt;em&gt;天空体育&lt;/em&gt;.&lt;/p&gt;&lt;p&gt;「当他们从一个极端走到另一个极端，在一个地方找不到自己的状态，并且有些东西不起作用或不起作用，然后他们决定回到之前的地方时，需要时间来调整并获得他们的信心和状态&lt;/p&gt;&lt;p&gt;「在这种情况下，我认为主教练对球员要有耐心，让球员做他们的事情并提供帮助，但不要给他们太大的压力，让他们立即发挥出最高水平，这一点非常重要。&lt;/p&gt;
&lt;h3&gt;&lt;strong&gt;真正的桑乔再次崛起&lt;/strong&gt;&lt;/h3&gt;&lt;p&gt;统计数据说明了他对多特蒙德的重要性。&lt;/p&gt;&lt;ul&gt;&lt;li&gt;&lt;strong&gt;&lt;a href="https://www.skysports.com/football/news/11095/13130665/champions-league-final-2024-date-kick-off-time-venue-teams-referee-and-more-in-match-guide"&gt;2024 年欧冠决赛何时何地举行？&lt;/a&gt;&lt;/strong&gt;&lt;/li&gt;&lt;li&gt;&lt;strong&gt;&lt;a href="https://www.skysports.com/football/news/11945/13143876/champions-league-2024-25-everything-you-need-to-know-about-the-new-format-of-europes-most-prestigious-club-competition"&gt;解释：新的冠军联赛赛制如何运作&lt;/a&gt;&lt;/strong&gt;&lt;/li&gt;&lt;/ul&gt;&lt;p&gt;但他真正给人留下深刻印象的是冠军联赛。&lt;/p&gt;&lt;p&gt;他在首回合完成的 13 次过人不仅是本赛季欧冠比赛中球员中最多的，而且也是前两个赛季中最多的。&lt;/p&gt;
&lt;p&gt;信心恢复后，桑乔再次有目的地冲向防守队员，无论有球还是无球，都充满活力。&lt;/p&gt;&lt;p&gt;克林斯曼表示很高兴看到他这样，这代表了所有人。 &lt;/p&gt;&lt;p&gt;剩下的就是一个合适的结局。&lt;/p&gt;</summary>
        <published>2024-05-30T10:00:00+00:00</published>
    </entry>
    <entry>
        <id>https://www.skysports.com/football/news/11095/13144867/will-manchester-united-and-man-citys-multi-club-structures-with-nice-and-girona-affect-their-european-hopes</id>
        <title>曼联、曼城设定欧足联最后期限——解释多俱乐部规则和欧洲杯影响</title>
        <updated>2024-05-29T14:20:00+00:00</updated>
        <link href="https://www.skysports.com/football/news/11095/13144867/will-manchester-united-and-man-citys-multi-club-structures-with-nice-and-girona-affect-their-european-hopes"/>
        <summary type="html">&lt;p&gt;曼联赢得足总杯晋级欧联杯，但他们是否面临降级联赛的风险？&lt;/p&gt;&lt;p&gt;5 月 25 日，曼联在温布利球场决赛中以 2-1 击败邻国曼城，直接进入欧罗巴联赛小组赛，但他们将与法国俱乐部并肩作战。&lt;strong&gt;好的&lt;/strong&gt;，该公司也由 INEOS 创始人吉姆·拉特克利夫爵士 (Sir Jim Ratcliffe) 控制。&lt;/p&gt;&lt;div class="sdc-site-outbrain sdc-site-outbrain--AR_5"&gt;
&lt;div class="OUTBRAIN"&gt;
&lt;/div&gt;
&lt;/div&gt;
&lt;p&gt;欧足联规则对同一所有权结构下的俱乐部提供了严格的指导方针，不允许两支合作球队在同一场比赛中相互比赛。&lt;/p&gt;&lt;ul&gt;&lt;li&gt;&lt;strong&gt;&lt;a href="https://www.skysports.com/football/news/11700/13136992/premier-league-2024-25-season-start-date-schedule-fixture-release-international-breaks-and-final-day"&gt;英超联赛 2024/25 赛季关键日期&lt;/a&gt;&lt;/strong&gt; | &lt;a href="https://www.skysports.com/transfer-centre"&gt;&lt;strong&gt;换乘中心现场直播！&lt;/strong&gt;&lt;/a&gt;&lt;/li&gt;&lt;li&gt;&lt;a href="https://www.skysports.com/football/news/11095/13136937/premier-league-pre-season-friendlies-fixtures-results-2024-summer-tours-training-in-usa-asia-australia-and-more"&gt;&lt;strong&gt;2024 年英超联赛季前友谊赛&lt;/strong&gt;&lt;/a&gt;&lt;/li&gt;&lt;li&gt;&lt;a href="https://www.skysports.com/football/live-blog/11095/13129903/football-kits-2024-25-premier-league-efl-wsl-shirts-strips-and-retro-fits"&gt;&lt;strong&gt;2024/25 赛季新英超球衣&lt;/strong&gt;&lt;/a&gt;&lt;/li&gt;&lt;/ul&gt;&lt;p&gt;自曼联举起奖杯以来，英力士发布了一份声明，其中写道：「我们了解两家具乐部的立场，并正在与欧足联进行直接对话。&lt;/p&gt;
&lt;p&gt;「我们有信心为下赛季的欧洲赛程做好准备。」&lt;/p&gt;
&lt;p&gt;类似的情况影响&lt;strong&gt;曼彻斯特城&lt;/strong&gt;和他们的姐妹俱乐部&lt;strong&gt;赫罗纳&lt;/strong&gt;，两人都获得了欧冠资格，&lt;em&gt;天空体育&lt;/em&gt;看看两个俱乐部的规则和潜在的解决方案......&lt;/p&gt;&lt;div class="ad ad--teads"&gt;
&lt;div class="sdc-site-au"&gt;
&lt;div&gt;&lt;/div&gt;
&lt;div class="sdc-site-au__teads" id="in-article-desktop"&gt;&lt;/div&gt;
&lt;/div&gt;
&lt;/div&gt;
&lt;h3&gt;欧足联比赛中多俱乐部所有权的规则是什么？&lt;/h3&gt;&lt;p&gt;根据欧足联的多俱乐部所有权规则，任何个人或法人实体都不能在同一场欧足联比赛中对超过一个俱乐部拥有控制权或决定性影响力。&lt;/p&gt;
&lt;p&gt;控制力和决定性影响是什么意思？&lt;strong&gt;股东权利、财务支持、俱乐部治理和转让&lt;/strong&gt;.&lt;/p&gt;&lt;p&gt;&lt;strong&gt;股东权利：&lt;/strong&gt;欧足联俱乐部财务控制机构表示，如果一个俱乐部属于另一家具乐部，则该俱乐部对另一个俱乐部具有决定性影响力，例如。&lt;/p&gt;&lt;p&gt;&lt;strong&gt;经济支持：&lt;/strong&gt;如果一个俱乐部通过借钱向另一个俱乐部提供财务保障，或者一个俱乐部占另一个俱乐部总营业收入的至少 30%，那么您就具有决定性的影响力。&lt;/p&gt;&lt;p&gt;&lt;strong&gt;俱乐部治理：&lt;/strong&gt;如果一个人在两个俱乐部的管理机构（包括首席执行官、体育总监、俱乐部主席和首席财务官）中都担任职务，那么您就具有决定性的影响力。&lt;/p&gt;&lt;p&gt;如果一个俱乐部的关键人物可以罢免另一家具乐部的董事会成员、主要高管和一线队主教练，并在多个俱乐部之间做出球员转会、决定预算等关键行政决策，那么你也具有决定性影响力&lt;/p&gt;&lt;p&gt;&lt;strong&gt;球员转会：&lt;/strong&gt;如果一个俱乐部将三名或更多球员转移到另一家具乐部，或者共享相同的球探或球探数据库安排，则该俱乐部对另一家具乐部具有决定性影响。&lt;/p&gt;&lt;p&gt;如果满足其中一项或多项标准，那么欧足联将对是否产生决定性影响进行更详细的评估，然后再决定他们是否可以参加同一场欧足联比赛。&lt;/p&gt;&lt;h3&gt;那么这对曼联和曼城有何影响？&lt;/h3&gt;
&lt;p&gt;为了&lt;strong&gt;曼联&lt;/strong&gt;, 新少数投资者&lt;strong&gt;吉姆·拉特克利夫爵士&lt;/strong&gt;- 其英力士集团控制着俱乐部的足球业务并拥有俱乐部 27.7% 的股份 - 也是法国俱乐部的多数股东&lt;strong&gt;好的&lt;/strong&gt;.&lt;/p&gt;&lt;p&gt;虽然拉特克利夫拥有曼联不到 30% 的股份，因此通过股东权利遵守欧足联的规则，但英力士需要向欧足联证明，他们通过财务支持和治理对尼斯和曼联没有决定性影响。&lt;/p&gt;&lt;p&gt;鉴于拉特克利夫和戴夫·布雷尔斯福德爵士等其他关键人物的确切角色可能会受到调查，因为他们都直接参与了曼联和尼斯的工作。&lt;/p&gt;&lt;p&gt;同时，&lt;strong&gt;曼彻斯特城&lt;/strong&gt;和&lt;strong&gt;赫罗纳&lt;/strong&gt;两队均已获得下赛季欧冠小组赛资格，两支球队均隶属于阿布扎比联合集团旗下城市足球集团。&lt;/p&gt;&lt;p&gt;城市足球集团是英超冠军曼城的大股东，同时他们还拥有西甲俱乐部赫罗纳 44.3% 的股份。&lt;/p&gt;&lt;p&gt;看起来城市足球集团可能需要减少在赫罗纳的股份，以便两支球队都有资格参加欧洲冠军联赛。&lt;/p&gt;&lt;p&gt;欧洲管理机构向 CFG 提供了多种合规选项，其中包括通过欧足联批准的模式将赫罗纳的部分股权出售给独立第三方所有权，将其所有权控制在 30% 以下。&lt;/p&gt;&lt;p&gt;与此同时，由于本赛季的转会交易，城市足球集团可能对曼城和赫罗纳产生决定性影响。&lt;/p&gt;&lt;p&gt;赫罗纳本赛季还从 CFG 俱乐部签下了三名球员，包括直接来自曼城的右后衞扬·库托和中场球员扬格尔·埃雷拉。&lt;/p&gt;&lt;p&gt;城市体育总监 Txiki Begiristain 也是 CFG 的足球总监，不过赫罗纳确实有自己独立的体育总监 Quique Carcel。&lt;/p&gt;&lt;h3&gt;那么现在会发生什么呢？&lt;/h3&gt;&lt;p&gt;曼联和曼城的老板都必须等到&lt;strong&gt;6 月 3 日截止日期&lt;/strong&gt;在向欧足联提交有关合作伙伴俱乐部的计划之前安排其所有权结构。&lt;/p&gt;&lt;p&gt;随后，一个独立小组将决定这些合作俱乐部是否可以参加同样的比赛，并在七月中旬欧冠预选赛开始前做出裁决。&lt;/p&gt;&lt;p&gt;这也意味着曼联和曼城在参与欧足联诉讼期间不得分别通过尼斯和赫罗纳签下或出售任何球员。&lt;/p&gt;&lt;h3&gt;如果欧足联和专家组对计划不满意怎么办？&lt;/h3&gt;&lt;p&gt;如果合作俱乐部不符合欧足联的标准，则两个合作俱乐部中只有一个可以出现在同一赛事中。&lt;/p&gt;&lt;p&gt;然后，欧足联将查看哪支球队在联赛中排名较高，作为确定哪支球队参加更高级别赛事的标准的一部分。&lt;/p&gt;&lt;p&gt;就曼联而言，埃里克·十·哈格的球队在英超联赛中排名第八，尼斯在法甲联赛中获得第五名，那么法国队将获得欧罗巴联赛的席位，而曼联将降级到西甲联赛。&lt;/p&gt;&lt;p&gt;由于曼城在英超联赛中排名第一，而赫罗纳在西甲联赛中排名第三，那么西班牙球队将不得不转入欧罗巴联赛，只剩下曼城进入欧洲冠军联赛。&lt;/p&gt;&lt;h3&gt;那么曼联和赫罗纳的位置会发生什么变化呢？&lt;/h3&gt;
&lt;p&gt;根据欧足联规定，未获准参加比赛的俱乐部将由同一协会国内顶级联赛中排名第二的俱乐部取代。&lt;/p&gt;&lt;p&gt;那意味着&lt;strong&gt;切尔西&lt;/strong&gt;如果英力士未能达到欧足联的标准，那么他们将升入欧罗巴联赛以取代曼联的位置。&lt;/p&gt;&lt;p&gt;和&lt;strong&gt;毕尔巴鄂竞技队&lt;/strong&gt;赫罗纳队将是赫罗纳队未能进入欧洲冠军联赛的主要受益者，因为他们将凭借西甲第五名的成绩晋升到欧洲顶级联赛。&lt;/p&gt;&lt;h3&gt;这些困境以前发生过吗？&lt;/h3&gt;&lt;p&gt;是的，事实上就在最近。&lt;/p&gt;&lt;p&gt;&lt;strong&gt;阿斯顿维拉&lt;/strong&gt;被迫改变其在合作伙伴俱乐部的所有权结构&lt;strong&gt;吉马良斯维多利亚&lt;/strong&gt;因为两家具乐部上赛季都参加了欧罗巴联赛。&lt;/p&gt;&lt;p&gt;别墅老板纳塞夫·萨维里斯 (Nassef Sawiris) 和韦斯·艾登斯 (Wes Edens) 于 2023 年 2 月购买了这家葡萄牙俱乐部 46% 的股份，但去年夏天不得不将股份减少至 29%，以遵守欧足联股东规则。&lt;/p&gt;&lt;p&gt;&lt;strong&gt;布莱顿&lt;/strong&gt;老板托尼·布鲁姆也不得不减少他在姐妹俱乐部的股份&lt;strong&gt;联合圣吉卢瓦斯&lt;/strong&gt;上赛季比利时俱乐部与海鸥队一起参加欧罗巴联赛后。&lt;/p&gt;&lt;p&gt;然而，布莱顿和维拉均被欧足联告知，在 2024 年夏季转会窗口结束之前，他们不得通过转会或租借的方式交换球员。&lt;/p&gt;&lt;p&gt;&lt;strong&gt;AC 米兰&lt;/strong&gt;和&lt;strong&gt;图卢兹&lt;/strong&gt;尽管红鸟资本拥有，但他们也被允许一起参加欧洲比赛，因为欧足联将他们视为独立的第三方投资者，这样他们就可以平衡两家具乐部之间的股份以满足标准。&lt;/p&gt;</summary>
        <published>2024-05-29T14:20:00+00:00</published>
    </entry>
    <entry>
        <id>https://www.skysports.com/football/news/11667/13136937/premier-league-pre-season-friendlies-fixtures-results-2024-summer-tours-training-in-usa-asia-australia-and-more</id>
        <title>英超联赛季前友谊赛：你的俱乐部什么时候恢复比赛？</title>
        <updated>2024-05-29T12:15:00+00:00</updated>
        <link href="https://www.skysports.com/football/news/11667/13136937/premier-league-pre-season-friendlies-fixtures-results-2024-summer-tours-training-in-usa-asia-australia-and-more"/>
        <summary type="html">&lt;p&gt;英超俱乐部已经在为 2024/25 赛季制定计划，在全球范围内安排季前友谊赛。&lt;/p&gt;&lt;p&gt;阿森纳、曼联和利物浦今年夏天将在美国重新展开较量，而托特纳姆热刺则在一周内两次对阵拜仁慕尼黑。&lt;/p&gt;&lt;div class="sdc-site-outbrain sdc-site-outbrain--AR_5"&gt;
&lt;div class="OUTBRAIN"&gt;
&lt;/div&gt;
&lt;/div&gt;
&lt;p&gt;请跟踪下面所有友谊赛的赛程和结果。&lt;em&gt;随着更多俱乐部宣布季前赛日期并确认开球时间，此页面将会更新。&lt;/em&gt;&lt;/p&gt;&lt;ul&gt;&lt;li&gt;&lt;a href="https://www.skysports.com/football/news/11095/13136992/premier-league-2024-25-season-start-date-schedule-fixture-release-international-breaks-and-final-day"&gt;&lt;strong&gt;英超联赛 2024/25：赛程表、日期和赛程发布日&lt;/strong&gt;&lt;/a&gt;&lt;/li&gt;&lt;li&gt;&lt;strong&gt;&lt;a href="https://www.skysports.com/football/live-blog/11095/12476234/transfer-centre-live-bruno-fernandes-reportedly-set-to-stay-at-man-utd-after-talks-over-future"&gt;换乘中心现场直播！&lt;/a&gt;&lt;/strong&gt;&lt;/li&gt;&lt;li&gt;&lt;strong&gt;&lt;a href="https://www.skysports.com/football/news/11095/13136308/transfer-window-summer-2024-when-does-it-open-and-close-dates-and-deadline-day-for-premier-league-efl-wsl-and-more"&gt;2024 年夏季转会窗口日期和截止日期&lt;/a&gt;&lt;/strong&gt;&lt;/li&gt;&lt;li&gt;&lt;strong&gt;&lt;a href="https://www.skysports.com/football/news/11095/12002801/live-football-on-sky-sports-today-and-this-week-plus-more-fixtures-games-dates-kick-off-times"&gt;天空体育直播足球比赛&lt;/a&gt;&lt;/strong&gt;&lt;/li&gt;&lt;/ul&gt;&lt;h2&gt;哪些英超球队将在 2024 年夏天前往美国？&lt;/h2&gt;&lt;p&gt;几位英超重量级人物即将前往美国。&lt;/p&gt;&lt;p&gt;阿森纳将于 7 月分别在洛杉矶和费城对阵曼联和利物浦，而切尔西将在哥伦布迎战曼城，并且还与雷克瑟姆和皇家马德里进行了友谊赛。&lt;/p&gt;
&lt;p&gt;阿斯顿维拉、水晶宫、狼队和西汉姆联也将前往美国进行热身赛。&lt;/p&gt;&lt;div class="ad ad--teads"&gt;
&lt;div class="sdc-site-au"&gt;
&lt;div&gt;&lt;/div&gt;
&lt;div class="sdc-site-au__teads" id="in-article-desktop"&gt;&lt;/div&gt;
&lt;/div&gt;
&lt;/div&gt;
&lt;h2&gt;英超联赛季前友谊赛 - 目前已确定日期&lt;/h2&gt;&lt;h3&gt;兵工厂&lt;/h3&gt;&lt;p&gt;&lt;strong&gt;7 月 27 日：&lt;/strong&gt;阿森纳 vs 曼联 - 洛杉矶 SoFi 体育场（英国时间 7 月 28 日凌晨 1 点开球）&lt;br/&gt;&lt;strong&gt;7 月 31 日：&lt;/strong&gt;阿森纳 vs 利物浦 - 费城林肯金融球场，当地时间晚上 7 点开球（英国时间 8 月 1 日上午 12 点 30 分）&lt;/p&gt;
&lt;h3&gt;阿斯顿维拉&lt;/h3&gt;&lt;p&gt;&lt;strong&gt;7 月 17 日：&lt;/strong&gt;阿斯顿维拉 vs 沃尔索尔 - 贝斯科特体育场，晚上 7.30 开球&lt;br/&gt;&lt;strong&gt;7 月 27 日：&lt;/strong&gt;阿斯顿维拉 vs 哥伦布机员 - Lower.com Field，俄亥俄州，当地时间晚上 8 点开球（英国时间 7 月 28 日凌晨 1 点）&lt;br/&gt;&lt;strong&gt;7 月 31 日：&lt;/strong&gt;阿斯顿维拉 vs RB 莱比锡 - 新泽西州红牛竞技场，当地时间晚上 8 点开球（英国时间 8 月 1 日凌晨 1 点）&lt;br/&gt;&lt;strong&gt;8 月 3 日：&lt;/strong&gt;阿斯顿维拉 vs 美国俱乐部 - 芝加哥士兵场，当地时间下午 4.30 开球（英国时间晚上 10.30）&lt;br/&gt;&lt;strong&gt;8 月 10 日：&lt;/strong&gt;阿斯顿维拉 vs 多特蒙德 - 多特蒙德西格纳伊杜纳公园球场，英国时间下午 4 点开球&lt;/p&gt;&lt;h3&gt;布伦特福德&lt;/h3&gt;&lt;p&gt;&lt;strong&gt;8 月 3 日&lt;/strong&gt;：布伦特福德 vs 沃特福德 - 牧师路，下午 3 点开球&lt;br/&gt;&lt;strong&gt;8 月 9 日&lt;/strong&gt;：布伦特福德 vs 沃尔夫斯堡 - Gtech 社区体育场，晚上 7.45 开球&lt;/p&gt;&lt;h3&gt;布莱顿&lt;/h3&gt;&lt;p&gt;&lt;strong&gt;7 月 24 日：&lt;/strong&gt;鹿岛鹿角 vs 布莱顿 - 东京国家体育场，英国时间上午 11 点开球&lt;br/&gt;&lt;strong&gt;7 月 28 日：&lt;/strong&gt;东京绿茵 vs 布莱顿 - 东京国家体育场，英国时间上午 10.30 开球&lt;br/&gt;&lt;strong&gt;8 月 3 日：&lt;/strong&gt;QPR vs 布莱顿 - 洛夫特斯路，下午 3 点开球&lt;/p&gt;&lt;h3&gt;切尔西&lt;/h3&gt;&lt;p&gt;&lt;strong&gt;7 月 24 日：&lt;/strong&gt;切尔西 vs 雷克瑟姆 - 圣克拉拉李维斯体育场&lt;br/&gt;&lt;strong&gt;7 月 27 日：&lt;/strong&gt;切尔西 vs 凯尔特人 - 印第安纳州圣母体育场&lt;br/&gt;&lt;strong&gt;7 月 31 日：&lt;/strong&gt;切尔西 vs 美洲俱乐部 - 亚特兰大梅赛德斯奔驰体育场&lt;br/&gt;&lt;strong&gt;8 月 3 日：&lt;/strong&gt;切尔西 vs 曼城 - 俄亥俄体育场，哥伦布&lt;br/&gt;&lt;strong&gt;8 月 6 日：&lt;/strong&gt;切尔西 vs 皇家马德里 - 美国银行体育场，夏洛特&lt;/p&gt;&lt;h3&gt;水晶宫&lt;/h3&gt;&lt;p&gt;&lt;strong&gt;7 月 31 日：&lt;/strong&gt;水晶宫 vs 狼队 - 马里兰州海军陆战队纪念体育场，当地时间晚上 8 点开球（英国时间 8 月 1 日凌晨 1 点）&lt;br/&gt;&lt;strong&gt;8 月 3 日：&lt;/strong&gt;水晶宫 vs 西汉姆 - 佛罗里达州雷蒙德詹姆斯体育场，当地时间晚上 7 点开球（英国时间 8 月 4 日上午 12 点）&lt;/p&gt;&lt;h3&gt;埃弗顿&lt;/h3&gt;&lt;p&gt;&lt;strong&gt;7 月 27 日：&lt;/strong&gt;索尔福德城 vs 埃弗顿 - 半岛体育场，下午 3 点开球&lt;br/&gt;&lt;strong&gt;7 月 30 日：&lt;/strong&gt;考文垂 vs 埃弗顿 - 考文垂建筑协会竞技场，晚上 7.45 开球&lt;br/&gt;&lt;strong&gt;8 月 3 日：&lt;/strong&gt;普雷斯顿北区 vs 埃弗顿 - Deepdale，下午 3 点开球&lt;/p&gt;&lt;h3&gt;富勒姆&lt;/h3&gt;&lt;p&gt;&lt;strong&gt;8 月 10 日：&lt;/strong&gt;霍芬海姆 vs 富勒姆 - 德国 PreZero 竞技场，英国时间下午 4 点开球&lt;/p&gt;&lt;h3&gt;伊普斯威奇&lt;/h3&gt;&lt;p&gt;&lt;strong&gt;7 月 27 日：&lt;/strong&gt;伊普斯维奇 vs 杜塞尔多夫福图纳 - 波特曼路，下午 3 点&lt;/p&gt;&lt;h3&gt;利物浦&lt;/h3&gt;&lt;p&gt;&lt;strong&gt;7 月 27 日：&lt;/strong&gt;利物浦 vs 皇家贝蒂斯 - Acrisure 体育场，匹兹堡，英国时间上午 12.30 开球&lt;br/&gt;&lt;strong&gt;7 月 31 日：&lt;/strong&gt;利物浦 vs 阿森纳 - 费城林肯金融球场，当地时间晚上 7 点开球（英国时间 8 月 1 日上午 12 点 30 分）&lt;br/&gt;&lt;strong&gt;8 月 3 日：&lt;/strong&gt;利物浦 vs 曼联 - 南卡罗来纳州布莱斯体育场，英国时间 8 月 4 日上午 12 点 30 分开球&lt;/p&gt;&lt;h3&gt;曼城&lt;/h3&gt;&lt;p&gt;&lt;strong&gt;7 月 23 日：&lt;/strong&gt;曼城 vs 凯尔特人 - 北卡罗来纳州教堂山凯南体育场&lt;br/&gt;&lt;strong&gt;7 月 27 日：&lt;/strong&gt;曼城 vs AC 米兰 - 纽约洋基体育场&lt;br/&gt;&lt;strong&gt;7 月 30 日：&lt;/strong&gt;曼城 vs 巴塞罗那 - 奥兰多露营世界体育场&lt;br/&gt;&lt;strong&gt;8 月 3 日：&lt;/strong&gt;曼城 vs 切尔西 - 俄亥俄体育场，哥伦布&lt;/p&gt;&lt;h3&gt;曼联&lt;/h3&gt;&lt;p&gt;&lt;strong&gt;7 月 15 日：&lt;/strong&gt;曼联 vs 罗森博格 - 特隆赫姆莱肯达尔体育场，英国时间下午 5 点开球&lt;br/&gt;&lt;strong&gt;7 月 20 日：&lt;/strong&gt;曼联 vs 流浪者队 - 苏格兰燃气默里菲尔德，爱丁堡 - 下午 4 点开球&lt;br/&gt;&lt;strong&gt;7 月 27 日：&lt;/strong&gt;曼联 vs 阿森纳 - 洛杉矶 SoFi 体育场，英国时间 7 月 28 日凌晨 1 点开球&lt;br/&gt;&lt;strong&gt;7 月 31 日：&lt;/strong&gt;曼联 vs 皇家贝蒂斯 - 圣地亚哥金鱼草体育场，英国时间 8 月 1 日上午 5 点开球&lt;br/&gt;&lt;strong&gt;8 月 3 日&lt;/strong&gt;：曼联 vs 利物浦 - 南卡罗来纳州布莱斯体育场，英国时间 8 月 4 日上午 12 点 30 分开球&lt;/p&gt;&lt;h3&gt;新城堡&lt;/h3&gt;&lt;p&gt;&lt;strong&gt;5 月 22 日：&lt;/strong&gt;&lt;a href="https://www.skysports.com/football/newcastle-united-vs-tottenham-hotspur/504566"&gt;纽卡斯尔 1-1 托特纳姆热刺（纽卡斯尔点球大战 5-4 获胜） - MCG，墨尔本&lt;/a&gt;&lt;br/&gt;&lt;strong&gt;5 月 24 日：&lt;/strong&gt; &lt;a href="https://www.skysports.com/football/news/11095/13142371/newcastle-united-thrashed-8-0-by-a-league-all-stars-in-melbourne-as-post-season-tour-ends-on-low-note"&gt;澳超全明星 8-0 纽卡斯尔 - MCG、墨尔本&lt;/a&gt;&lt;br/&gt;&lt;strong&gt;7 月 31 日：&lt;/strong&gt;纽卡斯尔 vs 浦和红钻 - 埼玉县埼玉体育场，当地时间晚上 7.30 开球（英国时间上午 11.30）&lt;br/&gt;&lt;strong&gt;8 月 3 日：&lt;/strong&gt;纽卡斯尔 vs 横滨水手 - 东京国家体育场，当地时间晚上 7 点开球（英国时间下午 1 点）&lt;/p&gt;&lt;h3&gt;托特纳姆热刺&lt;/h3&gt;&lt;p&gt;&lt;strong&gt;5 月 22 日：&lt;/strong&gt;&lt;a href="https://www.skysports.com/football/newcastle-united-vs-tottenham-hotspur/504566"&gt;纽卡斯尔 1-1 托特纳姆热刺（纽卡斯尔点球大战 5-4 获胜） - MCG，墨尔本&lt;/a&gt;&lt;br/&gt;&lt;strong&gt;7 月 17 日：&lt;/strong&gt;哈茨 vs 托特纳姆热刺 - 泰恩卡斯尔，爱丁堡，晚上 7 点开球&lt;br/&gt;&lt;strong&gt;7 月 20 日：&lt;/strong&gt;QPR vs 托特纳姆热刺 - 洛夫特斯路，下午 3 点开球&lt;br/&gt;&lt;strong&gt;7 月 27 日：&lt;/strong&gt;托特纳姆热刺 vs 神户胜利船 - 东京国家体育场&lt;br/&gt;&lt;strong&gt;8 月 3 日：&lt;/strong&gt;托特纳姆热刺 vs 拜仁慕尼黑 - 韩国首尔世界杯体育场&lt;br/&gt;&lt;strong&gt;8 月 10 日：&lt;/strong&gt;托特纳姆热刺 vs 拜仁慕尼黑 - 托特纳姆热刺体育场，下午 5.30 开球&lt;/p&gt;&lt;h3&gt;西汉姆&lt;/h3&gt;&lt;p&gt;&lt;strong&gt;7 月 27 日：&lt;/strong&gt;西汉姆联 vs 狼队 - 佛罗里达州 EverBank 体育场，当地时间晚上 7 点开球（英国时间 7 月 28 日上午 12 点）&lt;br/&gt;&lt;strong&gt;8 月 3 日：&lt;/strong&gt;西汉姆联 vs 水晶宫 - 佛罗里达州雷蒙德詹姆斯体育场，当地时间晚上 7 点开球（英国时间 8 月 4 日上午 12 点）&lt;/p&gt;&lt;h3&gt;狼队&lt;/h3&gt;&lt;p&gt;&lt;strong&gt;7 月 27 日：&lt;/strong&gt;狼队 vs 西汉姆联 - 佛罗里达州 EverBank 体育场，当地时间晚上 7 点开球（英国时间 7 月 28 日上午 12 点）&lt;br/&gt;&lt;strong&gt;7 月 31 日：&lt;/strong&gt;狼队 vs 水晶宫 - 马里兰州海军陆战队纪念体育场，当地时间晚上 8 点开球（英国时间 8 月 1 日凌晨 1 点）&lt;/p&gt;&lt;h2&gt;2024/25 赛季英超联赛什么时候开始？&lt;/h2&gt;&lt;p&gt;2024/25 赛季英超联赛将于周末开始&lt;strong&gt;2018 年 8 月 17 日&lt;/strong&gt;.&lt;/p&gt;&lt;h2&gt;2024/25 赛季英超联赛赛程何时发布？&lt;/h2&gt;&lt;p&gt;英超联赛全部 380 场比赛的赛程将在&lt;strong&gt;6 月 18 日星期二上午 9 点&lt;/strong&gt;.&lt;/p&gt;&lt;p&gt;去年，&lt;em&gt;天空体育&lt;/em&gt;同时确认了其首周末的现场报道选择。&lt;/p&gt;&lt;p&gt;所有英超联赛比赛的日期和开球时间可能会发生变化。&lt;/p&gt;
&lt;h2&gt;天空体育直播 2024/25 年英超联赛&lt;/h2&gt;&lt;p&gt;&lt;em&gt;天空体育&lt;/em&gt;将在 2024/25 赛季独家现场直播 128 场比赛 - 以及一个品牌&lt;a href="https://www.skysports.com/football/news/11661/13019562/sky-sports-to-show-215-premier-league-games-a-season-from-2025-26#:~:text=From%202025%2C%20Sky%20Sports%20will,26%20through%20to%202028%2F29."&gt;天空体育与英超联赛达成新协议&lt;/a&gt;意味着从 2025/26 年开始会有更多现场比赛。&lt;/p&gt;&lt;p&gt;从 2025 年开始，&lt;em&gt;天空体育&lt;/em&gt;在敲定新的四年协议后，将创纪录地每赛季转播至少 215 场英超联赛。&lt;/p&gt;&lt;p&gt;整个 2024/25 赛季，您可以免费观看英超联赛的比赛集锦 - 无需成为&lt;em&gt;天空体育&lt;/em&gt;订户。&lt;/p&gt;&lt;p&gt;您会发现每场英超比赛的精彩片段&lt;a href="https://www.skysports.com/football/live-blog/11095/12478403/premier-league-football-goals-and-highlights-of-every-match-in-the-2022-23-season"&gt;&lt;strong&gt;在计分中心以及&lt;strong&gt;天空体育网站&lt;/strong&gt;和&lt;strong&gt;天空体育应用程序&lt;/strong&gt;全日制毕业后不久&lt;/strong&gt;&lt;/a&gt;，或从下午 5.15 开始，周六中午开球。&lt;strong&gt;&lt;a href="https://www.youtube.com/channel/UCNAf1k0yIjyGu3k9BwAg3lg"&gt;天空体育足球 YouTube&lt;/a&gt;&lt;/strong&gt;渠道。&lt;/p&gt;&lt;p&gt;您可以在无月或日会员合同的情况下直播天空体育直播&lt;strong&gt;&lt;a href="https://www.skysports.com/football/news/11095/13056245/sky-sports-on-whatsapp-how-to-follow-our-channel-for-the-latest-news-features-and-highlights"&gt;现在——了解更多&lt;/a&gt;&lt;/strong&gt;&lt;em&gt;&lt;strong&gt; &lt;/strong&gt;&lt;/em&gt;关于即时观看英超联赛、EFL、F1、英格兰板球等赛事的现场直播。&lt;/p&gt;&lt;h3&gt;天空体育+ - 更多体育赛事，八月推出！&lt;/h3&gt;&lt;p&gt;&lt;a href="https://www.skysports.com/football/news/32461/13131189/sky-sports-launches-in-august-to-give-more-choice-to-fans-via-live-streams-app-and-new-channel"&gt;天空体育+&lt;/a&gt;将通过直播和新的专用频道为体育迷提供更多选择，无需额外费用。&lt;/p&gt;&lt;p&gt;今年 8 月推出，&lt;strong&gt;天空体育+&lt;/strong&gt;体育迷可以通过直播获得的选择数量将发生转变&lt;a href="https://www.sky.com/tv/sports?dcmp=articlelink"&gt;天空电视台&lt;/a&gt;, 流媒体服务&lt;a href="https://www.nowtv.com/watch-sky-sports-online?DCMP=ilc_skysports_nc_articlelink"&gt;现在&lt;/a&gt;以及改进后的&lt;a href="https://qrcode.skysports.com/skysports/ContentPromo"&gt;天空体育应用程序&lt;/a&gt;在移动。&lt;/p&gt;&lt;p&gt;由于 EFL、网球巡回赛和男子超级联赛的报道比以往任何时候都多，天空体育的客户今年可以享受超过 50% 的现场体育赛事。&lt;/p&gt;</summary>
        <published>2024-05-29T12:15:00+00:00</published>
    </entry>
    <entry>
        <id>https://www.skysports.com/football/news/11095/13144899/jarrad-branthwaite-manchester-united-interested-in-signing-everton-defender-this-summer</id>
        <title>曼联有意签下埃弗顿后衞布兰斯维特</title>
        <updated>2024-05-29T10:30:00+00:00</updated>
        <link href="https://www.skysports.com/football/news/11095/13144899/jarrad-branthwaite-manchester-united-interested-in-signing-everton-defender-this-summer"/>
        <summary type="html">&lt;p&gt;曼联有兴趣从埃弗顿签下贾拉德·布兰斯维特。&lt;/p&gt;&lt;p&gt;曼联非常崇拜这位中后衞，他最近入选了英格兰 2024 年欧洲杯的训练阵容。&lt;/p&gt;&lt;div class="sdc-site-outbrain sdc-site-outbrain--AR_5"&gt;
&lt;div class="OUTBRAIN"&gt;
&lt;/div&gt;
&lt;/div&gt;
&lt;p&gt;后防核心的招募已被视为足总杯冠军球队的首要任务——无论下赛季的主教练是谁，这名 21 岁的球员都在讨论的名单中名列前茅。&lt;/p&gt;&lt;ul&gt;&lt;li&gt;&lt;a href="https://www.skysports.com/transfer-centre"&gt;&lt;strong&gt;换乘中心现场直播！&lt;/strong&gt;&lt;/a&gt; &lt;strong&gt;| &lt;a href="https://www.skysports.com/football/live-blog/11667/13025492/man-utd-transfer-news-and-rumours-casemiro-jadon-sancho-raphael-varane-kalvin-phillips-and-anthony-martial-latest"&gt;曼联转会传闻&lt;/a&gt;&lt;/strong&gt;&lt;/li&gt;&lt;li&gt;&lt;strong&gt;&lt;a href="https://www.skysports.com/football/news/11700/13136992/premier-league-2024-25-season-start-date-schedule-fixture-release-international-breaks-and-final-day"&gt;英超联赛 2024/25 赛季日期、赛程、赛程发布&lt;/a&gt;&lt;/strong&gt;&lt;/li&gt;&lt;li&gt;&lt;strong&gt;&lt;a href="https://www.nowtv.com/watch-sky-sports-online?DCMP=ilc_skysports_nc_articlelink"&gt;通过 NOW 直播英超联赛&lt;/a&gt;| &lt;a href="https://www.sky.com/tv/sports?dcmp=ssf.com_bul_shop"&gt;获取天空体育&lt;/a&gt;&lt;/strong&gt;&lt;/li&gt;&lt;/ul&gt;&lt;div class="ui-vendor-monterosa"&gt;
&lt;div class="ui-vendor-monterosa__inner" id="monterosa-widget-c2aaccc5-4007-4fb3-8dd3-474c9447ea32-d9512460-0830-41db-a5e8-f4c29d2490a1"&gt;
&lt;/div&gt;
&lt;section class="ui-consent-roadblock"&gt;
&lt;div class="ui-consent-roadblock-body"&gt;
&lt;span class="ui-consent-roadblock-body__title"&gt;罗莎山&lt;/span&gt;
&lt;span class="ui-consent-roadblock-body__description"&gt;此内容由提供&lt;span class="ui-consent-roadblock-body__vendor-title"&gt;罗莎山&lt;/span&gt;，可能使用 cookie 和其他技术。
                &lt;span class="ui-consent-roadblock-body__vendor-title"&gt;罗莎山&lt;/span&gt;cookie 或仅允许这些 cookie 一次。
                &lt;a href="https://www.skysports.com/football/news/11095/13144899/jarrad-branthwaite-manchester-united-interested-in-signing-everton-defender-this-summer#privacy-options"&gt;隐私选项&lt;/a&gt;.
            &lt;/span&gt;
&lt;span class="ui-consent-roadblock-body__description"&gt;遗憾的是，我们无法验证您是否同意&lt;span class="ui-consent-roadblock-body__vendor-title"&gt;罗莎山&lt;/span&gt;饼干。
                &lt;span class="ui-consent-roadblock-body__vendor-title"&gt;罗莎山&lt;/span&gt;仅用于此会话的 cookie。&lt;/span&gt;
&lt;div class="ui-consent-roadblock-body__link-group"&gt;
&lt;a class="ui-consent-roadblock-body__link ui-consent-roadblock-permanently" href="https://www.skysports.com/football/news/11095/13144899/jarrad-branthwaite-manchester-united-interested-in-signing-everton-defender-this-summer#"&gt;启用 Cookie&lt;/a&gt;
&lt;a class="ui-consent-roadblock-body__link ui-consent-roadblock-once" href="https://www.skysports.com/football/news/11095/13144899/jarrad-branthwaite-manchester-united-interested-in-signing-everton-defender-this-summer#"&gt;允许 Cookie 一次&lt;/a&gt;
&lt;/div&gt;
&lt;/div&gt;
&lt;/section&gt;
&lt;/div&gt;
&lt;p&gt;然而，在今年夏天寻找一名可靠的防守型中场和前锋的同时，曼联还需要在即将到来的转会窗口中在财务上进行巧妙的调整，并且必须增加他们在销售方面的支出。&lt;/p&gt;&lt;p&gt;埃弗顿认为布兰斯维特的估值在 60​​00 万至 7000 万英镑之间，埃弗顿必须在 6 月底之前出售其主要资产之一，以保持与 PSR 的一致。&lt;/p&gt;
&lt;p&gt;另一位可以赚取可观费用的球员是&lt;strong&gt; &lt;/strong&gt;阿马杜·奥纳纳——但这位中场球员目前还没有任何转会消息。&lt;/p&gt;&lt;div class="ad ad--teads"&gt;
&lt;div class="sdc-site-au"&gt;
&lt;div&gt;&lt;/div&gt;
&lt;div class="sdc-site-au__teads" id="in-article-desktop"&gt;&lt;/div&gt;
&lt;/div&gt;
&lt;/div&gt;
&lt;p&gt;这意味着布兰斯维特可能成为 6 月 30 日之前更有可能吸引报价的球员，他也被曼城和热刺盯上。&lt;/p&gt;
&lt;p&gt;热刺在一月份转会窗口之前非常仔细地考虑签下布兰斯维特，但最终从热那亚买下了拉杜·德拉古辛，尽管他们今年夏天确实想要另一名中后衞。&lt;/p&gt;&lt;p&gt;如果曼城今年夏天失去一名中后衞，他们可能会考虑他，但从目前的情况来看，这种情况预计不会发生。&lt;/p&gt;&lt;h3&gt;&lt;a href="https://www.skysports.com/football/news/11095/13143930/whats-next-for-manchester-united-and-erik-ten-hag-the-key-questions-answered"&gt;曼联和十哈格的下一步是什么？&lt;/a&gt;&lt;/h3&gt;
&lt;p&gt;&lt;em&gt;天空体育新闻&lt;/em&gt;资深记者梅丽莎·雷迪回答了曼联面临的关键问题，以及他们对埃里克·十·哈格在俱乐部的时光的回顾。&lt;/p&gt;&lt;p&gt;「我们已经确定，自从英力士确认将接管足球业务以来，戴夫·布雷尔斯福德爵士一直在与球员和工作人员讨论他们对曼联问题的看法。例如，队长布鲁诺·费尔南德斯提供了一个&lt;/p&gt;&lt;p&gt;「自一个多月前正式加入技术总监以来，杰森·威尔科克斯的关键任务之一就是对比赛模型、训练课程、教练组和更衣室之间的关系以及他们如何与其他区域互动进行更全面的审核&lt;/p&gt;&lt;p&gt;「对十哈格咒语的审查早已开始，主教练透露，审查以及他与曼联高层的讨论已经发生。他现在正在度假。&lt;/p&gt;
&lt;p&gt;「尽管已经掌握了所有信息，并且十女巫相信评估已经完成，但俱乐部表示他们的审查将&lt;em&gt;现在&lt;/em&gt;发生。&lt;/p&gt;&lt;p&gt;「有一种感觉是，在意识到与范加尔被解雇的情况进行比较后，曼联不想破坏足总杯决赛的庆祝活动，也不想被指责冷酷无情。这也不符合他们的最佳利益。」&lt;/p&gt;&lt;p&gt;「有足够的证据表明俱乐部在过去几个月公开搞乱了他们的继任计划——拜仁就是主要例子——曼联不想重蹈覆辙。」&lt;/p&gt;&lt;p&gt;&lt;a href="https://www.skysports.com/football/news/11095/13143930/whats-next-for-manchester-united-and-erik-ten-hag-the-key-questions-answered"&gt;&lt;strong&gt;请在此处阅读梅丽莎·雷迪 (Melissa Reddy) 的分析的更多内容。&lt;/strong&gt;&lt;/a&gt;&lt;/p&gt;&lt;h3&gt;&lt;a href="https://www.skysports.com/football/news/11095/13143812/premier-league-transfers-data-insights-on-what-each-club-needs-in-summer-window"&gt;数据显示曼联今年夏天需要什么&lt;/a&gt;&lt;/h3&gt;&lt;p&gt;由于埃里克·十·哈格的未来仍然悬而未决，曼联在夏天不可避免的动荡可能会在球场的各个领域看到新的球员——他们在防守和进攻上都陷入困境。&lt;/p&gt;&lt;p&gt;经验丰富的拉斐尔·瓦拉内的离开将使俱乐部的后防线变得光明，尤其是在利桑德罗·马丁内斯和卢克·肖持续受到伤病困扰的情况下。&lt;/p&gt;&lt;p&gt;本赛季他们使用了 14 名不同的中后衞搭档，老将乔尼·埃文斯 (Jonny Evans) 的联赛出场次数比俱乐部中任何其他中后衞都多。&lt;/p&gt; &lt;h3&gt;&lt;a href="https://www.skysports.com/football/news/11095/13136308/transfer-window-summer-2024-when-does-it-open-and-close-dates-and-deadline-day-for-premier-league-efl-wsl-and-more"&gt;夏季转会窗口何时开启和关闭？&lt;/a&gt;&lt;/h3&gt;&lt;p&gt;"(《世界人权宣言》)&lt;a href="https://www.skysports.com/football/news/11095/13136308/transfer-window-summer-2024-when-does-it-open-and-close-dates-and-deadline-day-for-premier-league-efl-wsl-and-more" target="_blank"&gt;&lt;strong&gt;2024 年夏季转会窗口&lt;/strong&gt;&lt;/a&gt;英超联赛将于 6 月 14 日星期五正式开幕，即 2024 年欧洲杯开始的同一天。&lt;/p&gt;&lt;p&gt;该窗口将于英国时间 8 月 30 日晚上 11 点关闭。&lt;/p&gt;&lt;p&gt;英超联赛提前了截止日期，以便与欧洲其他主要联赛联系起来。&lt;/p&gt;</summary>
        <published>2024-05-29T10:30:00+00:00</published>
    </entry>
    <entry>
        <id>https://www.skysports.com/football/news/11095/13144651/gareth-southgate-stays-committed-to-england-amid-manchester-united-season-review</id>
        <title>索斯盖特在曼联审查中仍致力于英格兰</title>
        <updated>2024-05-28T18:04:00+00:00</updated>
        <link href="https://www.skysports.com/football/news/11095/13144651/gareth-southgate-stays-committed-to-england-amid-manchester-united-season-review"/>
        <summary type="html">&lt;p&gt;有人向加雷斯·索斯盖特询问了有一天成为曼联主帅的可能性，但他没有兴趣参与任何与他作为英格兰主帅的工作无关的谈话。&lt;/p&gt;&lt;p&gt;索斯盖特唯一的关注点是带领三狮军团参加下个月在德国举行的欧洲锦标赛，该锦标赛将于 6 月 14 日开始，两天后英格兰队将迎战塞尔维亚队。&lt;/p&gt;&lt;div class="sdc-site-outbrain sdc-site-outbrain--AR_5"&gt;
&lt;div class="OUTBRAIN"&gt;
&lt;/div&gt;
&lt;/div&gt;
&lt;p&gt;尽管索斯盖特与英格兰队的合同将于 12 月到期，但在世界杯结束后英足总希望他留下来，才会对他的未来做出决定。&lt;/p&gt;&lt;ul&gt;&lt;li&gt;&lt;strong&gt;&lt;a href="https://www.skysports.com/football/news/11095/13143930/whats-next-for-manchester-united-and-erik-ten-hag-the-key-questions-answered"&gt;曼联和埃里克十哈格的下一步是什么？&lt;/a&gt;&lt;/strong&gt;&lt;/li&gt;&lt;li&gt;&lt;strong&gt;&lt;a href="https://www.skysports.com/football/news/11095/13020967/englands-euro-2024-fixtures-dates-and-potential-route-for-tournament-in-germany"&gt;英格兰 2024 年欧洲杯赛程和路线&lt;/a&gt; &lt;/strong&gt;&lt;/li&gt;&lt;li&gt;&lt;strong&gt;&lt;a href="https://www.skysports.com/football/news/11095/12955701/euro-2024-fixtures-schedule-teams-venues-all-you-need-to-know-about-next-summers-tournament-in-germany"&gt;2024 年欧洲杯：谁有资格以及何时获得资格？&lt;/a&gt;&lt;/strong&gt;&lt;/li&gt;&lt;li&gt;&lt;strong&gt;&lt;a href="https://www.nowtv.com/watch-sky-sports-online?DCMP=ilc_skysports_nc_articlelink"&gt;通过 NOW 直播英超联赛&lt;/a&gt;| &lt;a href="https://www.sky.com/tv/sports?dcmp=ssf.com_bul_shop"&gt;获取天空体育&lt;/a&gt;&lt;/strong&gt;&lt;/li&gt;&lt;/ul&gt;&lt;p&gt;上个月被问及他的未来时，索斯盖特&lt;a href="https://www.skysports.com/football/news/12016/13099973/gareth-southgate-says-he-won-t-speak-to-clubs-about-jobs-before-euro-2024-amid-links-to-manchester-united"&gt;明确表示他在工作期间不会与任何人交谈。&lt;/a&gt;&lt;/p&gt;
&lt;p&gt;索斯盖特与英力士体育总监戴夫·布雷斯福德爵士关系良好，他在英足总与即将上任的曼联体育总监丹·阿什沃斯密切合作。&lt;/p&gt;
&lt;p&gt;曼联目前正在进行赛季回顾，其中包括决定是否让埃里克·十·哈格继续担任主教练。&lt;/p&gt;&lt;div class="ad ad--teads"&gt;
&lt;div class="sdc-site-au"&gt;
&lt;div&gt;&lt;/div&gt;
&lt;div class="sdc-site-au__teads" id="in-article-desktop"&gt;&lt;/div&gt;
&lt;/div&gt;
&lt;/div&gt;
&lt;h3&gt;&lt;strong&gt;谁是替代十女巫的人选？&lt;/strong&gt;&lt;/h3&gt;&lt;p&gt;&lt;em&gt;天空体育新闻的梅丽莎·雷迪：&lt;/em&gt;&lt;/p&gt;
&lt;p&gt;"&lt;strong&gt;毛里西奥·波切蒂诺&lt;/strong&gt;和&lt;strong&gt;托马斯·图切尔&lt;/strong&gt;，过去都曾认真考虑过这两个人。&lt;em&gt;天空体育&lt;/em&gt;上个月报道称，一位消息人士指出，在拜仁慕尼黑宣布离开后，没有其他大俱乐部愿意签下这位德国人，对此持保留态度。&lt;/p&gt;&lt;p&gt;「除了美因茨之外，决策者们也没有逃过这一点，图赫尔的所有任期都只有两年左右或不到两年。&lt;/p&gt;
&lt;p&gt;「切尔西的情况促使曼联采取了行动。波切蒂诺的到来出人意料，他在俱乐部长期以来一直拥有大量的崇拜者，但也受到布雷尔斯福德、吉姆·拉特克利夫爵士和亚历克斯·弗格森爵士的高度评价。&lt;/p&gt;&lt;p&gt;「切尔西的兴趣在于&lt;strong&gt;基兰·麦肯纳&lt;/strong&gt;还敦促曼联采取行动并与他的代表会面，然而&lt;em&gt;天空体育新闻&lt;/em&gt;据了解，他将与伊普斯维奇签订一份长期合同。&lt;/p&gt;&lt;p&gt;「他对曼联的强烈亲和力和深入了解，再加上他在伊普斯维奇的出色工作，使他成为一个有吸引力的选择，尽管有风险。据了解，如果他同时收到斯坦福桥和老特拉福德的报价，他不会选择斯坦福桥。&lt;/p&gt;
&lt;p&gt;"&lt;strong&gt;托马斯·弗兰克&lt;/strong&gt;还吸引了曼联的转变，将英冠联赛中的进攻机器打造为一支更具防守意识、更有效的球队，以巩固英超地位，他与支持者的融洽关系，以及伊万·托尼、大衞·拉亚和埃兹里·孔萨等球员的进步，以及&lt;/p&gt;</summary>
        <published>2024-05-28T18:04:00+00:00</published>
    </entry>
    <entry>
        <id>https://www.skysports.com/football/news/11095/13143812/premier-league-transfers-data-insights-on-what-each-club-needs-in-summer-window</id>
        <title>英超转会：数据显示每个俱乐部需要什么</title>
        <updated>2024-05-28T08:00:00+00:00</updated>
        <link href="https://www.skysports.com/football/news/11095/13143812/premier-league-transfers-data-insights-on-what-each-club-needs-in-summer-window"/>
        <summary type="html">&lt;p&gt;每支英超球队在夏季转会窗口都需要什么？&lt;em&gt;天空体育&lt;/em&gt; &lt;/p&gt;&lt;h3&gt;兵工厂&lt;/h3&gt;&lt;p&gt;连续几个赛季屈居曼城亚军的球队几乎找不到任何缺陷。&lt;/p&gt;&lt;div class="sdc-site-outbrain sdc-site-outbrain--AR_5"&gt;
&lt;div class="OUTBRAIN"&gt;
&lt;/div&gt;
&lt;/div&gt;
&lt;p&gt;本赛季，凯·哈弗茨在最后 14 场联赛中打进 9 粒进球，前景光明，但埃迪·恩凯蒂亚和加布里埃尔·热苏斯在总共 54 场联赛中的进球数未能达到两位数，一月份后都没有进球。&lt;/p&gt;&lt;ul&gt;&lt;li&gt;&lt;strong&gt;&lt;a href="https://www.skysports.com/football/news/11095/13136308/transfer-window-summer-2024-when-does-it-open-and-close-dates-and-deadline-day-for-premier-league-efl-wsl-and-more"&gt;2024 年夏季转会窗口日期&lt;/a&gt;&lt;/strong&gt;&lt;/li&gt;&lt;li&gt;&lt;a href="https://www.skysports.com/transfer-centre"&gt;&lt;strong&gt;换乘中心现场直播！&lt;/strong&gt;&lt;/a&gt;&lt;/li&gt;&lt;li&gt;&lt;strong&gt;&lt;a href="https://www.skysports.com/football/news/11700/13136992/premier-league-2024-25-season-start-date-schedule-fixture-release-international-breaks-and-final-day"&gt;英超联赛 2024/25 赛季日期、赛程、赛程发布&lt;/a&gt;&lt;/strong&gt;&lt;/li&gt;&lt;/ul&gt;&lt;h3&gt;阿斯顿维拉&lt;/h3&gt;&lt;p&gt;阿斯顿维拉将自 1982/83 赛季衞冕欧洲冠军以来首次参加下赛季的欧洲精英赛事。&lt;/p&gt;&lt;p&gt;他们的防守记录肯定需要改进才能再次达到这样的高度。&lt;/p&gt;
&lt;p&gt;只有诺维奇——在首届英超联赛中获得第三名——曾经进入前四名并且失球数更多。&lt;/p&gt;&lt;div class="ad ad--teads"&gt;
&lt;div class="sdc-site-au"&gt;
&lt;div&gt;&lt;/div&gt;
&lt;div class="sdc-site-au__teads" id="in-article-desktop"&gt;&lt;/div&gt;
&lt;/div&gt;
&lt;/div&gt;
&lt;h3&gt;伯恩茅斯&lt;/h3&gt;&lt;p&gt;伯恩茅斯本赛季获得 48 分，创俱乐部纪录。&lt;/p&gt;
&lt;p&gt;下赛季的成功可能取决于留住头号得分手多米尼克·索兰克以及任何潜在的新人。&lt;/p&gt;&lt;p&gt;他的 19 个联赛进球不仅是任何队友的两倍多，而且如果没有这些进球，伯恩茅斯将在积分榜上排名第 17 位，距离降级仅差 6 分。&lt;/p&gt; &lt;h3&gt;布伦特福德&lt;/h3&gt;&lt;p&gt;本赛季是布伦特福德在三个英超赛季中成绩最低（第 16 位）和总积分最低（第 39 位）的赛季——他们在最后 24 场联赛中只赢了 5 场。&lt;/p&gt;&lt;p&gt;在赛季前半段，他们看到了没有护身符伊万·托尼的生活——这可能会成为今年夏天的永久特色，而他的合同只剩下一年了。&lt;/p&gt;&lt;p&gt;托马斯·弗兰克（Thomas Frank）行动迅速，二月份确认签下巴西前锋伊戈尔·蒂亚戈（Igor Thiago）。&lt;/p&gt; &lt;h3&gt;布莱顿&lt;/h3&gt;&lt;p&gt;罗伯托·德泽尔比的离开使俱乐部内部保持了惯例的季节性流失。&lt;/p&gt;&lt;p&gt;在过去的两年里，布莱顿的关键球员马克·库库雷拉、伊夫·比苏马、莱安德罗·特罗萨德、亚历克西斯·麦克·阿利斯特和莫伊塞斯·凯塞多都以高额费用离开，格雷厄姆·波特也于 2022 年 9 月效仿。&lt;/p&gt;&lt;p&gt;不断的变化也反映在了球场上：他们对首发阵容的调整比分区内任何其他球队都多了 36 次——仅落后英超纪录一次。&lt;/p&gt;&lt;p&gt;下赛季的稳定性和一致性可能与任何新签约一样重要。&lt;/p&gt; &lt;h3&gt;切尔西&lt;/h3&gt;&lt;p&gt;切尔西在最后三个月中表现出了进步的迹象——最后 15 场联赛中只输掉了一场——但如果前四是一个现实的目标，他们的年轻球队将受益于经验的注入。&lt;/p&gt; &lt;p&gt;现年 39 岁的蒂亚戈·席尔瓦将在 6 月底合同到期后跟随毛里西奥·波切蒂诺离开俱乐部。&lt;/p&gt;&lt;p&gt;尽管巴西人首发了 27 场比赛，但蓝军本赛季的平均首发阵容是该分区中最年轻的。&lt;/p&gt; &lt;h3&gt;水晶宫&lt;/h3&gt;&lt;p&gt;当奥利弗·格拉斯纳二月份被任命时，水晶宫在之前的 17 场联赛中输掉了 10 场。&lt;/p&gt;&lt;p&gt;这一转变主要归功于迈克尔·奥利塞、埃贝雷奇·埃兹和让·菲利普·马特塔的出色表现，他们在奥地利人麾下的 13 场比赛中总共打进了 23 个联赛进球。&lt;/p&gt;&lt;p&gt;保留他们的进攻三人组并保持奥利斯的健康可能是老鹰队今年夏天最好的生意。&lt;/p&gt; &lt;h3&gt;埃弗顿&lt;/h3&gt;&lt;p&gt;如果没有扣掉七分，肖恩·戴奇的球队就已经接近上半区了——在最后六场联赛中赢了四场。&lt;/p&gt;&lt;p&gt;然而，如果要避免连续第四次保级混战，他们对定位球的依赖就需要解决。&lt;/p&gt; &lt;p&gt;太妃糖队在比赛中的进球数比垫底的谢菲尔德联队少五个，减轻德怀特·麦克尼尔的负担，因为他们唯一自然的、创造性的出路应该是优先考虑的事情。&lt;/p&gt; &lt;h3&gt;富勒姆&lt;/h3&gt;&lt;p&gt;富勒姆在最后九场英超比赛中仅取得两场胜利，欧洲足球的希望破灭了。&lt;/p&gt; &lt;p&gt;如果富勒姆下赛季想要重返上半区，一些年轻的球员和深度不会出现问题。&lt;/p&gt; &lt;h3&gt;伊普斯威奇&lt;/h3&gt;&lt;p&gt;连续从联赛升级到英超意味着波特曼路队下赛季的期望可能是现实的：他们目前的球队中只有六名球员之前曾在英格兰顶级联赛踢过球。&lt;/p&gt;&lt;p&gt;卢顿本赛季的一个关键问题是缺乏这个级别的经验，基兰·麦肯纳今年夏天应该明智地解决这个问题。&lt;/p&gt; &lt;h3&gt;莱斯特&lt;/h3&gt;&lt;p&gt;狐狸队在 2022/23 赛季意外降级主要是由于他们的防守问题。&lt;/p&gt;&lt;p&gt;然而，他们那个赛季的两名顶级得分手——哈维·巴恩斯和詹姆斯·麦迪逊——去年夏天离开了，第三位得分手凯莱奇·伊希纳乔今年夏天合同到期。&lt;/p&gt;&lt;p&gt;这个负担将落在杰米·瓦尔迪身上，但是，37 岁的瓦尔迪在上一次英超联赛中苦苦挣扎之后，似乎必须有一名有保证的射手，因为莱斯特城拥有本赛季英冠联赛中最好的防守。&lt;/p&gt; &lt;h3&gt;利物浦&lt;/h3&gt;&lt;p&gt;尤尔根·克洛普在利物浦度过了八年的辉煌岁月后离开，在离开之前，安菲尔德的夏季重建就已经被吹捧。&lt;/p&gt;&lt;p&gt;在去年夏天的中场改组之后，焦点可能会集中在防守补强上：维吉尔·范戴克的未来仍然不确定，乔尔·马蒂普的合同已经到期，特伦特·亚历山大·阿诺德即将进入他目前合同的最后 12 个月，以及安迪·罗伯逊的受伤&lt;/p&gt;&lt;p&gt;他们本赛季的防守数据明显比近几年差。&lt;/p&gt; &lt;h3&gt;曼城&lt;/h3&gt;&lt;p&gt;在史无前例地连续第四次获得英格兰顶级联赛冠军后，曼城将很难在夏天之前找到任何重大缺陷。&lt;/p&gt;&lt;p&gt;由于卡尔文·菲利普斯预计将在两个平淡的赛季后离开，因此有影响力的罗德里的副手可能是一个优先事项：曼城的三场联赛失利都是在西班牙人本赛季停赛时发生的。&lt;/p&gt; &lt;h3&gt;曼联&lt;/h3&gt;&lt;p&gt;由于埃里克·十·哈格的未来仍然悬而未决，曼联在夏天不可避免的动荡可能会在球场的各个领域看到新的球员——他们在防守和进攻上都陷入困境。&lt;/p&gt;&lt;p&gt;经验丰富的拉斐尔·瓦拉内的离开将使俱乐部的后防线变得光明，尤其是在利桑德罗·马丁内斯和卢克·肖持续受到伤病困扰的情况下。&lt;/p&gt;&lt;p&gt;本赛季他们使用了 14 名不同的中后衞搭档，老将乔尼·埃文斯 (Jonny Evans) 的联赛出场次数比俱乐部中任何其他中后衞都多。&lt;/p&gt; &lt;h3&gt;新城堡&lt;/h3&gt;&lt;p&gt;对于埃迪·豪的球队本赛季来说，平衡期望和欧洲始终是一个挑战。&lt;/p&gt;
&lt;p&gt;这两个边后衞位置最近都存在问题，似乎有可能对后防线进行更新——特别是如果他们能够保留布鲁诺·吉马良斯和亚历山大·伊萨克的服务。&lt;/p&gt;&lt;h3&gt;诺丁汉森林&lt;/h3&gt;&lt;p&gt;努诺·桑托·埃斯皮里托在狼队令人印象深刻的防守记录帮助诺丁汉森林在解雇了史蒂夫·库珀后在赛季中期任命了他。&lt;/p&gt;&lt;p&gt;比利时人自从加盟森林队以来一直表现不佳，本赛季只有队友奥德西斯·弗拉霍迪莫斯和布莱顿队的贾森·斯蒂尔的扑救率较低。&lt;/p&gt;&lt;p&gt;棍棒之间的一致存在将有助于补充在最后冲刺阶段开始凝结的进攻。&lt;/p&gt; &lt;h3&gt;南安普敦&lt;/h3&gt;&lt;p&gt;南安普顿本赛季仅在五场英冠比赛中未能进球，这是该分区的最佳战绩。&lt;/p&gt;&lt;p&gt;圣徒队经常依靠强大的进攻来挽救在失球数和不失球数方面排名中游的防守。&lt;/p&gt; &lt;h3&gt;托特纳姆热刺&lt;/h3&gt;&lt;p&gt;托特纳姆热刺队又迎来了一个虚假的曙光，在安吉·波斯特科格鲁的带领下，热刺队在 10 场英超联赛中保持不败，位居积分榜榜首。&lt;/p&gt;&lt;p&gt;随着赛季的进行，他们在 11 月主场 4-1 输给切尔西的比赛中失利已经成为常态。&lt;/p&gt;&lt;p&gt;如果他们想要在下赛季争夺前四名，就需要更好的中场保护和足够的防守深度。&lt;/p&gt; &lt;h3&gt;西汉姆&lt;/h3&gt;&lt;p&gt;由于卢卡斯·帕奎塔可能因涉嫌违反投注规则而面临多年禁赛，因此更换这位巴西国脚的创造力至关重要。&lt;/p&gt;&lt;p&gt;帕奎塔本赛季的直传球数量是任何队友的六倍，并且毫无疑问是他们在空战中最有力的创造者。&lt;/p&gt;&lt;p&gt;本赛季只有三支降级球队的丢球数超过西汉姆联，而帕奎塔的技术是他们获得第九名的关键因素之一。&lt;/p&gt; &lt;h3&gt;狼队&lt;/h3&gt;&lt;p&gt;加里·奥尼尔稳定但平淡的处子赛季以失望告终：他的球队在最后 10 场联赛中只赢了一场。&lt;/p&gt;&lt;p&gt;对于一支拥有佩德罗·内托、马修斯·库尼亚和黄熙灿才华横溢的球队来说，进球很少成为问题，但如果他们想要在比赛结束后扭转糟糕的状态，那么在最后 17 场比赛中只保持一场不失球的防守就需要努力。&lt;/p&gt; &lt;h2&gt;夏季转会窗口何时开启和关闭？&lt;/h2&gt;&lt;p&gt;"(《世界人权宣言》)&lt;a href="https://www.skysports.com/football/news/11095/13136308/transfer-window-summer-2024-when-does-it-open-and-close-dates-and-deadline-day-for-premier-league-efl-wsl-and-more"&gt;2024 年夏季转会窗口&lt;/a&gt;英超联赛将于 6 月 14 日星期五正式开幕，即 2024 年欧洲杯开始的同一天。&lt;/p&gt;&lt;p&gt;该窗口将于英国时间 8 月 30 日晚上 11 点关闭。&lt;/p&gt;&lt;p&gt;英超联赛提前了截止日期，以便与欧洲其他主要联赛联系起来。&lt;/p&gt;</summary>
        <published>2024-05-28T08:00:00+00:00</published>
    </entry>
    <entry>
        <id>https://www.skysports.com/football/news/11707/13144042/kieran-mckenna-to-stay-at-ipswich-town-after-interest-from-manchester-united-chelsea-and-brighton</id>
        <title>麦肯纳留在伊普斯维奇并签署新的长期合同</title>
        <updated>2024-05-27T18:50:00+00:00</updated>
        <link href="https://www.skysports.com/football/news/11707/13144042/kieran-mckenna-to-stay-at-ipswich-town-after-interest-from-manchester-united-chelsea-and-brighton"/>
        <summary type="html">&lt;p&gt;在吸引了曼联、切尔西和布莱顿的兴趣后，基兰·麦肯纳将留在伊普斯维奇并签署一份新的长期合同。&lt;/p&gt;&lt;p&gt;这位 38 岁的教练 22 年来带领伊普斯维奇连续两届 EFL 晋级，并在波特曼路首次征战英超，但下赛季他是否会留在俱乐部仍存在疑问。&lt;/p&gt;&lt;div class="sdc-site-outbrain sdc-site-outbrain--AR_5"&gt;
&lt;div class="OUTBRAIN"&gt;
&lt;/div&gt;
&lt;/div&gt;
&lt;p&gt;&lt;em&gt;天空体育新闻&lt;/em&gt;透露麦肯纳是罗伯托·德泽尔比离开后布莱顿空缺职位的候选人，&lt;a href="https://www.skysports.com/football/news/11667/13142093/kieran-mckenna-manchester-united-meet-with-representatives-of-ipswich-boss-amid-chelsea-interest"&gt;而曼联官员会见了伊普斯维奇主帅的代表&lt;/a&gt;.&lt;/p&gt;&lt;ul&gt;&lt;li&gt;&lt;strong&gt;&lt;a href="https://www.skysports.com/football/news/11707/13141696/kieran-mckenna-why-ipswich-manager-is-in-demand-this-summer-amid-links-to-brighton-chelsea-and-manchester-united"&gt;为什么伊普斯维奇的基兰·麦肯纳很受欢迎&lt;/a&gt;&lt;/strong&gt;&lt;/li&gt;&lt;li&gt;&lt;a href="https://www.skysports.com/transfer-centre"&gt;&lt;strong&gt;换乘中心现场直播！&lt;/strong&gt;&lt;/a&gt;&lt;/li&gt;&lt;li&gt;&lt;strong&gt;&lt;a href="https://www.skysports.com/football/news/11700/13136992/premier-league-2024-25-season-start-date-schedule-fixture-release-international-breaks-and-final-day"&gt;英超联赛 2024/25 赛季日期、赛程、赛程发布&lt;/a&gt;&lt;/strong&gt;&lt;/li&gt;&lt;li&gt;&lt;strong&gt;&lt;a href="https://www.nowtv.com/watch-sky-sports-online?DCMP=ilc_skysports_nc_articlelink"&gt;通过 NOW 直播英超联赛&lt;/a&gt;| &lt;a href="https://www.sky.com/tv/sports?dcmp=ssf.com_bul_shop"&gt;获取天空体育&lt;/a&gt;&lt;/strong&gt;&lt;/li&gt;&lt;/ul&gt;&lt;p&gt;麦肯纳也曾与接替切尔西的毛里西奥·波切蒂诺有关，但周日通过电话被告知俱乐部正在寻找其他人选。&lt;/p&gt;&lt;p&gt;&lt;em&gt;天空体育新闻&lt;/em&gt;另悉，伊普斯维奇镇大股东埃德·施瓦茨于上周末从美国飞抵英国，与俱乐部首席执行官马克·阿什顿和麦肯纳进行会谈。&lt;/p&gt;
&lt;p&gt;现在，围绕伊普斯维奇主帅未来的猜测即将结束，麦肯纳准备延长他在波特曼路的停留时间，这对新晋级的俱乐部来说将是一个重大推动。&lt;/p&gt;&lt;div class="ad ad--teads"&gt;
&lt;div class="sdc-site-au"&gt;
&lt;div&gt;&lt;/div&gt;
&lt;div class="sdc-site-au__teads" id="in-article-desktop"&gt;&lt;/div&gt;
&lt;/div&gt;
&lt;/div&gt;
&lt;p&gt;伊普斯维奇于 2021 年任命麦肯纳为球队主教练，在他执教的第一个完整赛季中，他带领伊普斯维奇从甲级联赛升级至英冠联赛。&lt;/p&gt;
&lt;p&gt;随后，伊普斯维奇在自 2002 年以来首次尝试进入英超联赛时，连续第二次晋级。&lt;/p&gt;
&lt;h3&gt;麦肯纳如何获得双重晋升&lt;/h3&gt;
&lt;p&gt;&lt;em&gt;天空体育的亚当·威廉姆斯：&lt;/em&gt;&lt;/p&gt;&lt;p&gt;2021 年 12 月 16 日，伊普斯维奇确认 35 岁的曼联助理教练麦肯纳已被任命为新任主教练，合同为期三年半。&lt;/p&gt;&lt;p&gt;「基兰是谁？」&lt;/p&gt;&lt;p&gt;麦肯纳一开始说话轻声细语，但在与媒体的接触中却有条不紊、清晰而诚实，粉丝们很快就对麦肯纳离开更傲慢、有时甚至是专横的前任表示欢迎。&lt;/p&gt;
&lt;p&gt;事实证明，在那个赛季剩余的时间里，升级是一项艰巨的任务，因为伊普斯维奇排名第 11，但麦肯纳已经在他执教的第一个完整赛季中打好了铁杆。&lt;/p&gt;&lt;p&gt;弗雷迪·拉达波、多姆·鲍尔和莱夫·戴维斯将成为夏季引人瞩目的签约球员，从一开始，很明显，该赛季争夺联赛冠军的竞争将异常激烈。&lt;/p&gt;&lt;p&gt;普利茅斯始终保持着节奏，而伊普斯维奇、谢菲尔德星期三和巴恩斯利则试图跟上。&lt;/p&gt;&lt;p&gt;2 月 14 日与布里斯托尔流浪者队互交白卷，滑落至第四名后，可以理解的是，人们的想法转向了另一个令人失望的赛季，镇队落后前两名 8 分。&lt;/p&gt;
&lt;p&gt;但一月份的转会窗口已经引进了四名关键球员：乔治·赫斯特、哈里·克拉克、马西莫·隆戈和内森·布罗德海德。&lt;/p&gt;&lt;p&gt;回到第二级别联赛的感觉很好，随着本赛季的开始，许多球迷希望赢得的比赛多于输掉的比赛，并以此为契机，在过去 18 个月的良好工作基础上继续前进。&lt;/p&gt;&lt;p&gt;但 46 场比赛之后，他们重返顶级联赛。&lt;/p&gt;
&lt;h3&gt;&lt;a href="https://www.skysports.com/football/news/11095/13141696/kieran-mckenna-why-ipswich-manager-is-in-demand-this-summer-amid-links-to-brighton-chelsea-and-manchester-united"&gt;分析：为什么伊普斯维奇的麦肯纳是炙手可热的主教练&lt;/a&gt;&lt;/h3&gt;
&lt;p&gt;麦肯纳今年夏天一直是通缉犯——出于各种正当理由。&lt;/p&gt;&lt;p&gt;&lt;a href="http://www.skysports.com/football/news/11095/13141696/kieran-mckenna-why-ipswich-manager-is-in-demand-this-summer-amid-links-to-brighton-chelsea-and-manchester-united"&gt;瓦&lt;/a&gt;&lt;a href="https://www.skysports.com/football/news/11095/13141696/kieran-mckenna-why-ipswich-manager-is-in-demand-this-summer-amid-links-to-brighton-chelsea-and-manchester-united"&gt;为什么他是一位如此受欢迎的经理？&lt;em&gt;天空体育&lt;/em&gt;看看这里的原因......&lt;/a&gt;&lt;/p&gt;</summary>
        <published>2024-05-27T18:50:00+00:00</published>
    </entry>
    <entry>
        <id>https://www.skysports.com/football/news/11095/13143930/whats-next-for-manchester-united-and-erik-ten-hag-the-key-questions-answered</id>
        <title>曼联和十哈格的下一步是什么？</title>
        <updated>2024-05-27T12:27:00+00:00</updated>
        <link href="https://www.skysports.com/football/news/11095/13143930/whats-next-for-manchester-united-and-erik-ten-hag-the-key-questions-answered"/>
        <summary type="html">&lt;p&gt;天空体育新闻的资深记者梅丽莎·雷迪回答了曼联面临的关键问题，以及他们对埃里克·十·哈格在俱乐部的时光的回顾。&lt;/p&gt;&lt;h3&gt;&lt;strong&gt;曼联对十哈格任期的审查发生了什么？&lt;/strong&gt;&lt;/h3&gt;&lt;p&gt;这是一个非常有趣的元素。&lt;/p&gt;&lt;div class="sdc-site-outbrain sdc-site-outbrain--AR_5"&gt;
&lt;div class="OUTBRAIN"&gt;
&lt;/div&gt;
&lt;/div&gt;
&lt;p&gt;Jason Wilcox 自一个多月前正式加入技术总监以来，最重要的任务之一就是对比赛模型、训练课程、教练组和更衣室之间的关系以及他们如何与其他领域互动进行更全面的审核。&lt;/p&gt;&lt;ul&gt;&lt;li&gt;&lt;strong&gt;&lt;a href="https://www.skysports.com/football/live-blog/11095/13025492/man-utd-transfer-news-and-rumours-erik-ten-hag-wants-future-decided-quickly-as-club-prepare-review"&gt;埃里克十哈格希望曼联的未来尽快决定&lt;/a&gt;&lt;/strong&gt;&lt;/li&gt;&lt;li&gt;&lt;a href="https://www.skysports.com/transfer-centre"&gt;&lt;strong&gt;换乘中心现场直播！&lt;/strong&gt;&lt;/a&gt;&lt;/li&gt;&lt;li&gt;&lt;strong&gt;&lt;a href="https://www.skysports.com/football/news/11700/13136992/premier-league-2024-25-season-start-date-schedule-fixture-release-international-breaks-and-final-day"&gt;英超联赛 2024/25 赛季日期、赛程、赛程发布&lt;/a&gt;&lt;/strong&gt;&lt;/li&gt;&lt;li&gt;&lt;strong&gt;&lt;a href="https://www.nowtv.com/watch-sky-sports-online?DCMP=ilc_skysports_nc_articlelink"&gt;通过 NOW 直播英超联赛&lt;/a&gt;| &lt;a href="https://www.sky.com/tv/sports?dcmp=ssf.com_bul_shop"&gt;获取天空体育&lt;/a&gt;&lt;/strong&gt;&lt;/li&gt;&lt;/ul&gt;
&lt;p&gt;对十哈格咒语的审查早已在进行中，主教练透露，审查以及他与曼联高层的讨论已经发生。&lt;/p&gt;&lt;p&gt;尽管已经掌握了所有信息，并且十巫婆相信评估已经完成，但俱乐部表示他们的审查将&lt;em&gt;现在&lt;/em&gt;发生。&lt;/p&gt;
&lt;p&gt;有一种感觉是，在意识到与路易斯·范加尔被解雇的比较后，曼联不想破坏足总杯决赛的庆祝活动，也不想被指责冷酷无情。&lt;/p&gt;&lt;div class="ad ad--teads"&gt;
&lt;div class="sdc-site-au"&gt;
&lt;div&gt;&lt;/div&gt;
&lt;div class="sdc-site-au__teads" id="in-article-desktop"&gt;&lt;/div&gt;
&lt;/div&gt;
&lt;/div&gt;
&lt;p&gt;有足够的证据表明俱乐部在过去几个月公开搞乱了他们的继任计划——拜仁就是主要例子——而曼联不想重蹈覆辙。&lt;/p&gt;
&lt;h3&gt;&lt;strong&gt;曼联为何在审查期间与潜在继任者会面？&lt;/strong&gt;&lt;/h3&gt;&lt;p&gt;他们会说他们只是在探索选择并进行尽职调查。&lt;/p&gt;&lt;p&gt;新的领导团队希望自己挑选自己的经理，这是完全正常和可以理解的，但与十女巫关系密切的人对缺乏沟通和「个人和职业尊重」感到恼火。&lt;/p&gt;&lt;h3&gt;&lt;strong&gt;那么这些选择中有哪些人呢？&lt;/strong&gt;&lt;/h3&gt;
&lt;p&gt;&lt;strong&gt;毛里西奥·波切蒂诺&lt;/strong&gt;和&lt;strong&gt;托马斯·图切尔&lt;/strong&gt;，过去都曾认真考虑过这两个人。&lt;em&gt;天空体育&lt;/em&gt;上个月报道称，一位消息人士指出，在拜仁慕尼黑宣布离开后，没有其他大俱乐部愿意签下这位德国人，对此持保留态度。&lt;/p&gt;&lt;p&gt;决策者们也没有逃过这一点，除了美因茨之外，图赫尔的所有任期都只有两年左右或不到两年。&lt;/p&gt;&lt;p&gt;切尔西的情况促使曼联采取了行动。&lt;/p&gt;
&lt;p&gt;切尔西的兴趣&lt;strong&gt;基兰·麦肯纳&lt;/strong&gt;还敦促曼联采取行动并与他的代表会面，然而&lt;em&gt;天空体育新闻&lt;/em&gt;据了解，他将与伊普斯维奇签订一份长期合同。&lt;/p&gt;&lt;p&gt;他对曼联的强烈亲和力和深入了解，再加上他在伊普斯维奇的出色工作，使他成为一个有吸引力但有风险的选择。&lt;/p&gt;&lt;p&gt;&lt;strong&gt;托马斯·弗兰克&lt;/strong&gt;还吸引了曼联的转变，将英冠联赛中的进攻机器打造为一支更具防守意识、更有效的球队，以巩固英超地位，他与支持者的融洽关系，以及伊万·托尼、大衞·拉亚和埃兹里·孔萨等球员的进步，以及&lt;/p&gt;&lt;h3&gt;&lt;strong&gt;但这些都是截然不同的经理？&lt;/strong&gt;&lt;/h3&gt;&lt;p&gt;确实如此，这使得我们很难确定英力士所追求的形象。&lt;/p&gt;&lt;p&gt;正如几个月前所知，夹伤的可能性&lt;strong&gt;加雷斯·索斯盖特&lt;/strong&gt;在欧洲杯探索之后，来自英格兰的候选人让-克洛德·布兰克广泛的联系簿被用来了解其他候选人。&lt;/p&gt;&lt;p&gt;人们预计，鉴于他的可用性以及瓜迪奥拉声称他是「过去 20 年来最有影响力的教练之一」，他将与&lt;strong&gt;罗伯托·德泽比&lt;/strong&gt;.&lt;/p&gt;&lt;p&gt;我应该指出，曼联有很多人与十哈格密切合作，并希望他继续下去。&lt;/p&gt; &lt;h3&gt;&lt;strong&gt;足总杯决赛的胜利能否拯救十女巫？&lt;/strong&gt;&lt;/h3&gt;&lt;p&gt;曼联高层一直坚持认为，关于十黑格的决定将基于他的整个执教时间，而不是周六的比赛结果。&lt;/p&gt;
&lt;h3&gt;&lt;strong&gt;但如果这是他负责的最后一幕，那还有一段路要走吗？！&lt;/strong&gt;&lt;/h3&gt;&lt;p&gt;是的，又获得了一枚奖杯——并且克服重重困难，阻止曼城获得两双。&lt;/p&gt;&lt;p&gt;这不仅仅是结果，更是曼联近乎完美的表现。&lt;/p&gt;&lt;p&gt;这是十哈格将他们打造成「世界上最好的过渡球队」的愿景的一个小窗口，也指出了主教练整个赛季一直在说的话：稳固的中衞伙伴关系和可供选择的球员将产生重大的影响。&lt;/p&gt;&lt;p&gt;在人的层面上，场景也很精彩。&lt;/p&gt;
&lt;h3&gt;&lt;strong&gt;接下来发生什么？&lt;/strong&gt;&lt;/h3&gt;&lt;p&gt;曼联正在与其他教练的代表进行接触这一事实比其他任何事情都更能说明问题。&lt;/p&gt;&lt;p&gt;但他们能否与真正想要的候选人达成协议，这是否具有经济意义，并且他们会得到支持者的支持吗？&lt;/p&gt;&lt;p&gt;这些都是考虑因素，如果他们不能解决这个问题，也许十女巫仍会继续发挥作用。&lt;/p&gt;</summary>
        <published>2024-05-27T12:27:00+00:00</published>
    </entry>
    <entry>
        <id>https://www.skysports.com/football/news/11700/13136992/premier-league-2024-25-season-start-date-schedule-fixture-release-international-breaks-and-final-day</id>
        <title>英超联赛 2024/25 赛季日期、赛程、赛程发布</title>
        <updated>2024-05-26T16:00:00+00:00</updated>
        <link href="https://www.skysports.com/football/news/11700/13136992/premier-league-2024-25-season-start-date-schedule-fixture-release-international-breaks-and-final-day"/>
        <summary type="html">&lt;p&gt;已经期待 2024/25 赛季英超联赛了吗？&lt;/p&gt;&lt;p&gt;新赛季将于 2023/24 赛季结束后仅 90 天开始，新的球队、球衣和球员以及比赛都会恢复。&lt;/p&gt;&lt;div class="sdc-site-outbrain sdc-site-outbrain--AR_5"&gt;
&lt;div class="OUTBRAIN"&gt;
&lt;/div&gt;
&lt;/div&gt;
&lt;p&gt;从重大赛事公告到国际比赛日，您需要了解的一切都在这。&lt;/p&gt;&lt;ul&gt;&lt;li&gt;&lt;strong&gt;&lt;a href="https://www.nowtv.com/watch-sky-sports-online?DCMP=ilc_skysports_nc_articlelink"&gt;通过 NOW 直播英超联赛&lt;/a&gt;| &lt;a href="https://www.sky.com/tv/sports?dcmp=ssf.com_bul_shop"&gt;获取天空体育&lt;/a&gt;&lt;/strong&gt;&lt;/li&gt;&lt;li&gt;&lt;a href="https://www.skysports.com/transfer-centre"&gt;&lt;strong&gt;换乘中心现场直播！&lt;/strong&gt;&lt;/a&gt;&lt;/li&gt;&lt;li&gt;&lt;a href="https://www.skysports.com/football/news/11095/13136937/premier-league-pre-season-friendlies-fixtures-results-2024-summer-tours-training-in-usa-asia-australia-and-more"&gt;&lt;strong&gt;2024 年英超联赛季前友谊赛&lt;/strong&gt;&lt;/a&gt;&lt;/li&gt;&lt;li&gt;&lt;a href="https://www.skysports.com/football/live-blog/11095/13129903/football-kits-2024-25-premier-league-efl-wsl-shirts-strips-and-retro-fits"&gt;&lt;strong&gt;2024/25 赛季新英超球衣&lt;/strong&gt;&lt;/a&gt;&lt;/li&gt;&lt;li&gt;&lt;strong&gt;&lt;a href="https://www.sky.com/tv/sports?dcmp=ssf.com_bul_shop"&gt;获取天空体育&lt;/a&gt; | &lt;a href="https://www.skysports.com/football/news/11677/12572660/download-the-sky-sports-app-premier-league-goals-f1-race-control-and-more-at-your-fingertips"&gt;下载天空体育应用程序&lt;/a&gt;&lt;/strong&gt;&lt;/li&gt;&lt;/ul&gt;&lt;h2&gt;2024/25 赛季英超联赛什么时候开始？&lt;/h2&gt;&lt;p&gt;2024/25 赛季英超联赛将于周末开始&lt;strong&gt;2018 年 8 月 17 日&lt;/strong&gt;.&lt;/p&gt;&lt;p&gt;该活动将持续 33 个周末、四轮周中比赛和一场银行假日比赛周。&lt;/p&gt;
&lt;p&gt;英超联赛表示，为了解决「圣诞节和新年期间赛程拥挤」的问题，将在节日比赛的三轮比赛中为球队提供更多的休息时间，在另一场比赛后的 60 小时内没有俱乐部进行比赛。&lt;/p&gt;&lt;div class="ad ad--teads"&gt;
&lt;div class="sdc-site-au"&gt;
&lt;div&gt;&lt;/div&gt;
&lt;div class="sdc-site-au__teads" id="in-article-desktop"&gt;&lt;/div&gt;
&lt;/div&gt;
&lt;/div&gt;
&lt;p&gt;与 2023 年狼队在平安夜主场迎战切尔西不同，2024 年 12 月 24 日将没有比赛。&lt;/p&gt;
&lt;h2&gt;英超赛季什么时候结束？&lt;/h2&gt;&lt;p&gt;最后一轮比赛将在&lt;strong&gt;2025 年 5 月 25 日，星期日&lt;/strong&gt;。&lt;/p&gt;&lt;h2&gt;2024/25 赛季英超联赛赛程何时发布？&lt;/h2&gt;&lt;p&gt;英超联赛全部 380 场比赛的赛程将在&lt;strong&gt;6 月 18 日星期二上午 9 点&lt;/strong&gt;.&lt;/p&gt;&lt;p&gt;去年，&lt;em&gt;天空体育&lt;/em&gt;同时确认了其首周末的现场报道选择。&lt;/p&gt;&lt;p&gt;所有英超联赛比赛的日期和开球时间可能会发生变化。&lt;/p&gt;&lt;h2&gt;哪些球队是 2024/25 赛季新晋顶级联赛球队？&lt;/h2&gt;
&lt;p&gt;&lt;a href="https://www.skysports.com/football/news/11712/13123323/leicester-promoted-to-premier-league-leeds-loss-at-qpr-confirms-foxes-immediate-return-to-the-top-flight#:~:text=Leicester%20promoted%20to%20Premier%20League,flight%20%7C%20Football%20News%20%7C%20Sky%20Sports"&gt;&lt;strong&gt;莱斯特城&lt;/strong&gt;密封促销&lt;/a&gt;从英冠回到英超第一时间询问。&lt;/p&gt;&lt;p&gt;&lt;a href="https://www.skysports.com/football/news/11688/13128758/ipswich-town-promoted-how-tractor-boys-ended-22-years-of-premier-league-exile"&gt;基兰·麦肯纳指导&lt;strong&gt;伊普斯威奇镇&lt;/strong&gt;返回顶部航班&lt;/a&gt;22 年后。&lt;/p&gt;&lt;p&gt;2024/25 赛季的阵容在冠军附加赛决赛后完成，最终由&lt;strong&gt;南安普敦。&lt;/strong&gt;&lt;/p&gt;&lt;p&gt;谢菲尔德联队、伯恩利队和卢顿队这三支 2022/23 赛季晋级的球队都直接降级回第二梯队。&lt;/p&gt;&lt;h2&gt;夏季转会窗口何时开启和关闭？&lt;/h2&gt;&lt;p&gt;"(《世界人权宣言》)&lt;a href="https://www.skysports.com/football/news/11095/13136308/transfer-window-summer-2024-when-does-it-open-and-close-dates-and-deadline-day-for-premier-league-efl-wsl-and-more"&gt;2024 年夏季转会窗口&lt;/a&gt;英超联赛将于 6 月 14 日星期五正式开幕，即 2024 年欧洲杯开始的同一天。&lt;/p&gt;&lt;p&gt;该窗口将于英国时间 8 月 30 日晚上 11 点关闭。&lt;/p&gt;&lt;p&gt;英超联赛提前了截止日期，以便与欧洲其他主要联赛联系起来。&lt;/p&gt;&lt;h2&gt;这个季节有寒假吗？&lt;/h2&gt;&lt;p&gt;赛季中期的休息时间也已从日历中删除，以便英超联赛可以在八月中旬开始。&lt;/p&gt;
&lt;p&gt;根据国际足联男子国际比赛日历，英格兰新一轮国家联赛的国际比赛日定于 2024 年 9 月 1 日至 9 日、10 月 6 日至 14 日和 11 月 10 日至 18 日。&lt;/p&gt;&lt;p&gt;另一次国际比赛日将于 2025 年 3 月 23 日至 31 日举行，届时 2026 年世界杯预选赛将开始。&lt;/p&gt;&lt;h2&gt;天空体育直播 2024/25 年英超联赛&lt;/h2&gt;&lt;p&gt;&lt;em&gt;天空体育&lt;/em&gt;将在 2024/25 赛季独家现场直播 128 场比赛 - 以及一个品牌&lt;a href="https://www.skysports.com/football/news/11661/13019562/sky-sports-to-show-215-premier-league-games-a-season-from-2025-26#:~:text=From%202025%2C%20Sky%20Sports%20will,26%20through%20to%202028%2F29."&gt;天空体育与英超联赛达成新协议&lt;/a&gt;意味着从 2025/26 年开始会有更多现场比赛。&lt;/p&gt;&lt;p&gt;从 2025 年开始，&lt;em&gt;天空体育&lt;/em&gt;在敲定新的四年协议后，将创纪录地每赛季转播至少 215 场英超联赛。&lt;/p&gt;&lt;p&gt;整个 2024/25 赛季，您可以免费观看英超联赛的比赛集锦 - 无需成为&lt;em&gt;天空体育&lt;/em&gt;订户。&lt;/p&gt;&lt;p&gt;您会发现每场英超比赛的精彩片段&lt;a href="https://www.skysports.com/football/live-blog/11095/12478403/premier-league-football-goals-and-highlights-of-every-match-in-the-2022-23-season"&gt;&lt;strong&gt;在计分中心以及&lt;strong&gt;天空体育网站&lt;/strong&gt;和&lt;strong&gt;天空体育应用程序&lt;/strong&gt;全日制毕业后不久&lt;/strong&gt;&lt;/a&gt;，或从下午 5.15 开始，周六中午开球。&lt;strong&gt;&lt;a href="https://www.youtube.com/channel/UCNAf1k0yIjyGu3k9BwAg3lg"&gt;天空体育足球 YouTube&lt;/a&gt;&lt;/strong&gt;渠道。&lt;/p&gt;&lt;p&gt;您可以在无月或日会员合同的情况下直播天空体育直播&lt;strong&gt;&lt;a href="https://www.skysports.com/football/news/11095/13056245/sky-sports-on-whatsapp-how-to-follow-our-channel-for-the-latest-news-features-and-highlights"&gt;现在——了解更多&lt;/a&gt;&lt;/strong&gt;&lt;em&gt;&lt;strong&gt; &lt;/strong&gt;&lt;/em&gt;关于即时观看英超联赛、EFL、F1、英格兰板球等赛事的现场直播。&lt;/p&gt;&lt;h3&gt;天空体育+ - 更多体育赛事，八月推出！&lt;/h3&gt;&lt;p&gt;&lt;a href="https://www.skysports.com/football/news/32461/13131189/sky-sports-launches-in-august-to-give-more-choice-to-fans-via-live-streams-app-and-new-channel"&gt;天空体育+&lt;/a&gt;将通过直播和新的专用频道为体育迷提供更多选择，无需额外费用。&lt;/p&gt;&lt;p&gt;今年 8 月推出，&lt;strong&gt;天空体育+&lt;/strong&gt;体育迷可以通过直播获得的选择数量将发生转变&lt;a href="https://www.sky.com/tv/sports?dcmp=articlelink"&gt;天空电视台&lt;/a&gt;, 流媒体服务&lt;a href="https://www.nowtv.com/watch-sky-sports-online?DCMP=ilc_skysports_nc_articlelink"&gt;现在&lt;/a&gt;以及改进后的&lt;a href="https://qrcode.skysports.com/skysports/ContentPromo"&gt;天空体育应用程序&lt;/a&gt;在移动。&lt;/p&gt;&lt;p&gt;由于 EFL、网球巡回赛和男子超级联赛的报道比以往任何时候都多，天空体育的客户今年可以享受超过 50% 的现场体育赛事。&lt;/p&gt;</summary>
        <published>2024-05-26T16:00:00+00:00</published>
    </entry>
    <entry>
        <id>https://www.skysports.com/football/news/12709/13143201/manchester-united-to-make-erik-ten-hag-decision-next-week-paper-talk</id>
        <title>文件：下周将做出十个女巫的决定</title>
        <updated>2024-05-25T22:00:00+00:00</updated>
        <link href="https://www.skysports.com/football/news/12709/13143201/manchester-united-to-make-erik-ten-hag-decision-next-week-paper-talk"/>
        <summary type="html">&lt;p&gt;周日报纸的头条新闻和转会传闻......&lt;/p&gt;&lt;p&gt;&lt;strong&gt;运动型&lt;/strong&gt;&lt;/p&gt;&lt;div class="sdc-site-outbrain sdc-site-outbrain--AR_5"&gt;
&lt;div class="OUTBRAIN"&gt;
&lt;/div&gt;
&lt;/div&gt;
&lt;p&gt;曼联将在下周进行完整的赛季回顾，包括埃里克十哈格的表现，然后再决定俱乐部在管理和球员方面的下一步行动。&lt;/p&gt;&lt;p&gt;在担心法比奥·维埃拉在阿森纳训练中的表现后，米克尔·阿尔特塔正在考虑今年夏天以 3500 万英镑的价格出售中场球员法比奥·维埃拉。&lt;/p&gt;&lt;p&gt;&lt;strong&gt;周日邮寄&lt;/strong&gt;&lt;/p&gt;
&lt;p&gt;德国的报道表明，托马斯·图切尔拒绝了继续担任拜仁慕尼黑主教练的机会，因为他知道自己已经掌握了曼联的职位。&lt;/p&gt;&lt;div class="ad ad--teads"&gt;
&lt;div class="sdc-site-au"&gt;
&lt;div&gt;&lt;/div&gt;
&lt;div class="sdc-site-au__teads" id="in-article-desktop"&gt;&lt;/div&gt;
&lt;/div&gt;
&lt;/div&gt;
&lt;ul&gt;&lt;li&gt;&lt;strong&gt;&lt;a href="https://www.skysports.com/transfer-centre"&gt;换乘中心现场直播！&lt;/a&gt;&lt;/strong&gt;&lt;/li&gt;&lt;li&gt;&lt;strong&gt;&lt;a href="https://www.skysports.com/football/news/32461/13130980/efl-on-sky-sports-how-to-watch-your-championship-league-one-or-league-two-team-live-next-season"&gt;天空体育+ - 下赛季超过 1,000 场 EFL 比赛直播，无需支付额外费用&lt;/a&gt;&lt;/strong&gt;&lt;/li&gt;&lt;li&gt;&lt;a href="https://www.skysports.com/football/news/11677/13078979/now-sports-membership-qa-how-do-i-stream-sky-sports-is-it-instant-is-there-a-contract"&gt;&lt;strong&gt;您需要知道的一切 - 通过 NOW 直播天空体育&lt;/strong&gt;&lt;/a&gt;&lt;/li&gt;&lt;li&gt;&lt;strong&gt;&lt;a href="https://www.skysports.com/football/news/11095/13056245/sky-sports-on-whatsapp-how-to-follow-our-channel-for-the-latest-news-features-and-highlights" target="_blank"&gt;通过 WhatsApp 获取天空体育&lt;/a&gt; | &lt;a href="https://www.skysports.com/football/news/11677/12572660/download-the-sky-sports-app-premier-league-goals-f1-race-control-and-more-at-your-fingertips" target="_blank"&gt;下载天空体育应用程序&lt;/a&gt;&lt;/strong&gt;&lt;/li&gt;&lt;/ul&gt;&lt;p&gt;莱斯特城正在考虑引进费耶诺德后衞大衞·汉科，因为他显然不会追随前主帅阿恩·斯洛特前往利物浦。&lt;/p&gt;
&lt;p&gt;德怀特·约克支持埃里克十哈格扭转曼联的局面，然后继续表示他愿意亲自担任老特拉福德的最高职位。&lt;/p&gt;
&lt;p&gt;安东尼奥·孔蒂即将重返俱乐部管理层，那不勒斯准备在周末结束前确认他为新任主帅。&lt;/p&gt;&lt;p&gt;曼联在签下维尔港年轻球员贝利·迪佩帕的竞争中处于领先地位，纽卡斯尔和西汉姆联也在关注他。&lt;/p&gt;&lt;p&gt;当局警告飞镖选手，如果在舞台上被发现水瓶中含有酒精，他们将面临最高 1000 英镑的罚款，并可能被停赛。&lt;/p&gt;&lt;p&gt;&lt;strong&gt;周日的太阳&lt;/strong&gt;&lt;/p&gt;&lt;p&gt;VAR 裁判的越位可能会从 2024 年欧洲杯中取消，因为类似系统的发明者正在将欧足联和球追踪专家 Kinexon 告上法庭，指控其专利侵权，听证会定于 6 月 4 日举行。&lt;/p&gt;&lt;p&gt;卢克·利特勒（Luke Littler）不得不在周六在家观看他心爱的曼联赢得足总杯决赛，「为了自己的安全」，因为担心他会在温布利被球迷围攻。&lt;/p&gt;&lt;p&gt;&lt;strong&gt;星期日电讯报&lt;/strong&gt;&lt;/p&gt;&lt;p&gt;曼联卡灵顿训练场的工作人员已被告知在繁忙的夏季翻新设施现代化之前腾出工作空间。&lt;/p&gt;&lt;p&gt;&lt;strong&gt;周日星报&lt;/strong&gt;&lt;/p&gt;&lt;p&gt;康纳·科迪表示，退出英超联赛加盟莱斯特城是他漫长职业生涯中最好的决定之一。&lt;/p&gt;&lt;p&gt;&lt;strong&gt;麦德龙&lt;/strong&gt;&lt;/p&gt;&lt;p&gt;利物浦已经与曼联一起参与了签下里尔年轻后衞莱尼·约罗的竞争。&lt;/p&gt;
&lt;p&gt;&lt;strong&gt;周日快报&lt;/strong&gt;&lt;/p&gt;&lt;p&gt;切尔西担心今年夏天他们会错过长期目标拉斐尔·莱奥，因为沙特冠军阿尔希拉尔愿意斥资 8500 万英镑签下这位 AC 米兰边锋。&lt;/p&gt;&lt;p&gt;&lt;strong&gt;星期日邮报&lt;/strong&gt;&lt;/p&gt;&lt;p&gt;肯尼·米勒确信，如果凯尔特人今年夏天决定在中场球星马特·奥莱利身上兑现，他们将获得至少 2000 万英镑的转会费。&lt;/p&gt;&lt;p&gt;流浪者队正面临来自雄心勃勃的土耳其球队埃尤普体育队签下巴拿马后衞何塞·科尔多巴的竞争。&lt;/p&gt;&lt;p&gt;&lt;strong&gt;苏格兰人&lt;/strong&gt;&lt;/p&gt;&lt;p&gt;工资要求可能是凯尔特人队今年夏天从诺维奇城永久签下租借球星亚当·伊达的一个重大障碍。&lt;/p&gt;</summary>
        <published>2024-05-25T22:00:00+00:00</published>
    </entry>
    <entry>
        <id>https://www.skysports.com/watch/video/13143135/the-verdict-has-erik-ten-hag-gone-out-on-a-high-at-manchester-united</id>
        <title>结论：杯赛的荣耀足以拯救十女巫吗？</title>
        <updated>2024-05-25T19:52:00+00:00</updated>
        <link href="https://www.skysports.com/watch/video/13143135/the-verdict-has-erik-ten-hag-gone-out-on-a-high-at-manchester-united"/>
        <summary type="html"/>
        <published>2024-05-25T19:52:00+00:00</published>
    </entry>
    <entry>
        <id>https://www.skysports.com/football/news/11095/13142901/man-utd-win-the-fa-cup-erik-ten-hag-says-he-will-go-somewhere-else-and-win-trophies-if-club-doesnt-want-him</id>
        <title>十大女巫：如果曼联不需要我，我会去其他地方并赢得奖杯</title>
        <updated>2024-05-25T19:05:00+00:00</updated>
        <link href="https://www.skysports.com/football/news/11095/13142901/man-utd-win-the-fa-cup-erik-ten-hag-says-he-will-go-somewhere-else-and-win-trophies-if-club-doesnt-want-him"/>
        <summary type="html">&lt;p&gt;在曼联足总杯决赛战胜曼城后，乐观的埃里克十哈格进行了反击，因为他在俱乐部的未来仍然存在不确定性。&lt;/p&gt;&lt;p&gt;在他的球队在温布利 2-1 获胜后，荷兰人受到了很多关注，亚历杭德罗·加纳乔和科比·麦努的进球帮助球队在十哈格的带领下在两个赛季中第二次捧起奖杯。&lt;/p&gt;&lt;div class="sdc-site-outbrain sdc-site-outbrain--AR_5"&gt;
&lt;div class="OUTBRAIN"&gt;
&lt;/div&gt;
&lt;/div&gt;
&lt;p&gt;胜利也确保了下赛季欧罗巴联赛的席位。&lt;/p&gt;&lt;ul&gt;&lt;li&gt;&lt;strong&gt;&lt;a href="https://www.skysports.com/football/manchester-city-vs-manchester-united/504674"&gt;曼城 1-2 曼联 - 比赛报告&lt;/a&gt;&lt;/strong&gt;&lt;/li&gt;&lt;li&gt;&lt;strong&gt;&lt;a href="https://www.skysports.com/football/news/11095/13142525/erik-ten-hag-makes-his-point-as-under-fire-boss-inspires-man-utd-to-stunning-fa-cup-win-over-man-city"&gt;埃里克·十·哈格 (Erik ten Hag) 表达了自己的观点，曼联将最好成绩留到最后&lt;/a&gt;&lt;/strong&gt;&lt;/li&gt;&lt;li&gt;&lt;strong&gt;&lt;a href="https://www.skysports.com/football/news/11667/13142093/kieran-mckenna-manchester-united-meet-with-representatives-of-ipswich-boss-amid-chelsea-interest"&gt;切尔西对伊普斯维奇主帅感兴趣，曼联会见基兰·麦肯纳代表&lt;/a&gt;&lt;/strong&gt;&lt;/li&gt;&lt;/ul&gt;&lt;p&gt;当赛后被问及他的未来时，十哈格说：「我不考虑这个。我正在一个项目中，我们正是我们想要的地方。&lt;/p&gt;&lt;p&gt;「我们正在组建一支球队，当我接手时，曼联一片混乱。我们现在正在为未来组建一支球队。&lt;/p&gt;
&lt;div class="ui-vendor-monterosa"&gt;
&lt;div class="ui-vendor-monterosa__inner" id="monterosa-widget-c2aaccc5-4007-4fb3-8dd3-474c9447ea32-018358f4-fc66-4b9e-ae81-24b438963e81"&gt;
&lt;/div&gt;
&lt;section class="ui-consent-roadblock"&gt;
&lt;div class="ui-consent-roadblock-body"&gt;
&lt;span class="ui-consent-roadblock-body__title"&gt;罗莎山&lt;/span&gt;
&lt;span class="ui-consent-roadblock-body__description"&gt;此内容由提供&lt;span class="ui-consent-roadblock-body__vendor-title"&gt;罗莎山&lt;/span&gt;，可能使用 cookie 和其他技术。
                &lt;span class="ui-consent-roadblock-body__vendor-title"&gt;罗莎山&lt;/span&gt;cookie 或仅允许这些 cookie 一次。
                &lt;a href="https://www.skysports.com/football/news/11095/13142901/man-utd-win-the-fa-cup-erik-ten-hag-says-he-will-go-somewhere-else-and-win-trophies-if-club-doesnt-want-him#privacy-options"&gt;隐私选项&lt;/a&gt;.
            &lt;/span&gt;
&lt;span class="ui-consent-roadblock-body__description"&gt;遗憾的是，我们无法验证您是否同意&lt;span class="ui-consent-roadblock-body__vendor-title"&gt;罗莎山&lt;/span&gt;饼干。
                &lt;span class="ui-consent-roadblock-body__vendor-title"&gt;罗莎山&lt;/span&gt;仅用于此会话的 cookie。&lt;/span&gt;
&lt;div class="ui-consent-roadblock-body__link-group"&gt;
&lt;a class="ui-consent-roadblock-body__link ui-consent-roadblock-permanently" href="https://www.skysports.com/football/news/11095/13142901/man-utd-win-the-fa-cup-erik-ten-hag-says-he-will-go-somewhere-else-and-win-trophies-if-club-doesnt-want-him#"&gt;启用 Cookie&lt;/a&gt;
&lt;a class="ui-consent-roadblock-body__link ui-consent-roadblock-once" href="https://www.skysports.com/football/news/11095/13142901/man-utd-win-the-fa-cup-erik-ten-hag-says-he-will-go-somewhere-else-and-win-trophies-if-club-doesnt-want-him#"&gt;允许 Cookie 一次&lt;/a&gt;
&lt;/div&gt;
&lt;/div&gt;
&lt;/section&gt;
&lt;/div&gt;
&lt;p&gt;「会有起起落落，但你看，球队正在发展，球队正在获胜，归根结底，这就是赢得奖杯。&lt;/p&gt;&lt;div class="ad ad--teads"&gt;
&lt;div class="sdc-site-au"&gt;
&lt;div&gt;&lt;/div&gt;
&lt;div class="sdc-site-au__teads" id="in-article-desktop"&gt;&lt;/div&gt;
&lt;/div&gt;
&lt;/div&gt;
&lt;p&gt;「球队也有自己的特色，但你需要有足够的球员。在顶级足球中，你需要一支强大的球队，尤其是当你在英格兰和欧洲踢球时。英超联赛竞争如此激烈，所以你需要一支非常好的球队。」&lt;/p&gt;
&lt;p&gt;「还有很多工作要做，但我们确实处于现在的位置。我们的球队很有价值，而且我们有潜力很大的球员，他们进步得很好。」&lt;/p&gt;
&lt;p&gt;「球队正在进步，我们正在赢得奖杯。两年内两座奖杯也不错。三进决赛也不错，但我们必须继续前进。我对此并不满意。」&lt;/p&gt;&lt;p&gt;「我们必须做得更好，如果他们不再想要我，那么我会去其他任何地方赢得奖杯，因为这就是我整个职业生涯所做的事情。」&lt;/p&gt;&lt;p&gt;当被问及俱乐部在决赛前与其他主教练的谈话是否让他感到受到损害时，十哈格补充道：&lt;em&gt; &lt;/em&gt;「我不知道他们是否这么做了。我无法回答这个问题。也许你有消息来源，我没有。」&lt;/p&gt;
&lt;p&gt;当被问及自弗格森爵士离开以来俱乐部任命了五名永久主教练后是否需要稳定时，十哈格回答说：「当你看到过去十年时，这个俱乐部没有那么多决赛，这个俱乐部没有那么多奖杯，&lt;/p&gt;&lt;p&gt;「而且，在中游组中，他们本赛季发展得非常好。以迪奥戈·达洛特为例。还有其他人。&lt;/p&gt;&lt;p&gt;「我们通过教练和训练增强了球队实力。但同时，我们仍然需要转会窗口来引进更好的球员以及始终可用或经常可用的球员。&lt;/p&gt;&lt;p&gt;「当球员不够强健时，尤其是本赛季球员不够强健时，你就无法提供稳定的表现。」&lt;/p&gt;&lt;p&gt;十女巫希望他的未来尽快得到澄清。&lt;/p&gt;&lt;p&gt;荷兰人正在度假，他感觉自己是这份工作的最佳人选。&lt;/p&gt;&lt;h3&gt;基恩：祈祷曼联支持主教练&lt;/h3&gt;
&lt;p&gt;&lt;em&gt;天空体育&lt;/em&gt;评论员罗伊·基恩希望曼联能够支持埃里克十哈格，并补充说主教练已经完成了他的工作，赢得了周六的足总杯。&lt;/p&gt;&lt;p&gt;他说&lt;em&gt;英国独立电视台体育频道：&lt;/em&gt;「我们不知道是否已经做出决定，我们知道主教练承受的压力以及赛前的问题。&lt;/p&gt;&lt;p&gt;「当你准备杯赛决赛时，这总是很困难的。在足球比赛中，你必须享受这些时刻，包括工作人员、球员、支持者。然后在涉及到的时候过桥。」&lt;/p&gt;&lt;p&gt;「主教练今天完成了他的工作。在足总杯决赛中击败曼城是额外的奖励。祈祷他们支持主教练。」&lt;/p&gt; &lt;p&gt;在谈到他的前球队的表现时，基恩补充道：「我真的为曼联感到高兴。今天早上我有一种奇怪的感觉，他们会出现并赢得奖杯。我无法确定，但我很高兴他们&lt;/p&gt;&lt;p&gt;「联赛的状态必须提高，但你必须享受这些时刻。这就是你为曼联效力时想要的——你想要更多。这就是期望。」&lt;/p&gt;&lt;p&gt;「这是一场正确的曼联表现。他们顽强地踢球，踢出了漂亮的足球，打进了两个进球。他们在过去的两场比赛中充满了信心。」&lt;/p&gt;&lt;p&gt;「多年来我一直批评布鲁诺（费尔南德斯），但事实证明我错了，他的领导能力非常出色。我总是提到他作为一名球员是多么出色。」&lt;/p&gt;
&lt;h3&gt;Mainoo：这是隧道尽头的光明&lt;/h3&gt;
&lt;p&gt;&lt;strong&gt;曼联&lt;/strong&gt;进球者和全场最佳球员&lt;strong&gt;科比·麦努&lt;/strong&gt;赞扬了艰难赛季结束时的团结，并补充说他的进球是「一个令人惊叹的时刻」。&lt;/p&gt;&lt;p&gt;他说&lt;em&gt;英国独立电视台体育频道：&lt;/em&gt;「这真是令人难以置信，球迷们，整个比赛。我们试图阻止他们从中路进攻，他们太危险了。他们的实力太强了。我们试图把他们送到边路，从那里挡住，用我们的生命来防守。」&lt;/p&gt;&lt;p&gt;「我什至不记得它（他的进球），那是一个令人惊叹的时刻。我刚刚跑动并将球射入角落。布鲁诺的能力，他看到了其他人看不到的东西。&lt;/p&gt;&lt;p&gt;「这是一个艰难的赛季，球迷们一直和我们在一起，但在这样的比赛中，我们必须团结起来。这场比赛是隧道尽头的曙光，我们必须团结起来。」&lt;/p&gt;
&lt;h3&gt;瓜迪奥拉：我的比赛计划不好&lt;/h3&gt;&lt;p&gt;&lt;strong&gt;曼城&lt;/strong&gt;老板&lt;strong&gt;瓜迪奥拉&lt;/strong&gt;为周六足总杯决赛输给曼联承担责任。&lt;/p&gt;&lt;p&gt;「首先祝贺曼联」，他在赛后新闻发布会上说道。 &lt;/p&gt;&lt;p&gt;「球员们知道原因。从战术上讲，这并不好。你为一场比赛和不同的位置制定了计划，但没有奏效。&lt;/p&gt;&lt;p&gt;「与对阵曼联的比赛一样，我们控制了比赛，但不像下半场那样，我们无法创造机会。&lt;/p&gt;
&lt;p&gt;「今天我们很失望。一支球队输掉决赛是很正常的，但这个赛季却非同寻常。&lt;/p&gt;&lt;p&gt;「我们以良好的方式挑战了所有奖杯。现在我们需要休息并回来。」&lt;/p&gt;&lt;p&gt;曼联主帅十哈格也得到了赞扬，瓜迪奥拉补充道：「他们必须（关于十哈格的未来）做出决定。&lt;/p&gt;&lt;p&gt;「我不知道，但他是一个可爱的人，一位非凡的教练，赢得足总杯对他们来说很重要，就像上赛季对我们来说一样。」&lt;/p&gt;&lt;h3&gt;&lt;a href="https://www.skysports.com/football/news/11095/13142525/erik-ten-hag-makes-his-point-as-under-fire-boss-inspires-man-utd-to-stunning-fa-cup-win-over-man-city" target="_blank"&gt;&lt;strong&gt;分析：十女巫让拉特克利夫陷入困境了吗？&lt;/strong&gt;&lt;/a&gt;&lt;/h3&gt;&lt;p&gt;&lt;em&gt;天空体育的尼克·赖特：&lt;/em&gt;&lt;/p&gt;&lt;p&gt;比赛的准备过程主要是对埃里克十哈格未来的猜测，一份报纸报道甚至说解雇他的决定已经做出。&lt;/p&gt;&lt;p&gt;如果股东吉姆·拉特克利夫爵士确实得出了这个结论，也就不足为奇了。&lt;/p&gt;&lt;p&gt;但十女巫至少让他停下来思考。&lt;/p&gt;&lt;p&gt;十个女巫可以指出这些情况，并且有两年内两次赢得奖杯的记录。&lt;/p&gt;</summary>
        <published>2024-05-25T19:05:00+00:00</published>
    </entry>
    <entry>
        <id>https://www.skysports.com/watch/video/13143097/fiery-erik-ten-hag-presser-in-full-if-they-dont-want-me-anymore-ill-win-trophies-elsewhere</id>
        <title>在全！</title>
        <updated>2024-05-25T18:40:00+00:00</updated>
        <link href="https://www.skysports.com/watch/video/13143097/fiery-erik-ten-hag-presser-in-full-if-they-dont-want-me-anymore-ill-win-trophies-elsewhere"/>
        <summary type="html"/>
        <published>2024-05-25T18:40:00+00:00</published>
    </entry>
    <entry>
        <id>https://www.skysports.com/football/live-blog/11667/13025492/man-utd-transfer-news-rumours-and-gossip-live-updates-and-latest-on-deals-signings-loans-and-contracts</id>
        <title>曼联传言：「费尔南德斯不是拜仁的具体目标」</title>
        <updated>2024-06-07T11:24:51.755851+00:00</updated>
        <link href="https://www.skysports.com/football/live-blog/11667/13025492/man-utd-transfer-news-rumours-and-gossip-live-updates-and-latest-on-deals-signings-loans-and-contracts"/>
        <summary type="html"/>
    </entry>
    <entry>
        <id>https://www.skysports.com/football/story-telling/11096/13148353/next-up-how-kobbie-mainoo-became-manchester-uniteds-main-man</id>
        <title>下一篇：迈努如何成为曼联的主力</title>
        <updated>2024-06-07T11:24:51.755879+00:00</updated>
        <link href="https://www.skysports.com/football/story-telling/11096/13148353/next-up-how-kobbie-mainoo-became-manchester-uniteds-main-man"/>
        <summary type="html"/>
    </entry>
</feed>
