<?xml version='1.0' encoding='utf-8'?>
<?xml-stylesheet type="text/xsl" href="/static/rss.xsl"?>
<feed
    xmlns="http://www.w3.org/2005/Atom" xml:lang="en">
    <id>https://www.theverge.com/apps</id>
    <title>The Verge - Apps Posts</title>
    <updated>2024-06-11T23:45:48+00:00</updated>
    <link href="https://www.theverge.com/apps" rel="alternate"/>
    <generator uri="https://lkiesow.github.io/python-feedgen" version="1.0.0">python-feedgen</generator>
    <subtitle>The Verge - Apps Posts - Made with love by RSSHub(https://github.com/DIYgod/RSSHub)</subtitle>
    <entry>
        <id>https://www.theverge.com/2024/6/11/24176333/bereal-acquired-500-million-voodoo</id>
        <title>是時候以 5 億歐元收購了</title>
        <updated>2024-06-11T20:02:03+00:00</updated>
        <author>
            <name>Emma Roth</name>
        </author>
        <link href="https://www.theverge.com/2024/6/11/24176333/bereal-acquired-500-million-voodoo"/>
        <summary type="html">&lt;h2 class="inline selection:bg-franklin-20"&gt;&lt;/h2&gt;&lt;img src="https://cdn.vox-cdn.com/thumbor/b-EId7Ls6ce4paYzW8662qLVfe8=/0x0:2160x2160/1200x628/filters:focal(1080x1080:1081x1081)/cdn.vox-cdn.com/uploads/chorus_asset/file/25487038/bereal_acquired_voodoo.png"/&gt;&lt;div&gt;&lt;div class="duet--article--article-body-component"&gt;&lt;p class="duet--article--dangerously-set-cms-markup duet--article--standard-paragraph mb-20 font-fkroman text-18 leading-160 -tracking-1 selection:bg-franklin-20 dark:text-white dark:selection:bg-blurple [&amp;amp;_a:hover]:shadow-highlight-franklin dark:[&amp;amp;_a:hover]:shadow-highlight-blurple [&amp;amp;_a]:shadow-underline-black dark:[&amp;amp;_a]:shadow-underline-white"&gt;&lt;a href="https://blog.voodoo.io/articles/voodoo-acquires-bereal"&gt;&lt;/a&gt;&lt;/p&gt;&lt;/div&gt;&lt;div class="duet--article--article-body-component"&gt;&lt;p class="duet--article--dangerously-set-cms-markup duet--article--standard-paragraph mb-20 font-fkroman text-18 leading-160 -tracking-1 selection:bg-franklin-20 dark:text-white dark:selection:bg-blurple [&amp;amp;_a:hover]:shadow-highlight-franklin dark:[&amp;amp;_a:hover]:shadow-highlight-blurple [&amp;amp;_a]:shadow-underline-black dark:[&amp;amp;_a]:shadow-underline-white"&gt;&lt;a href="https://www.theverge.com/2023/4/26/23698859/bereal-losing-interest-missed-opportunity"&gt;一份報告來自&lt;em&gt;&lt;/em&gt;&lt;/a&gt;&lt;/p&gt;&lt;/div&gt;&lt;div class="duet--article--article-body-component clear-both block"&gt;&lt;div class="duet--media--embed min-h-[240px] mb-20 w-full md:max-w-[460px]"&gt;&lt;/div&gt;&lt;/div&gt;&lt;div class="duet--article--article-body-component"&gt;&lt;p class="duet--article--dangerously-set-cms-markup duet--article--standard-paragraph mb-20 font-fkroman text-18 leading-160 -tracking-1 selection:bg-franklin-20 dark:text-white dark:selection:bg-blurple [&amp;amp;_a:hover]:shadow-highlight-franklin dark:[&amp;amp;_a:hover]:shadow-highlight-blurple [&amp;amp;_a]:shadow-underline-black dark:[&amp;amp;_a]:shadow-underline-white"&gt;&lt;a href="https://techcrunch.com/2023/12/12/bereal-adds-private-groups-and-live-photo-like-features-pew-estimates-13-of-us-teens-use-app/"&gt;&lt;/a&gt;和&lt;a href="https://www.bbc.com/news/newsbeat-65374359"&gt;&lt;/a&gt;&lt;a href="https://www.theverge.com/2024/2/6/24061923/bereal-launches-its-celebrity-and-brand-driven-feeds"&gt;RealPeople 二月飼料&lt;/a&gt;專注於&lt;a href="https://www.theverge.com/2023/5/1/23707181/bereal-feed-famous-people-realpeople"&gt;顯示名人的帖子&lt;/a&gt;和品牌。&lt;/p&gt;&lt;/div&gt;&lt;div class="duet--article--article-body-component"&gt;&lt;p class="duet--article--dangerously-set-cms-markup duet--article--standard-paragraph mb-20 font-fkroman text-18 leading-160 -tracking-1 selection:bg-franklin-20 dark:text-white dark:selection:bg-blurple [&amp;amp;_a:hover]:shadow-highlight-franklin dark:[&amp;amp;_a:hover]:shadow-highlight-blurple [&amp;amp;_a]:shadow-underline-black dark:[&amp;amp;_a]:shadow-underline-white"&gt;今年早些時候，BeReal 出現了麻煩的跡象。&lt;a href="https://www.businessinsider.com/bereal-weighing-series-c-or-being-acquired-sources-say-2024-3"&gt;消息人士透露&lt;em&gt;商業內幕&lt;/em&gt;&lt;/a&gt;該應用程序的增長已趨於穩定，而公司領導者開始探索更多輪融資或可能的出售。 &lt;/p&gt;&lt;/div&gt;&lt;div class="duet--article--article-body-component"&gt;&lt;p class="duet--article--dangerously-set-cms-markup duet--article--standard-paragraph mb-20 font-fkroman text-18 leading-160 -tracking-1 selection:bg-franklin-20 dark:text-white dark:selection:bg-blurple [&amp;amp;_a:hover]:shadow-highlight-franklin dark:[&amp;amp;_a:hover]:shadow-highlight-blurple [&amp;amp;_a]:shadow-underline-black dark:[&amp;amp;_a]:shadow-underline-white"&gt;BeReal 創始人兼首席執行官 Barreyat 也將辭職，接替者將由 Voodoo 旗下社交應用 Wizz 的首席執行官 Aymeric Roffé 接任。&lt;/p&gt;&lt;/div&gt;&lt;/div&gt;&lt;div class="mb-40 mt-30"&gt;&lt;button class="duet--article--comments-button group inline-flex h-40 w-full items-center justify-center rounded-[2px] border-[1px] border-solid border-blurple font-polysans-mono text-11 font-light uppercase tracking-12 text-blurple hover:bg-blurple hover:text-white md:w-auto md:px-30"&gt;&lt;svg class="mr-10 inline pt-2" fill="none" height="14" stroke-width="1px" viewbox="0 0 12 12" width="12"
            xmlns="http://www.w3.org/2000/svg"&gt;&lt;title&gt;Comments&lt;/title&gt;&lt;path d="M2.4 9.1h-.207l-.147.146L.5 10.793V1.2c0-.384.316-.7.7-.7h9.6c.384 0 .7.316.7.7v7.2c0 .384-.316.7-.7.7H2.4Z" stroke="currentColor"&gt;&lt;/path&gt;&lt;/svg&gt;&lt;span class="coral-count"&gt;&lt;/span&gt;&lt;/button&gt;&lt;/div&gt;
        </summary>
        <published>2024-06-11T20:02:03+00:00</published>
    </entry>
    <entry>
        <id>https://www.theverge.com/2024/6/11/24175689/apple-vision-pro-2-wwdc-2024-keynote-best-updates</id>
        <title>蘋果跳過了最好的 visionOS 2 更新</title>
        <updated>2024-06-11T15:34:23+00:00</updated>
        <author>
            <name>Wes Davis</name>
        </author>
        <link href="https://www.theverge.com/2024/6/11/24175689/apple-vision-pro-2-wwdc-2024-keynote-best-updates"/>
        <summary type="html">&lt;h2 class="inline selection:bg-franklin-20"&gt;僅根據視頻，您可能會覺得 visionOS 2 不會是一個大的更新。&lt;/h2&gt;&lt;img src="https://cdn.vox-cdn.com/thumbor/M1Px-ofmt6jCQf-45pPv6a0_7mk=/0x0:2231x1253/1200x628/filters:focal(1116x627:1117x628)/cdn.vox-cdn.com/uploads/chorus_asset/file/25485970/Screenshot_2024_06_10_at_6.16.30_PM.png"/&gt;&lt;div&gt;&lt;div class="duet--article--article-body-component"&gt;&lt;p class="duet--article--dangerously-set-cms-markup duet--article--standard-paragraph mb-20 font-fkroman text-18 leading-160 -tracking-1 selection:bg-franklin-20 dark:text-white dark:selection:bg-blurple [&amp;amp;_a:hover]:shadow-highlight-franklin dark:[&amp;amp;_a:hover]:shadow-highlight-blurple [&amp;amp;_a]:shadow-underline-black dark:[&amp;amp;_a]:shadow-underline-white"&gt;蘋果提到了一些&lt;a href="https://www.theverge.com/2024/6/10/24171950/apple-vision-pro-wwdc-2024-visionos-2-first-party-native-apps"&gt;Vision Pro 即將推出新功能&lt;/a&gt;其期間&lt;a href="https://www.theverge.com/2024/6/10/24171999/apple-wwdc-2024-news-rumors-announcements-ios-18-ai"&gt;WWDC 2024 主題演講&lt;/a&gt;週一，例如將 2D 照片轉換為 3D 照片的能力以及支持在火車上使用耳機。&lt;/p&gt;&lt;/div&gt;&lt;div class="duet--article--article-body-component"&gt;&lt;p class="duet--article--dangerously-set-cms-markup duet--article--standard-paragraph mb-20 font-fkroman text-18 leading-160 -tracking-1 selection:bg-franklin-20 dark:text-white dark:selection:bg-blurple [&amp;amp;_a:hover]:shadow-highlight-franklin dark:[&amp;amp;_a:hover]:shadow-highlight-blurple [&amp;amp;_a]:shadow-underline-black dark:[&amp;amp;_a]:shadow-underline-white"&gt;今年秋季更新發布後，您將能夠在虛擬環境中工作時看到妙控鍵盤，使用您想要的任何藍牙鼠標，並重新排列主屏幕圖標 - 包括將 iPad 和 iPhone 應用程序放在您想要的位置。&lt;a href="https://www.theverge.com/24054862/apple-vision-pro-review-vr-ar-headset-features-price"&gt;從一開始就&lt;/a&gt;，他們將以有意義的方式改善 Vision Pro 的日常使用體驗。&lt;/p&gt;&lt;/div&gt;&lt;div class="duet--article--article-body-component clear-both block"&gt;&lt;div class="my-9"&gt;&lt;div class="transition-all duration-300 ease-in-out"&gt;&lt;div class="fixed inset-0 h-[110vh] w-full bg-white transition-all duration-300 ease-in-out z-[-1] cursor-default opacity-0" tabindex="0"&gt;&lt;/div&gt;&lt;div class="visible z-30 w-full origin-center transition-all duration-300 ease-in-out cursor-zoom-in" tabindex="0"&gt;&lt;figure class="transition-all duration-300 ease-in-out lg:mx-0"&gt;&lt;div&gt;&lt;div class="duet--media--content-warning relative"&gt;&lt;span style="display: block; overflow: hidden; width: initial; height: initial; background: none; border: 0; margin: 0; padding: 0;"&gt;&lt;img alt="A Magic Keyboard floats below the homescreen in a Vision Pro virtual environment." src="data:image/gif;base64,R0lGODlhAQABAIAAAAAAAP///yH5BAEAAAAALAAAAAABAAEAAAIBRAA7" style="padding: 0; border: none; margin: auto; display: block; width: 0; height: 0;"/&gt;&lt;noscript&gt;&lt;img alt="A Magic Keyboard floats below the homescreen in a Vision Pro virtual environment." src="https://duet-cdn.vox-cdn.com/thumbor/0x0:1960x1102/2400x1349/filters:focal(980x551:981x552):format(webp)/cdn.vox-cdn.com/uploads/chorus_asset/file/25486451/Apple_WWDC24_visionOS_2_Magic_Keyboard_breakthrough_240610.jpg" style="padding: 0; border: none; margin: auto; display: block; width: 0; height: 0;"/&gt;&lt;/noscript&gt;&lt;/span&gt;&lt;/div&gt;&lt;/div&gt;&lt;/figure&gt;&lt;/div&gt;&lt;div class="z-1 w-full hidden"&gt;&lt;figure class="transition-all duration-300 ease-in-out lg:mx-0"&gt;&lt;div&gt;&lt;div class="duet--media--content-warning relative"&gt;&lt;span style="display: block; overflow: hidden; width: initial; height: initial; background: none; border: 0; margin: 0; padding: 0;"&gt;&lt;img alt="A Magic Keyboard floats below the homescreen in a Vision Pro virtual environment." src="data:image/gif;base64,R0lGODlhAQABAIAAAAAAAP///yH5BAEAAAAALAAAAAABAAEAAAIBRAA7" style="padding: 0; border: none; margin: auto; display: block; width: 0; height: 0;"/&gt;&lt;noscript&gt;&lt;img alt="A Magic Keyboard floats below the homescreen in a Vision Pro virtual environment." src="https://duet-cdn.vox-cdn.com/thumbor/0x0:1960x1102/2400x1349/filters:focal(980x551:981x552):format(webp)/cdn.vox-cdn.com/uploads/chorus_asset/file/25486451/Apple_WWDC24_visionOS_2_Magic_Keyboard_breakthrough_240610.jpg" style="padding: 0; border: none; margin: auto; display: block; width: 0; height: 0;"/&gt;&lt;/noscript&gt;&lt;/span&gt;&lt;/div&gt;&lt;/div&gt;&lt;/figure&gt;&lt;/div&gt;&lt;/div&gt;&lt;div class="duet--media--caption pt-6 font-polysans-mono text-12 font-light leading-130 tracking-1"&gt;&lt;figcaption class="duet--article--dangerously-set-cms-markup inline text-gray-13 dark:text-gray-e9 [&amp;amp;&amp;gt;a:hover]:text-black [&amp;amp;&amp;gt;a:hover]:shadow-underline-black dark:[&amp;amp;&amp;gt;a:hover]:text-gray-e9 dark:[&amp;amp;&amp;gt;a:hover]:shadow-underline-gray-63 [&amp;amp;&amp;gt;a]:shadow-underline-gray-13 dark:[&amp;amp;&amp;gt;a]:shadow-underline-gray-63"&gt;&lt;em&gt;飛吧，小鍵盤，飛吧！&lt;/em&gt;&lt;/figcaption&gt; &lt;cite class="duet--article--dangerously-set-cms-markup inline not-italic text-gray-63 dark:text-gray-bd [&amp;amp;&amp;gt;a:hover]:text-gray-63 [&amp;amp;&amp;gt;a:hover]:shadow-underline-black dark:[&amp;amp;&amp;gt;a:hover]:text-gray-bd dark:[&amp;amp;&amp;gt;a:hover]:shadow-underline-gray [&amp;amp;&amp;gt;a]:shadow-underline-gray-63 dark:[&amp;amp;&amp;gt;a]:text-gray-bd dark:[&amp;amp;&amp;gt;a]:shadow-underline-gray"&gt;圖片：蘋果&lt;/cite&gt;&lt;/div&gt;&lt;/div&gt;&lt;/div&gt;&lt;div class="duet--article--article-body-component"&gt;&lt;p class="duet--article--dangerously-set-cms-markup duet--article--standard-paragraph mb-20 font-fkroman text-18 leading-160 -tracking-1 selection:bg-franklin-20 dark:text-white dark:selection:bg-blurple [&amp;amp;_a:hover]:shadow-highlight-franklin dark:[&amp;amp;_a:hover]:shadow-highlight-blurple [&amp;amp;_a]:shadow-underline-black dark:[&amp;amp;_a]:shadow-underline-white"&gt;蘋果表示，Vision Pro 還將開始為訪客用户保存眼睛和手部設置 30 天。&lt;a href="https://www.theverge.com/2024/2/16/24058318/apple-vision-pro-sharing-difficulties"&gt;與任何人分享 Vision Pro 都很痛苦&lt;/a&gt;因為每次您將其彈出到訪客模式時，該人都必須重新進行設置。&lt;/p&gt;&lt;/div&gt;&lt;div class="duet--article--article-body-component"&gt;&lt;p class="duet--article--dangerously-set-cms-markup duet--article--standard-paragraph mb-20 font-fkroman text-18 leading-160 -tracking-1 selection:bg-franklin-20 dark:text-white dark:selection:bg-blurple [&amp;amp;_a:hover]:shadow-highlight-franklin dark:[&amp;amp;_a:hover]:shadow-highlight-blurple [&amp;amp;_a]:shadow-underline-black dark:[&amp;amp;_a]:shadow-underline-white"&gt;體育迷們會很高興知道蘋果還在 Apple TV 應用程序中添加了五屏多視圖流媒體，這是該公司的一項舉措&lt;a href="https://www.theverge.com/2023/5/18/23728752/apple-tv-multiview-live-sports-tvos-update"&gt;添加到 Apple TV 流媒體盒中&lt;/a&gt;去年。&lt;/p&gt;&lt;/div&gt;&lt;div class="duet--article--article-body-component clear-both block"&gt;&lt;div class="my-9"&gt;&lt;div class="transition-all duration-300 ease-in-out"&gt;&lt;div class="fixed inset-0 h-[110vh] w-full bg-white transition-all duration-300 ease-in-out z-[-1] cursor-default opacity-0" tabindex="0"&gt;&lt;/div&gt;&lt;div class="visible z-30 w-full origin-center transition-all duration-300 ease-in-out cursor-zoom-in" tabindex="0"&gt;&lt;figure class="transition-all duration-300 ease-in-out lg:mx-0"&gt;&lt;div&gt;&lt;div class="duet--media--content-warning relative"&gt;&lt;span style="display: block; overflow: hidden; width: initial; height: initial; background: none; border: 0; margin: 0; padding: 0;"&gt;&lt;img alt="A GIF showing a video popping out of a webpage." src="data:image/gif;base64,R0lGODlhAQABAIAAAAAAAP///yH5BAEAAAAALAAAAAABAAEAAAIBRAA7" style="padding: 0; border: none; margin: auto; display: block; width: 0; height: 0;"/&gt;&lt;noscript&gt;&lt;img alt="A GIF showing a video popping out of a webpage." src="https://duet-cdn.vox-cdn.com/thumbor/0x0:600x334/2400x1336/filters:focal(300x167:301x168):no_upscale():format(webp)/cdn.vox-cdn.com/uploads/chorus_asset/file/25486493/Web_video_vision_pro.gif" style="padding: 0; border: none; margin: auto; display: block; width: 0; height: 0;"/&gt;&lt;/noscript&gt;&lt;/span&gt;&lt;/div&gt;&lt;/div&gt;&lt;/figure&gt;&lt;/div&gt;&lt;div class="z-1 w-full hidden"&gt;&lt;figure class="transition-all duration-300 ease-in-out lg:mx-0"&gt;&lt;div&gt;&lt;div class="duet--media--content-warning relative"&gt;&lt;span style="display: block; overflow: hidden; width: initial; height: initial; background: none; border: 0; margin: 0; padding: 0;"&gt;&lt;img alt="A GIF showing a video popping out of a webpage." src="data:image/gif;base64,R0lGODlhAQABAIAAAAAAAP///yH5BAEAAAAALAAAAAABAAEAAAIBRAA7" style="padding: 0; border: none; margin: auto; display: block; width: 0; height: 0;"/&gt;&lt;noscript&gt;&lt;img alt="A GIF showing a video popping out of a webpage." src="https://duet-cdn.vox-cdn.com/thumbor/0x0:600x334/2400x1336/filters:focal(300x167:301x168):no_upscale():format(webp)/cdn.vox-cdn.com/uploads/chorus_asset/file/25486493/Web_video_vision_pro.gif" style="padding: 0; border: none; margin: auto; display: block; width: 0; height: 0;"/&gt;&lt;/noscript&gt;&lt;/span&gt;&lt;/div&gt;&lt;/div&gt;&lt;/figure&gt;&lt;/div&gt;&lt;/div&gt;&lt;div class="duet--media--caption pt-6 font-polysans-mono text-12 font-light leading-130 tracking-1"&gt; &lt;cite class="duet--article--dangerously-set-cms-markup inline not-italic text-gray-63 dark:text-gray-bd [&amp;amp;&amp;gt;a:hover]:text-gray-63 [&amp;amp;&amp;gt;a:hover]:shadow-underline-black dark:[&amp;amp;&amp;gt;a:hover]:text-gray-bd dark:[&amp;amp;&amp;gt;a:hover]:shadow-underline-gray [&amp;amp;&amp;gt;a]:shadow-underline-gray-63 dark:[&amp;amp;&amp;gt;a]:text-gray-bd dark:[&amp;amp;&amp;gt;a]:shadow-underline-gray"&gt;動圖：蘋果&lt;/cite&gt;&lt;/div&gt;&lt;/div&gt;&lt;/div&gt;&lt;div class="duet--article--article-body-component"&gt;&lt;p class="duet--article--dangerously-set-cms-markup duet--article--standard-paragraph mb-20 font-fkroman text-18 leading-160 -tracking-1 selection:bg-franklin-20 dark:text-white dark:selection:bg-blurple [&amp;amp;_a:hover]:shadow-highlight-franklin dark:[&amp;amp;_a:hover]:shadow-highlight-blurple [&amp;amp;_a]:shadow-underline-black dark:[&amp;amp;_a]:shadow-underline-white"&gt;最後，當您在網絡上遇到視頻時，您將能夠將其分解為自由浮動的視頻播放器 -&lt;strong&gt; &lt;/strong&gt;這是蘋果必然要做的事情，因為 YouTube 和 Netflix 都沒有為 Vision Pro 開發應用程序。&lt;a href="https://www.theverge.com/2024/2/2/24059005/juno-youtube-vision-pro-app-christian-selig"&gt;朱諾&lt;/a&gt;或者&lt;a href="https://www.theverge.com/2024/4/8/24124534/supercut-netflix-vision-pro-app-4k-dolby-atmos-vision-visionos"&gt;超切&lt;/a&gt;，但是能夠以這種方式觀看其他在線視頻會很好。&lt;/p&gt;&lt;/div&gt;&lt;div class="duet--article--article-body-component"&gt;&lt;p class="duet--article--dangerously-set-cms-markup duet--article--standard-paragraph mb-20 font-fkroman text-18 leading-160 -tracking-1 selection:bg-franklin-20 dark:text-white dark:selection:bg-blurple [&amp;amp;_a:hover]:shadow-highlight-franklin dark:[&amp;amp;_a:hover]:shadow-highlight-blurple [&amp;amp;_a]:shadow-underline-black dark:[&amp;amp;_a]:shadow-underline-white"&gt;這些細節都出現在蘋果的新聞材料中。&lt;/p&gt;&lt;/div&gt;&lt;div class="duet--article--article-body-component"&gt;&lt;ul class="duet--article--unordered-list my-20 list-disc pl-18 marker:text-blurple/100 selection:bg-franklin-20 dark:text-white dark:selection:bg-blurple [&amp;amp;_a:hover]:shadow-highlight-franklin dark:[&amp;amp;_a:hover]:shadow-highlight-franklin [&amp;amp;_a]:shadow-underline-black dark:[&amp;amp;_a]:shadow-underline-white"&gt;&lt;li class="duet--article--dangerously-set-cms-markup mb-16 pl-12 font-fkroman text-18 leading-160 -tracking-1"&gt;將應用程序窗口放置得比以前更遠。&lt;/li&gt;&lt;li class="duet--article--dangerously-set-cms-markup mb-16 pl-12 font-fkroman text-18 leading-160 -tracking-1"&gt;體積窗户——其中&lt;a href="https://developer.apple.com/documentation/SwiftUI/WindowStyle/volumetric"&gt;讓您從各個角度查看應用程序的內容&lt;/a&gt;- 將傾斜面向您，以便您可以在躺着時使用它們（儘管開發人員可以根據需要選擇不這樣做）。&lt;a href="https://arc.net/l/quote/nxalxaqa"&gt;也可以調整它們的大小&lt;/a&gt;.&lt;/li&gt;&lt;li class="duet--article--dangerously-set-cms-markup mb-16 pl-12 font-fkroman text-18 leading-160 -tracking-1"&gt;卸載虛擬環境的能力——它們的圖標仍然存在，但如果你厭倦了 Mt. Hood，它就不再需要佔用空間了。&lt;/li&gt;&lt;li class="duet--article--dangerously-set-cms-markup mb-16 pl-12 font-fkroman text-18 leading-160 -tracking-1"&gt;在虛擬環境中觀看全屏視頻時，您可以躺下並將它們重新置於您的上方。&lt;/li&gt;&lt;/ul&gt;&lt;/div&gt;&lt;div class="duet--article--article-body-component"&gt;&lt;p class="duet--article--dangerously-set-cms-markup duet--article--standard-paragraph mb-20 font-fkroman text-18 leading-160 -tracking-1 selection:bg-franklin-20 dark:text-white dark:selection:bg-blurple [&amp;amp;_a:hover]:shadow-highlight-franklin dark:[&amp;amp;_a:hover]:shadow-highlight-blurple [&amp;amp;_a]:shadow-underline-black dark:[&amp;amp;_a]:shadow-underline-white"&gt;蘋果在 WWDC 主題演講中可能沒有滿足我的全部願望，但我驚訝於它如此具體地解決了我想要從 VisionOS 中得到的東西，比如用一個手勢調用主屏幕的能力。&lt;/p&gt;&lt;/div&gt;&lt;/div&gt;&lt;div class="mb-40 mt-30"&gt;&lt;button class="duet--article--comments-button group inline-flex h-40 w-full items-center justify-center rounded-[2px] border-[1px] border-solid border-blurple font-polysans-mono text-11 font-light uppercase tracking-12 text-blurple hover:bg-blurple hover:text-white md:w-auto md:px-30"&gt;&lt;svg class="mr-10 inline pt-2" fill="none" height="14" stroke-width="1px" viewbox="0 0 12 12" width="12"
            xmlns="http://www.w3.org/2000/svg"&gt;&lt;title&gt;Comments&lt;/title&gt;&lt;path d="M2.4 9.1h-.207l-.147.146L.5 10.793V1.2c0-.384.316-.7.7-.7h9.6c.384 0 .7.316.7.7v7.2c0 .384-.316.7-.7.7H2.4Z" stroke="currentColor"&gt;&lt;/path&gt;&lt;/svg&gt;&lt;span class="coral-count"&gt;&lt;/span&gt;&lt;/button&gt;&lt;/div&gt;
        </summary>
        <published>2024-06-11T15:34:23+00:00</published>
    </entry>
    <entry>
        <id>https://www.theverge.com/2024/6/11/24176008/apple-intelligence-siri-iphone-ipad-wwdc-2024</id>
        <title>Apple Intelligence、iPhone 以及 WWDC 2024 的其他內容</title>
        <updated>2024-06-11T13:33:38+00:00</updated>
        <author>
            <name>David Pierce</name>
        </author>
        <link href="https://www.theverge.com/2024/6/11/24176008/apple-intelligence-siri-iphone-ipad-wwdc-2024"/>
        <summary type="html">&lt;h2 class="inline selection:bg-franklin-20"&gt;On The Vergecast：蘋果公司推出了人工智能技術，今年所有新產品都會出現在你的手機、平板電腦、筆記本電腦、手錶和電視上。&lt;/h2&gt;&lt;img src="https://cdn.vox-cdn.com/thumbor/KEWJZhHN7z6BLCqcluyzarT78GE=/0x0:2040x1360/1200x628/filters:focal(1020x680:1021x681)/cdn.vox-cdn.com/uploads/chorus_asset/file/25486468/VST_0611_Site.jpg"/&gt;&lt;div&gt;&lt;div class="duet--article--article-body-component"&gt;&lt;p class="duet--article--dangerously-set-cms-markup duet--article--standard-paragraph mb-20 font-fkroman text-18 leading-160 -tracking-1 selection:bg-franklin-20 dark:text-white dark:selection:bg-blurple [&amp;amp;_a:hover]:shadow-highlight-franklin dark:[&amp;amp;_a:hover]:shadow-highlight-blurple [&amp;amp;_a]:shadow-underline-black dark:[&amp;amp;_a]:shadow-underline-white"&gt;今年幾乎有兩場不同的 WWDC。&lt;a href="https://www.theverge.com/2024/6/10/24172132/apple-ios-18-new-features-ai"&gt;添加內容到您的主屏幕&lt;/a&gt;, &lt;a href="https://www.theverge.com/2024/6/10/24171315/apple-messages-rcs-ios-18-imessage-green-bubble"&gt;與你的朋友分享東西&lt;/a&gt;, &lt;a href="https://www.theverge.com/2024/6/10/24175423/apple-tv-plus-features-tvos-wwdc'"&gt;在電視上看東西&lt;/a&gt;, &lt;a href="https://www.theverge.com/2024/6/10/24175487/ipad-calculator-app-ipados18-pencil-apple-wwdc2024"&gt;在平板電腦上計算內容&lt;/a&gt;， 和更多。&lt;/p&gt;&lt;/div&gt;&lt;div class="duet--article--article-body-component"&gt;&lt;p class="duet--article--dangerously-set-cms-markup duet--article--standard-paragraph mb-20 font-fkroman text-18 leading-160 -tracking-1 selection:bg-franklin-20 dark:text-white dark:selection:bg-blurple [&amp;amp;_a:hover]:shadow-highlight-franklin dark:[&amp;amp;_a:hover]:shadow-highlight-blurple [&amp;amp;_a]:shadow-underline-black dark:[&amp;amp;_a]:shadow-underline-white"&gt;WWDC 的第二幕是&lt;a href="https://www.theverge.com/2024/6/10/24175405/wwdc-apple-ai-news-features-ios-18-macos-15-iphone-ipad-mac"&gt;蘋果情報秀&lt;/a&gt;，蘋果開始公佈其人工智能戰略。&lt;a href="https://www.theverge.com/2024/6/10/24171936/apple-siri-ai-update-ios18-features-wwdc"&gt;Siri 的全新且令人興奮的願景&lt;/a&gt;- 但也瞭解了蘋果計劃如何應對這一具有潛在顛覆性的新類別。&lt;/p&gt;&lt;/div&gt;&lt;div class="duet--article--article-body-component clear-both block"&gt;&lt;div class="duet--media--embed min-h-[100px] mb-20 w-full"&gt;&lt;/div&gt;&lt;/div&gt;&lt;div class="duet--article--article-body-component"&gt;&lt;p class="duet--article--dangerously-set-cms-markup duet--article--standard-paragraph mb-20 font-fkroman text-18 leading-160 -tracking-1 selection:bg-franklin-20 dark:text-white dark:selection:bg-blurple [&amp;amp;_a:hover]:shadow-highlight-franklin dark:[&amp;amp;_a:hover]:shadow-highlight-blurple [&amp;amp;_a]:shadow-underline-black dark:[&amp;amp;_a]:shadow-underline-white"&gt;在&lt;a href="https://link.chtbl.com/vergecast"&gt;這一集的&lt;em&gt;邊緣廣播&lt;/em&gt;&lt;/a&gt;，我們聚集在 Apple Park 沿街的一所房子裏來解決這一切。&lt;em&gt;邊緣廣播&lt;/em&gt;，我們喜歡可定製的小部件系統。）我們還介紹了我們個人最興奮的今年秋天在我們的設備上獲得的功能 - 以及我們不太關心的功能。&lt;/p&gt;&lt;/div&gt;&lt;div class="duet--article--article-body-component clear-both block"&gt;&lt;div class="duet--media--video-embed mb-20"&gt;&lt;div class="relative aspect-video"&gt;&lt;div class="duet--media--content-warning relative" style="padding-top: 56.25%;"&gt;&lt;div class="absolute top-0 h-full w-full"&gt;&lt;/div&gt;&lt;/div&gt;&lt;/div&gt;&lt;/div&gt;&lt;/div&gt;&lt;div class="duet--article--article-body-component"&gt;&lt;p class="duet--article--dangerously-set-cms-markup duet--article--standard-paragraph mb-20 font-fkroman text-18 leading-160 -tracking-1 selection:bg-franklin-20 dark:text-white dark:selection:bg-blurple [&amp;amp;_a:hover]:shadow-highlight-franklin dark:[&amp;amp;_a:hover]:shadow-highlight-blurple [&amp;amp;_a]:shadow-underline-black dark:[&amp;amp;_a]:shadow-underline-white"&gt;如果您想更多地瞭解我們在本集中討論的所有內容，這裏有一些鏈接可幫助您開始瞭解 WWDC 的所有內容：&lt;/p&gt;&lt;/div&gt;&lt;div class="duet--article--article-body-component"&gt;&lt;ul class="duet--article--unordered-list my-20 list-disc pl-18 marker:text-blurple/100 selection:bg-franklin-20 dark:text-white dark:selection:bg-blurple [&amp;amp;_a:hover]:shadow-highlight-franklin dark:[&amp;amp;_a:hover]:shadow-highlight-franklin [&amp;amp;_a]:shadow-underline-black dark:[&amp;amp;_a]:shadow-underline-white"&gt;&lt;li class="duet--article--dangerously-set-cms-markup mb-16 pl-12 font-fkroman text-18 leading-160 -tracking-1"&gt;&lt;a href="https://www.theverge.com/24171190/apple-wwdc-2024-biggest-announcements"&gt;Apple WWDC 2024：13 個最重大的公告&lt;/a&gt;&lt;/li&gt;&lt;li class="duet--article--dangerously-set-cms-markup mb-16 pl-12 font-fkroman text-18 leading-160 -tracking-1"&gt;&lt;a href="https://www.theverge.com/2024/6/10/24175405/wwdc-apple-ai-news-features-ios-18-macos-15-iphone-ipad-mac"&gt;Apple Intelligence：iPhone 和 Mac 上即將推出的每一項新 AI 功能&lt;/a&gt;&lt;/li&gt;&lt;li class="duet--article--dangerously-set-cms-markup mb-16 pl-12 font-fkroman text-18 leading-160 -tracking-1"&gt;&lt;a href="https://www.theverge.com/2024/6/10/24171936/apple-siri-ai-update-ios18-features-wwdc"&gt;蘋果將​​在 iOS 18 中對 Siri 進行人工智能升級&lt;/a&gt;&lt;/li&gt;&lt;li class="duet--article--dangerously-set-cms-markup mb-16 pl-12 font-fkroman text-18 leading-160 -tracking-1"&gt;&lt;a href="https://www.theverge.com/2024/6/10/24172132/apple-ios-18-new-features-ai"&gt;Apple 發佈 iOS 18，配備新的 AI 功能和更多可定製的主屏幕&lt;/a&gt;&lt;/li&gt;&lt;li class="duet--article--dangerously-set-cms-markup mb-16 pl-12 font-fkroman text-18 leading-160 -tracking-1"&gt;&lt;a href="https://www.theverge.com/2024/6/10/24171315/apple-messages-rcs-ios-18-imessage-green-bubble"&gt;蘋果將​​在 iOS 18 中將 RCS 引入 iPhone&lt;/a&gt;&lt;/li&gt;&lt;li class="duet--article--dangerously-set-cms-markup mb-16 pl-12 font-fkroman text-18 leading-160 -tracking-1"&gt;&lt;a href="https://www.theverge.com/2024/6/10/24175523/apple-ai-custom-emoji-images-ios18-wwdc"&gt;蘋果的人工智能可以製作自定義表情符號和圖像&lt;/a&gt;&lt;/li&gt;&lt;li class="duet--article--dangerously-set-cms-markup mb-16 pl-12 font-fkroman text-18 leading-160 -tracking-1"&gt;&lt;a href="https://www.theverge.com/2024/6/10/24175479/ios-18-satellite-imessage-wwdc-2024"&gt;iOS 18 為其 iMessage 應用引入了衞星功能&lt;/a&gt;&lt;/li&gt;&lt;li class="duet--article--dangerously-set-cms-markup mb-16 pl-12 font-fkroman text-18 leading-160 -tracking-1"&gt;&lt;a href="https://www.theverge.com/2024/6/10/24175466/iphone-game-mode-performance-frame-rate-optimization-wwdc-2024"&gt;iPhone 的新遊戲模式使其速度更快、響應更靈敏&lt;/a&gt;&lt;/li&gt;&lt;li class="duet--article--dangerously-set-cms-markup mb-16 pl-12 font-fkroman text-18 leading-160 -tracking-1"&gt;&lt;a href="https://www.theverge.com/2024/6/10/24140821/apple-ipados-18-features-updates-apps-wwdc-2024"&gt;Apple 發佈 iPadOS 18，配備內置計算器和可定製主屏幕&lt;/a&gt;&lt;/li&gt;&lt;li class="duet--article--dangerously-set-cms-markup mb-16 pl-12 font-fkroman text-18 leading-160 -tracking-1"&gt;&lt;a href="https://www.theverge.com/2024/6/10/24175487/ipad-calculator-app-ipados18-pencil-apple-wwdc2024"&gt;蘋果 14 年後推出 iPad 計算器應用&lt;/a&gt;&lt;/li&gt;&lt;li class="duet--article--dangerously-set-cms-markup mb-16 pl-12 font-fkroman text-18 leading-160 -tracking-1"&gt;&lt;a href="https://www.theverge.com/2024/6/10/24170653/apple-watch-watchos-11-features-updates-wwdc"&gt;Apple 宣佈 watchOS 11 具有新的訓練功能和實時活動&lt;/a&gt;&lt;/li&gt;&lt;li class="duet--article--dangerously-set-cms-markup mb-16 pl-12 font-fkroman text-18 leading-160 -tracking-1"&gt;&lt;a href="https://www.theverge.com/2024/6/10/24170586/macos-15-mac-apple-ai-wwdc-2024"&gt;Apple 在 WWDC 2024 上發佈 macOS Sequoia&lt;/a&gt; &lt;/li&gt;&lt;li class="duet--article--dangerously-set-cms-markup mb-16 pl-12 font-fkroman text-18 leading-160 -tracking-1"&gt;&lt;a href="https://www.theverge.com/2024/6/10/24175505/apple-password-app-passkey-manager-windows-mac-icloud"&gt;Apple 的獨立密碼應用程序可在 iOS、iPad、Mac 和 Windows 之間同步&lt;/a&gt; &lt;/li&gt;&lt;li class="duet--article--dangerously-set-cms-markup mb-16 pl-12 font-fkroman text-18 leading-160 -tracking-1"&gt;&lt;a href="https://www.theverge.com/2024/6/10/24173874/apple-airpods-new-features-wwdc-2024"&gt;Apple AirPods 正在升級，具有強大的輔助功能&lt;/a&gt;&lt;/li&gt;&lt;li class="duet--article--dangerously-set-cms-markup mb-16 pl-12 font-fkroman text-18 leading-160 -tracking-1"&gt;&lt;a href="https://www.theverge.com/2024/6/10/24175423/apple-tv-plus-features-tvos-wwdc"&gt;Apple TV Plus 的 InSight 功能會告訴你那個演員是誰&lt;/a&gt;&lt;/li&gt;&lt;li class="duet--article--dangerously-set-cms-markup mb-16 pl-12 font-fkroman text-18 leading-160 -tracking-1"&gt;&lt;a href="https://www.theverge.com/2024/6/10/24175308/apple-tv-plus-severance-silo-teaser-wwdc-2024"&gt;蘋果預告新一季《遣散費》和《筒倉》&lt;/a&gt;&lt;/li&gt;&lt;li class="duet--article--dangerously-set-cms-markup mb-16 pl-12 font-fkroman text-18 leading-160 -tracking-1"&gt;&lt;a href="https://www.theverge.com/2024/6/10/24171950/apple-vision-pro-wwdc-2024-visionos-2-first-party-native-apps"&gt;Apple 發佈具有 3D 照片轉換和超寬 Mac 顯示屏的 VisionOS 2&lt;/a&gt;&lt;/li&gt;&lt;li class="duet--article--dangerously-set-cms-markup mb-16 pl-12 font-fkroman text-18 leading-160 -tracking-1"&gt;&lt;a href="https://www.theverge.com/2024/6/10/24175468/canon-eos-spatial-lens-apple-wwdc-2024-announcement"&gt;佳能為 Apple Vision Pro 的空間視頻製作了特殊鏡頭&lt;/a&gt; &lt;/li&gt;&lt;/ul&gt;&lt;/div&gt;&lt;/div&gt;&lt;div class="mb-40 mt-30"&gt;&lt;button class="duet--article--comments-button group inline-flex h-40 w-full items-center justify-center rounded-[2px] border-[1px] border-solid border-blurple font-polysans-mono text-11 font-light uppercase tracking-12 text-blurple hover:bg-blurple hover:text-white md:w-auto md:px-30"&gt;&lt;svg class="mr-10 inline pt-2" fill="none" height="14" stroke-width="1px" viewbox="0 0 12 12" width="12"
            xmlns="http://www.w3.org/2000/svg"&gt;&lt;title&gt;Comments&lt;/title&gt;&lt;path d="M2.4 9.1h-.207l-.147.146L.5 10.793V1.2c0-.384.316-.7.7-.7h9.6c.384 0 .7.316.7.7v7.2c0 .384-.316.7-.7.7H2.4Z" stroke="currentColor"&gt;&lt;/path&gt;&lt;/svg&gt;&lt;span class="coral-count"&gt;&lt;/span&gt;&lt;/button&gt;&lt;/div&gt;
        </summary>
        <published>2024-06-11T13:33:38+00:00</published>
    </entry>
    <entry>
        <id>https://www.theverge.com/2024/6/11/24175980/spotify-hifi-add-on-cost-extra-lossless-audio-supremium</id>
        <title>Spotify 的 HiFi 附加組件每月可能要額外花費 5 美元</title>
        <updated>2024-06-11T13:02:05+00:00</updated>
        <author>
            <name>Emma Roth</name>
        </author>
        <link href="https://www.theverge.com/2024/6/11/24175980/spotify-hifi-add-on-cost-extra-lossless-audio-supremium"/>
        <summary type="html">&lt;h2 class="inline selection:bg-franklin-20"&gt;據彭博社報道，Spotify 傳聞中的 HiFi 音頻層還可能附帶生成播放列表和管理音樂庫的工具。&lt;/h2&gt;&lt;img src="https://cdn.vox-cdn.com/thumbor/twxLFoErhKvKYWgh8fYLKJG86Bo=/0x0:2040x1360/1200x628/filters:focal(1020x680:1021x681)/cdn.vox-cdn.com/uploads/chorus_asset/file/23951391/STK088_VRG_Illo_N_Barclay_4_spotify.jpg"/&gt;&lt;div&gt;&lt;div class="duet--article--article-body-component"&gt;&lt;p class="duet--article--dangerously-set-cms-markup duet--article--standard-paragraph mb-20 font-fkroman text-18 leading-160 -tracking-1 selection:bg-franklin-20 dark:text-white dark:selection:bg-blurple [&amp;amp;_a:hover]:shadow-highlight-franklin dark:[&amp;amp;_a:hover]:shadow-highlight-blurple [&amp;amp;_a]:shadow-underline-black dark:[&amp;amp;_a]:shadow-underline-white"&gt;據報道，Spotify 正準備推出一款高級附加組件，提供高保真音頻的訪問權限&lt;a href="https://www.bloomberg.com/news/articles/2024-06-11/spotify-to-introduce-more-expensive-subscription-tier-for-music-lovers?srnd=telecom&amp;amp;embedded-checkout=true"&gt;一份報告來自&lt;em&gt;彭博社&lt;/em&gt;&lt;/a&gt;。&lt;/p&gt;&lt;/div&gt;&lt;div class="duet--article--article-body-component"&gt;&lt;p class="duet--article--dangerously-set-cms-markup duet--article--standard-paragraph mb-20 font-fkroman text-18 leading-160 -tracking-1 selection:bg-franklin-20 dark:text-white dark:selection:bg-blurple [&amp;amp;_a:hover]:shadow-highlight-franklin dark:[&amp;amp;_a:hover]:shadow-highlight-blurple [&amp;amp;_a]:shadow-underline-black dark:[&amp;amp;_a]:shadow-underline-white"&gt;一位熟悉 Spotify 的消息人士透露&lt;em&gt;彭博社&lt;/em&gt;用户將能夠將 HiFi 音頻層添加到他們現有的計劃中。&lt;a href="https://www.theverge.com/2024/6/3/24170301/spotify-us-price-increase-plans"&gt;下個月價格上漲至 11.99 美元&lt;/a&gt;，售價為 16.99 美元。&lt;em&gt;彭博社&lt;/em&gt;據報道，該附加組件還將使用户能夠為特定活動、日期和一年中的時間生成自定義播放列表。&lt;em&gt;The Verge&lt;/em&gt;聯繫 Spotify 請求置評，但沒有立即收到回覆。&lt;/p&gt;&lt;/div&gt;&lt;div class="duet--article--article-body-component clear-both block md:float-left md:mr-30 md:w-[320px] lg:-ml-100"&gt;&lt;div class="duet--article--sidebar bg-gray-200 mb-20 w-full rounded-sm bg-[#F8F5FF] p-20 [&amp;amp;&amp;gt;*:last-child&amp;gt;*:last-child]:mb-0"&gt;&lt;div class="[&amp;amp;_*]:mb-10 [&amp;amp;_*]:ml-0 [&amp;amp;_*]:mt-4 [&amp;amp;_h2]:lg:text-33 [&amp;amp;_h3]:lg:text-26 [&amp;amp;_h5]:text-black"&gt;&lt;h5 class="duet--article--dangerously-set-cms-markup duet--article--standard-heading my-20 font-polysans-mono text-13 font-medium uppercase leading-110 tracking-12 text-blurple selection:bg-franklin-20 dark:selection:bg-blurple [&amp;amp;&amp;gt;a:hover]:shadow-highlight-franklin [&amp;amp;&amp;gt;a]:shadow-underline-blurple-1"&gt;&lt;strong&gt;您對 Spotify HiFi 或即將推出的「Supremium」計劃瞭解更多嗎？&lt;/strong&gt;&lt;/h5&gt;&lt;/div&gt;&lt;div class="[&amp;amp;_p]:font-polysans [&amp;amp;_p]:text-16 [&amp;amp;_p]:font-light [&amp;amp;_p]:leading-130"&gt;&lt;p class="duet--article--dangerously-set-cms-markup duet--article--standard-paragraph mb-20 font-fkroman text-18 leading-160 -tracking-1 selection:bg-franklin-20 dark:text-white dark:selection:bg-blurple [&amp;amp;_a:hover]:shadow-highlight-franklin dark:[&amp;amp;_a:hover]:shadow-highlight-blurple [&amp;amp;_a]:shadow-underline-black dark:[&amp;amp;_a]:shadow-underline-white"&gt;人們應該得到整個故事，所以讓我們把它交給他們。&lt;strong&gt; &lt;/strong&gt;如果你瞭解事情的現狀，&lt;strong&gt; &lt;/strong&gt;don’t hesitate to message Chris Welch confidentially and securely with Signal at 845-445-8455. Alternatively, you can email welch@theverge.com or contact him via &lt;a href="https://www.instagram.com/chriswelch/"&gt;Instagram&lt;/a&gt;或者&lt;a href="https://twitter.com/chriswelch"&gt;X / Twitter DM&lt;/a&gt;.&lt;/p&gt;&lt;/div&gt;&lt;/div&gt;&lt;/div&gt;&lt;div class="duet--article--article-body-component"&gt;&lt;p class="duet--article--dangerously-set-cms-markup duet--article--standard-paragraph mb-20 font-fkroman text-18 leading-160 -tracking-1 selection:bg-franklin-20 dark:text-white dark:selection:bg-blurple [&amp;amp;_a:hover]:shadow-highlight-franklin dark:[&amp;amp;_a:hover]:shadow-highlight-blurple [&amp;amp;_a]:shadow-underline-black dark:[&amp;amp;_a]:shadow-underline-white"&gt;Spotify 最初表示&lt;a href="https://www.theverge.com/2021/2/22/22295273/spotify-hifi-announced-lossless-streaming-hd-quality"&gt;HiFi 音頻功能將於 2021 年推出&lt;/a&gt;，但這從未發生過。&lt;a href="https://www.theverge.com/2023/6/20/22746337/spotify-hifi-lossless-new-premium-tier-supremium"&gt;報告來自&lt;em&gt;彭博社&lt;/em&gt;揭示了該服務&lt;/a&gt;正在制定價格更高的「Supremium」HiFi 計劃。&lt;a href="https://www.theverge.com/2024/4/12/24128218/spotify-music-remix-feature-sped-up-tiktok-songs"&gt;報告來自&lt;em&gt;華爾街日報&lt;/em&gt;&lt;/a&gt;表明 Spotify 可以捆綁混音功能來加速插件中的曲目。&lt;/p&gt;&lt;/div&gt;&lt;div class="duet--article--article-body-component"&gt;&lt;p class="duet--article--dangerously-set-cms-markup duet--article--standard-paragraph mb-20 font-fkroman text-18 leading-160 -tracking-1 selection:bg-franklin-20 dark:text-white dark:selection:bg-blurple [&amp;amp;_a:hover]:shadow-highlight-franklin dark:[&amp;amp;_a:hover]:shadow-highlight-blurple [&amp;amp;_a]:shadow-underline-black dark:[&amp;amp;_a]:shadow-underline-white"&gt;去年，Spotify 應用程序中也發現了代碼&lt;a href="https://www.theverge.com/2023/9/21/23884577/spotify-supremium-lossless-audio-tier-code"&gt;建議該層可能帶有&lt;/a&gt;24 位無損音頻、使用 AI 創建播放列表的功能、按心情過濾播放列表中的歌曲的功能等等。&lt;a href="https://www.theverge.com/2024/4/12/24128584/spotify-music-pro-lossless-audio"&gt;Reddit 用户發現了一串代碼&lt;/a&gt;在應用程序中顯示「無損已經到來」，而稍後另一個 Reddit 用户&lt;a href="https://www.theverge.com/2024/5/3/24147887/spotify-hifi-lossless-audio-music-streaming-ui-leak"&gt;發佈了泄露的 UI 元素&lt;/a&gt;提到高達 2,117kbps 的無損質量以及使用 FLAC 音頻格式的「有限歌曲」的 24 位/44.1kHz 的可用性。&lt;/p&gt;&lt;/div&gt;&lt;/div&gt;&lt;div class="mb-40 mt-30"&gt;&lt;button class="duet--article--comments-button group inline-flex h-40 w-full items-center justify-center rounded-[2px] border-[1px] border-solid border-blurple font-polysans-mono text-11 font-light uppercase tracking-12 text-blurple hover:bg-blurple hover:text-white md:w-auto md:px-30"&gt;&lt;svg class="mr-10 inline pt-2" fill="none" height="14" stroke-width="1px" viewbox="0 0 12 12" width="12"
            xmlns="http://www.w3.org/2000/svg"&gt;&lt;title&gt;Comments&lt;/title&gt;&lt;path d="M2.4 9.1h-.207l-.147.146L.5 10.793V1.2c0-.384.316-.7.7-.7h9.6c.384 0 .7.316.7.7v7.2c0 .384-.316.7-.7.7H2.4Z" stroke="currentColor"&gt;&lt;/path&gt;&lt;/svg&gt;&lt;span class="coral-count"&gt;&lt;/span&gt;&lt;/button&gt;&lt;/div&gt;
        </summary>
        <published>2024-06-11T13:02:05+00:00</published>
    </entry>
    <entry>
        <id>https://www.theverge.com/24173628/ai-pc-raspberry-pi-hit-man-rivian-chromatic-installer</id>
        <title>一台你想要擺弄的人工智能電腦</title>
        <updated>2024-06-09T12:00:00+00:00</updated>
        <author>
            <name>David Pierce</name>
        </author>
        <link href="https://www.theverge.com/24173628/ai-pc-raspberry-pi-hit-man-rivian-chromatic-installer"/>
        <summary type="html">&lt;h2 class="inline selection:bg-franklin-20"&gt;另外，在本週的安裝程序中：一部關於殺手的熱門電影、FBI 技術奇案、用於管理媒體的應用程序等等。&lt;/h2&gt;&lt;img src="https://cdn.vox-cdn.com/thumbor/cwZx8iU1MJ7gOftwCQFRnd4efxE=/0x0:2181x1455/1200x628/filters:focal(1091x728:1092x729)/cdn.vox-cdn.com/uploads/chorus_asset/file/25481662/installer_41.png"/&gt;&lt;div&gt;&lt;div class="duet--article--article-body-component"&gt;&lt;p class="duet--article--dangerously-set-cms-markup duet--article--standard-paragraph mb-20 font-fkroman text-18 leading-160 -tracking-1 selection:bg-franklin-20 dark:text-white dark:selection:bg-blurple [&amp;amp;_a:hover]:shadow-highlight-franklin dark:[&amp;amp;_a:hover]:shadow-highlight-blurple [&amp;amp;_a]:shadow-underline-black dark:[&amp;amp;_a]:shadow-underline-white"&gt;嗨，朋友們！&lt;em&gt;安裝人員&lt;/em&gt;第 41 期，您的最佳指南&lt;em&gt;邊緣&lt;/em&gt;-世界上最棒的東西。 &lt;a href="https://www.theverge.com/installer-newsletter"&gt;&lt;em&gt;安裝人員&lt;/em&gt;主頁&lt;/a&gt;.) &lt;/p&gt;&lt;/div&gt;&lt;div class="duet--article--article-body-component"&gt;&lt;p class="duet--article--dangerously-set-cms-markup duet--article--standard-paragraph mb-20 font-fkroman text-18 leading-160 -tracking-1 selection:bg-franklin-20 dark:text-white dark:selection:bg-blurple [&amp;amp;_a:hover]:shadow-highlight-franklin dark:[&amp;amp;_a:hover]:shadow-highlight-blurple [&amp;amp;_a]:shadow-underline-black dark:[&amp;amp;_a]:shadow-underline-white"&gt;這周，我讀到了&lt;a href="https://www.nytimes.com/2024/06/06/technology/humane-ai-pin.html?smid=nytcore-ios-share&amp;amp;sgrp=c-cb"&gt;&lt;strong&gt;人道主義的艱難時期&lt;/strong&gt;&lt;/a&gt;和&lt;a href="https://www.bloomberg.com/news/articles/2024-06-06/-suicide-squad-warner-bros-s-200-million-flop-haunts-the-gaming-industry?accessToken=eyJhbGciOiJIUzI1NiIsInR5cCI6IkpXVCJ9.eyJzb3VyY2UiOiJTdWJzY3JpYmVyR2lmdGVkQXJ0aWNsZSIsImlhdCI6MTcxNzY3NzY3MSwiZXhwIjoxNzE4MjgyNDcxLCJhcnRpY2xlSWQiOiJTRU5QQUlEV0xVNjgwMCIsImJjb25uZWN0SWQiOiJCMUVBQkI5NjQ2QUM0REZFQTJBRkI4MjI1MzgyQTJFQSJ9.w4OIlWguMfYk-NkNMnefg8NnCt9rIJFeBodZhB8DmhM"&gt;&lt;strong&gt;如何&lt;em&gt;自殺小隊&lt;/em&gt;失敗了&lt;/strong&gt;&lt;/a&gt;， 觀看&lt;a href="https://www.themoviedb.org/tv/253384-dancing-for-the-devil-the-7m-tiktok-cult"&gt;&lt;strong&gt;TikTok 舞蹈邪教紀錄片&lt;/strong&gt;&lt;/a&gt;和&lt;a href="https://www.themoviedb.org/movie/786892-furiosa-a-mad-max-saga?language=en-US"&gt;&lt;em&gt;&lt;strong&gt;生氣的&lt;/strong&gt;&lt;/em&gt;&lt;/a&gt;&lt;em&gt;, &lt;/em&gt;把我蹩腳的 Roku 換成稍微蹩腳的 Apple TV，聽了很多歌&lt;a href="https://wondery.com/shows/wikihole-with-darcy-carden/"&gt;&lt;em&gt;&lt;strong&gt;維基洞&lt;/strong&gt;&lt;/em&gt;&lt;/a&gt;&lt;em&gt;, &lt;/em&gt;混合新的無酒精雞尾酒配方，並測試&lt;a href="https://phanpy.social/"&gt;&lt;strong&gt;潘皮&lt;/strong&gt;&lt;/a&gt;適用於所有 Fediverse 事物的應用程序。&lt;/p&gt;&lt;/div&gt;&lt;div class="duet--article--article-body-component"&gt;&lt;p class="duet--article--dangerously-set-cms-markup duet--article--standard-paragraph mb-20 font-fkroman text-18 leading-160 -tracking-1 selection:bg-franklin-20 dark:text-white dark:selection:bg-blurple [&amp;amp;_a:hover]:shadow-highlight-franklin dark:[&amp;amp;_a:hover]:shadow-highlight-blurple [&amp;amp;_a]:shadow-underline-black dark:[&amp;amp;_a]:shadow-underline-white"&gt;我還為您準備了一個新的 Raspberry Pi 配件、一部本週末值得觀看的非常受歡迎的電影、幾本有趣的科技書籍、一些遊戲裝備等等。&lt;/p&gt;&lt;/div&gt;&lt;div class="duet--article--article-body-component"&gt;&lt;p class="duet--article--dangerously-set-cms-markup duet--article--standard-paragraph mb-20 font-fkroman text-18 leading-160 -tracking-1 selection:bg-franklin-20 dark:text-white dark:selection:bg-blurple [&amp;amp;_a:hover]:shadow-highlight-franklin dark:[&amp;amp;_a:hover]:shadow-highlight-blurple [&amp;amp;_a]:shadow-underline-black dark:[&amp;amp;_a]:shadow-underline-white"&gt;（一如既往，最好的部分&lt;em&gt;安裝人員&lt;/em&gt;是你的想法和技巧。&lt;a href="mailto:installer@theverge.com"&gt;installer@theverge.com&lt;/a&gt;， 與某人分享&lt;a href="https://www.threads.net/@imdavidpierce"&gt;@imdavidpierce&lt;/a&gt; on Threads, or find me on Signal @davidpierce.11. And if you know someone else who might enjoy &lt;em&gt;安裝人員&lt;/em&gt;，告訴他們&lt;a href="https://www.theverge.com/pages/installer-newsletter-sign-up"&gt;在這裏訂閲&lt;/a&gt;.)&lt;/p&gt;&lt;/div&gt;&lt;div class="duet--article--article-body-component"&gt;&lt;hr class="duet--layout--standard-divider my-36 border-0 border-b border-gray-94"/&gt;&lt;/div&gt;&lt;div class="duet--article--article-body-component"&gt;&lt;h3 class="duet--article--dangerously-set-cms-markup duet--article--standard-heading mb-20 mt-40 font-polysans text-26 font-medium leading-110 selection:bg-franklin-20 dark:text-white dark:selection:bg-blurple md:text-30 [&amp;amp;&amp;gt;a:hover]:shadow-highlight-franklin dark:[&amp;amp;&amp;gt;a:hover]:shadow-highlight-franklin [&amp;amp;&amp;gt;a]:shadow-underline-black dark:[&amp;amp;&amp;gt;a]:shadow-underline-white"&gt;掉落&lt;/h3&gt;&lt;/div&gt;&lt;div class="duet--article--article-body-component"&gt;&lt;ul class="duet--article--unordered-list my-20 list-disc pl-18 marker:text-blurple/100 selection:bg-franklin-20 dark:text-white dark:selection:bg-blurple [&amp;amp;_a:hover]:shadow-highlight-franklin dark:[&amp;amp;_a:hover]:shadow-highlight-franklin [&amp;amp;_a]:shadow-underline-black dark:[&amp;amp;_a]:shadow-underline-white"&gt;&lt;li class="duet--article--dangerously-set-cms-markup mb-16 pl-12 font-fkroman text-18 leading-160 -tracking-1"&gt;&lt;a href="https://www.raspberrypi.com/products/ai-kit/"&gt;&lt;strong&gt;Raspberry Pi 人工智能套件&lt;/strong&gt;&lt;/a&gt;&lt;em&gt;&lt;strong&gt;. &lt;/strong&gt;&lt;/em&gt;這是我喜歡的 AI PC：一個超級簡單的 70 美元套件，可與 Raspberry Pi 5 配合使用，併為您提供令人驚訝的強大功能來完成簡單的處理任務。&lt;/li&gt;&lt;li class="duet--article--dangerously-set-cms-markup mb-16 pl-12 font-fkroman text-18 leading-160 -tracking-1"&gt;&lt;a href="https://www.themoviedb.org/movie/974635-hit-man"&gt;&lt;em&gt;&lt;strong&gt;殺手&lt;/strong&gt;&lt;/em&gt;&lt;/a&gt;&lt;em&gt;&lt;strong&gt;. &lt;/strong&gt;&lt;/em&gt;一羣非常聰明的人説這部 Netflix 喜劇動作驚悚片是今年最好的電影之一。&lt;a href="https://www.texasmonthly.com/true-crime/hit-man-2/"&gt;雜誌文章的歷史記錄&lt;/a&gt;。&lt;/li&gt;&lt;li class="duet--article--dangerously-set-cms-markup mb-16 pl-12 font-fkroman text-18 leading-160 -tracking-1"&gt;&lt;a href="https://www.hachettebookgroup.com/titles/joseph-cox/dark-wire/9781541702691/"&gt;&lt;em&gt;&lt;strong&gt;暗線&lt;/strong&gt;&lt;/em&gt;&lt;/a&gt;&lt;em&gt;&lt;strong&gt;. &lt;/strong&gt;&lt;/em&gt;這是我見過的最好的一本書的前提：聯邦調查局秘密科技初創公司的故事，旨在追蹤世界上一些最狡猾的罪犯。 &lt;a href="https://www.wired.com/story/inside-biggest-fbi-sting-operation-in-history/"&gt;幾個地方&lt;/a&gt;有&lt;a href="https://www.404media.co/dark-wire-inside-a-kidnapping-planned-on-the-fbis-secret-chat-app/"&gt;發表的摘錄&lt;/a&gt;，我已經無法放下這本書了。&lt;/li&gt;&lt;li class="duet--article--dangerously-set-cms-markup mb-16 pl-12 font-fkroman text-18 leading-160 -tracking-1"&gt;&lt;a href="https://www.penguinrandomhouse.com/books/744393/building-simcity-by-chaim-gingold-foreword-by-janet-h-murray/"&gt;&lt;em&gt;&lt;strong&gt;構建模擬城市&lt;/strong&gt;&lt;/em&gt;&lt;/a&gt;&lt;em&gt;&lt;strong&gt;. &lt;/strong&gt;&lt;/em&gt;這周有兩本書！&lt;/li&gt;&lt;li class="duet--article--dangerously-set-cms-markup mb-16 pl-12 font-fkroman text-18 leading-160 -tracking-1"&gt;&lt;a href="https://rivian.com/r1s"&gt;&lt;strong&gt;新款 Rivian R1&lt;/strong&gt;&lt;/a&gt;&lt;strong&gt;.&lt;/strong&gt;相同的外觀，相同的時髦前燈設計，下面是全新的汽車。 &lt;a href="https://www.theverge.com/2024/6/6/24172761/rivian-r1t-r1s-refresh-update-motor-battery-price"&gt;顯然只是為了降低成本&lt;/a&gt;，但這仍然是我最渴望的電動汽車。&lt;/li&gt;&lt;li class="duet--article--dangerously-set-cms-markup mb-16 pl-12 font-fkroman text-18 leading-160 -tracking-1"&gt;&lt;a href="https://www.themoviedb.org/tv/114479-the-acolyte"&gt;&lt;em&gt;&lt;strong&gt;侍僧&lt;/strong&gt;&lt;/em&gt;&lt;/a&gt;&lt;em&gt;&lt;strong&gt;.&lt;/strong&gt; &lt;/em&gt;這是一個非常不同的星球大戰故事，發生在一個非常不同的時間和地點，從一個非常不同的角度講述，所有這些我絕對認為是一件好事。&lt;/li&gt;&lt;li class="duet--article--dangerously-set-cms-markup mb-16 pl-12 font-fkroman text-18 leading-160 -tracking-1"&gt;&lt;a href="https://www.getsequel.app/"&gt;&lt;strong&gt;續集 2.3&lt;/strong&gt;&lt;/a&gt;&lt;strong&gt;.&lt;/strong&gt;&lt;em&gt; &lt;/em&gt;一個非常酷的更新&lt;a href="https://www.theverge.com/23915813/sequel-sofa-media-tracking-apps-roblox-razr-big-vape-installer-newsletter"&gt;Installerverse 最喜歡的媒體跟蹤應用程序&lt;/a&gt;對於蘋果設備。&lt;/li&gt;&lt;li class="duet--article--dangerously-set-cms-markup mb-16 pl-12 font-fkroman text-18 leading-160 -tracking-1"&gt;&lt;a href="https://modretro.com/"&gt;&lt;strong&gt;ModRetro 半音階&lt;/strong&gt;&lt;/a&gt;&lt;strong&gt;.&lt;/strong&gt;我們現在所處的復古遊戲硬件熱潮是最好的事情。&lt;em&gt;偉大的。&lt;/em&gt;它要到今年年底才會發貨，但現在已經可以預訂了。&lt;/li&gt;&lt;li class="duet--article--dangerously-set-cms-markup mb-16 pl-12 font-fkroman text-18 leading-160 -tracking-1"&gt;&lt;a href="https://go.skimresources.com/?id=1025X1701640&amp;amp;xs=1&amp;amp;url=https%3A%2F%2Fgo.skimresources.com%3Fid%3D1025X1701640%26xs%3D1%26url%3Dhttps%253A%252F%252Frog.asus.com%252Fus%252Fgaming-handhelds%252Frog-ally%252Frog-ally-x-2024%252F"&gt;&lt;strong&gt;華碩 ROG Ally X&lt;/strong&gt;&lt;/a&gt;&lt;strong&gt;. &lt;/strong&gt;説到便攜式遊戲機！&lt;a href="https://www.theverge.com/2024/6/2/24169709/asus-rog-ally-x-price-release-date-inside-gaming-handheld"&gt;真正經得起 Steam Deck 的考驗&lt;/a&gt;?&lt;/li&gt;&lt;li class="duet--article--dangerously-set-cms-markup mb-16 pl-12 font-fkroman text-18 leading-160 -tracking-1"&gt;&lt;a href="https://www.macstories.net/comfort-zone/"&gt;&lt;em&gt;&lt;strong&gt;舒適區&lt;/strong&gt;&lt;/em&gt;&lt;/a&gt;&lt;em&gt;&lt;strong&gt;.&lt;/strong&gt; &lt;/em&gt;來自 MacStories 團隊的有趣的新播客，有一個我非常喜歡的花招：每週，三位主持人基本上必須進行「技術展示和講述」，然後發出與技術相關的挑戰，以在下一集之前完成。 &lt;a href="https://www.macstories.net/npc/"&gt;&lt;em&gt;&lt;strong&gt;全國人大&lt;/strong&gt;&lt;/em&gt;&lt;/a&gt;，關於便攜式遊戲的一切。&lt;/li&gt;&lt;li class="duet--article--dangerously-set-cms-markup mb-16 pl-12 font-fkroman text-18 leading-160 -tracking-1"&gt;&lt;a href="https://crooked.com/podcast/how-wall-e-reveals-our-changing-feelings-toward-tech/"&gt;&lt;strong&gt;「《機器人總動員》如何揭示了我們對科技不斷變化的看法。」&lt;/strong&gt;&lt;/a&gt;&lt;strong&gt; &lt;/strong&gt;我非常嫉妒這一系列的情節&lt;em&gt;離線&lt;/em&gt;播客，看看電影怎麼樣&lt;em&gt;她&lt;/em&gt;和&lt;em&gt;社交網絡&lt;/em&gt;影響了我們思考和構建技術的方式。&lt;/li&gt;&lt;/ul&gt;&lt;/div&gt;&lt;div class="duet--article--article-body-component"&gt;&lt;hr class="duet--layout--standard-divider my-36 border-0 border-b border-gray-94"/&gt;&lt;/div&gt;&lt;div class="duet--article--article-body-component"&gt;&lt;h3 class="duet--article--dangerously-set-cms-markup duet--article--standard-heading mb-20 mt-40 font-polysans text-26 font-medium leading-110 selection:bg-franklin-20 dark:text-white dark:selection:bg-blurple md:text-30 [&amp;amp;&amp;gt;a:hover]:shadow-highlight-franklin dark:[&amp;amp;&amp;gt;a:hover]:shadow-highlight-franklin [&amp;amp;&amp;gt;a]:shadow-underline-black dark:[&amp;amp;&amp;gt;a]:shadow-underline-white"&gt;屏幕共享&lt;/h3&gt;&lt;/div&gt;&lt;div class="duet--article--article-body-component"&gt;&lt;p class="duet--article--dangerously-set-cms-markup duet--article--standard-paragraph mb-20 font-fkroman text-18 leading-160 -tracking-1 selection:bg-franklin-20 dark:text-white dark:selection:bg-blurple [&amp;amp;_a:hover]:shadow-highlight-franklin dark:[&amp;amp;_a:hover]:shadow-highlight-blurple [&amp;amp;_a]:shadow-underline-black dark:[&amp;amp;_a]:shadow-underline-white"&gt;好吧，朋友們，這花了 41 個問題，但事情發生了：這周我有人排隊參加屏幕共享，但它沒有及時聚集。&lt;a href="https://niagaralauncher.app/"&gt;&lt;strong&gt;尼亞加拉發射器&lt;/strong&gt;&lt;/a&gt;理論上，它在很大程度上針對單手手機使用進行了優化，但也是一種更好、更安靜的組織主屏幕的方式。&lt;/p&gt;&lt;/div&gt;&lt;div class="duet--article--article-body-component"&gt;&lt;p class="duet--article--dangerously-set-cms-markup duet--article--standard-paragraph mb-20 font-fkroman text-18 leading-160 -tracking-1 selection:bg-franklin-20 dark:text-white dark:selection:bg-blurple [&amp;amp;_a:hover]:shadow-highlight-franklin dark:[&amp;amp;_a:hover]:shadow-highlight-blurple [&amp;amp;_a]:shadow-underline-black dark:[&amp;amp;_a]:shadow-underline-white"&gt;尼亞加拉真是太聰明瞭！&lt;a href="https://go.skimresources.com/?id=1025X1701640&amp;amp;xs=1&amp;amp;url=https%3A%2F%2Fwww.youtube.com%2Fwatch%3Fv%3DW9U-T_LbIak"&gt;&lt;strong&gt;一個很好的完整視頻&lt;/strong&gt;&lt;/a&gt;觀看。）&lt;/p&gt;&lt;/div&gt;&lt;div class="duet--article--article-body-component"&gt;&lt;p class="duet--article--dangerously-set-cms-markup duet--article--standard-paragraph mb-20 font-fkroman text-18 leading-160 -tracking-1 selection:bg-franklin-20 dark:text-white dark:selection:bg-blurple [&amp;amp;_a:hover]:shadow-highlight-franklin dark:[&amp;amp;_a:hover]:shadow-highlight-blurple [&amp;amp;_a]:shadow-underline-black dark:[&amp;amp;_a]:shadow-underline-white"&gt;Niagara 也剛剛進行了一次重大更新，特別是如果您支付每年 10 美元或 30 美元終身 Pro 訂閲的話。&lt;/p&gt;&lt;/div&gt;&lt;div class="duet--article--article-body-component"&gt;&lt;p class="duet--article--dangerously-set-cms-markup duet--article--standard-paragraph mb-20 font-fkroman text-18 leading-160 -tracking-1 selection:bg-franklin-20 dark:text-white dark:selection:bg-blurple [&amp;amp;_a:hover]:shadow-highlight-franklin dark:[&amp;amp;_a:hover]:shadow-highlight-blurple [&amp;amp;_a]:shadow-underline-black dark:[&amp;amp;_a]:shadow-underline-white"&gt;當我一直在修改自己的主屏幕時，我一直在收集一些我喜歡的 Niagara 設置，我想我應該分享一些。&lt;/p&gt;&lt;/div&gt;&lt;div class="duet--article--article-body-component clear-both block"&gt;&lt;div class="my-9"&gt;&lt;div class="transition-all duration-300 ease-in-out"&gt;&lt;div class="fixed inset-0 h-[110vh] w-full bg-white transition-all duration-300 ease-in-out z-[-1] cursor-default opacity-0" tabindex="0"&gt;&lt;/div&gt;&lt;div class="visible z-30 w-full origin-center transition-all duration-300 ease-in-out cursor-zoom-in" tabindex="0"&gt;&lt;figure class="transition-all duration-300 ease-in-out lg:mx-0"&gt;&lt;div&gt;&lt;div class="duet--media--content-warning relative"&gt;&lt;span style="display: block; overflow: hidden; width: initial; height: initial; background: none; border: 0; margin: 0; padding: 0;"&gt;&lt;img alt="" src="data:image/gif;base64,R0lGODlhAQABAIAAAAAAAP///yH5BAEAAAAALAAAAAABAAEAAAIBRAA7" style="padding: 0; border: none; margin: auto; display: block; width: 0; height: 0;"/&gt;&lt;noscript&gt;&lt;img alt="" src="https://duet-cdn.vox-cdn.com/thumbor/0x0:3548x3119/2400x2110/filters:focal(1774x1560:1775x1561):format(webp)/cdn.vox-cdn.com/uploads/chorus_asset/file/25481666/Niagara_Stuff.jpg" style="padding: 0; border: none; margin: auto; display: block; width: 0; height: 0;"/&gt;&lt;/noscript&gt;&lt;/span&gt;&lt;/div&gt;&lt;/div&gt;&lt;/figure&gt;&lt;/div&gt;&lt;div class="z-1 w-full hidden"&gt;&lt;figure class="transition-all duration-300 ease-in-out lg:mx-0"&gt;&lt;div&gt;&lt;div class="duet--media--content-warning relative"&gt;&lt;span style="display: block; overflow: hidden; width: initial; height: initial; background: none; border: 0; margin: 0; padding: 0;"&gt;&lt;img alt="" src="data:image/gif;base64,R0lGODlhAQABAIAAAAAAAP///yH5BAEAAAAALAAAAAABAAEAAAIBRAA7" style="padding: 0; border: none; margin: auto; display: block; width: 0; height: 0;"/&gt;&lt;noscript&gt;&lt;img alt="" src="https://duet-cdn.vox-cdn.com/thumbor/0x0:3548x3119/2400x2110/filters:focal(1774x1560:1775x1561):format(webp)/cdn.vox-cdn.com/uploads/chorus_asset/file/25481666/Niagara_Stuff.jpg" style="padding: 0; border: none; margin: auto; display: block; width: 0; height: 0;"/&gt;&lt;/noscript&gt;&lt;/span&gt;&lt;/div&gt;&lt;/div&gt;&lt;/figure&gt;&lt;/div&gt;&lt;/div&gt;&lt;/div&gt;&lt;/div&gt;&lt;div class="duet--article--article-body-component"&gt;&lt;p class="duet--article--dangerously-set-cms-markup duet--article--standard-paragraph mb-20 font-fkroman text-18 leading-160 -tracking-1 selection:bg-franklin-20 dark:text-white dark:selection:bg-blurple [&amp;amp;_a:hover]:shadow-highlight-franklin dark:[&amp;amp;_a:hover]:shadow-highlight-blurple [&amp;amp;_a]:shadow-underline-black dark:[&amp;amp;_a]:shadow-underline-white"&gt;&lt;em&gt;（頂行：&lt;/em&gt;&lt;a href="https://x.com/sm0ke_screens/status/1611399108224507904"&gt;&lt;em&gt;@sm0ke_screens&lt;/em&gt;&lt;/a&gt;&lt;em&gt; / &lt;/em&gt;&lt;a href="https://www.threads.net/@iamankursjain/post/C5r3xysKOLH"&gt;&lt;em&gt;@iamankursjain&lt;/em&gt;&lt;/a&gt;&lt;em&gt; / &lt;/em&gt;&lt;a href="https://www.threads.net/@justinbelcher/post/C717rHJvYEZ"&gt;&lt;em&gt;@justinbelcher&lt;/em&gt;&lt;/a&gt;&lt;em&gt; / &lt;/em&gt;&lt;a href="https://www.threads.net/@imaginationmatters6/post/C4s2YnJvhhY"&gt;&lt;em&gt;@想象力很重要 6&lt;/em&gt;&lt;/a&gt;&lt;em&gt;。&lt;/em&gt;&lt;a href="https://www.threads.net/@kustom_bee/post/Cu2Em4syUWj"&gt;&lt;em&gt;@kustom_bee&lt;/em&gt;&lt;/a&gt;&lt;em&gt; / &lt;/em&gt;&lt;a href="https://x.com/SandeepAugusti3/status/1550086116006629377"&gt;&lt;em&gt;@SandeepAugusti3&lt;/em&gt;&lt;/a&gt;&lt;em&gt; / &lt;/em&gt;&lt;a href="https://x.com/KushalWagh/status/1567394452586795010"&gt;&lt;em&gt;@KushalWagh&lt;/em&gt;&lt;/a&gt;&lt;em&gt;)&lt;/em&gt;&lt;/p&gt;&lt;/div&gt;&lt;div class="duet--article--article-body-component"&gt;&lt;p class="duet--article--dangerously-set-cms-markup duet--article--standard-paragraph mb-20 font-fkroman text-18 leading-160 -tracking-1 selection:bg-franklin-20 dark:text-white dark:selection:bg-blurple [&amp;amp;_a:hover]:shadow-highlight-franklin dark:[&amp;amp;_a:hover]:shadow-highlight-blurple [&amp;amp;_a]:shadow-underline-black dark:[&amp;amp;_a]:shadow-underline-white"&gt;很酷，對吧？&lt;/p&gt;&lt;/div&gt;&lt;div class="duet--article--article-body-component"&gt;&lt;hr class="duet--layout--standard-divider my-36 border-0 border-b border-gray-94"/&gt;&lt;/div&gt;&lt;div class="duet--article--article-body-component"&gt;&lt;h3 class="duet--article--dangerously-set-cms-markup duet--article--standard-heading mb-20 mt-40 font-polysans text-26 font-medium leading-110 selection:bg-franklin-20 dark:text-white dark:selection:bg-blurple md:text-30 [&amp;amp;&amp;gt;a:hover]:shadow-highlight-franklin dark:[&amp;amp;&amp;gt;a:hover]:shadow-highlight-franklin [&amp;amp;&amp;gt;a]:shadow-underline-black dark:[&amp;amp;&amp;gt;a]:shadow-underline-white"&gt;眾包&lt;/h3&gt;&lt;/div&gt;&lt;div class="duet--article--article-body-component"&gt;&lt;p class="duet--article--dangerously-set-cms-markup duet--article--standard-paragraph mb-20 font-fkroman text-18 leading-160 -tracking-1 selection:bg-franklin-20 dark:text-white dark:selection:bg-blurple [&amp;amp;_a:hover]:shadow-highlight-franklin dark:[&amp;amp;_a:hover]:shadow-highlight-blurple [&amp;amp;_a]:shadow-underline-black dark:[&amp;amp;_a]:shadow-underline-white"&gt;&lt;em&gt;這是什麼&lt;/em&gt;安裝人員&lt;em&gt;社區已進入本週。&lt;/em&gt;&lt;a href="mailto:installer@theverge.com"&gt;&lt;em&gt;installer@theverge.com&lt;/em&gt;&lt;/a&gt;&lt;em&gt; or message me on Signal — @davidpierce.11 — with your recommendations for anything and everything, and we’ll feature some of our favorites here every week. &lt;/em&gt;&lt;/p&gt;&lt;/div&gt;&lt;div class="duet--article--article-body-component"&gt;&lt;p class="duet--article--dangerously-set-cms-markup duet--article--standard-paragraph mb-20 font-fkroman text-18 leading-160 -tracking-1 selection:bg-franklin-20 dark:text-white dark:selection:bg-blurple [&amp;amp;_a:hover]:shadow-highlight-franklin dark:[&amp;amp;_a:hover]:shadow-highlight-blurple [&amp;amp;_a]:shadow-underline-black dark:[&amp;amp;_a]:shadow-underline-white"&gt;「新版本的&lt;a href="https://www.apposite.ai/"&gt;&lt;strong&gt;氛圍景觀&lt;/strong&gt;&lt;/a&gt;剛剛推出 Apple Vision Pro — 受俄勒岡海岸啓發的全新冥想環境！&lt;/p&gt;&lt;/div&gt;&lt;div class="duet--article--article-body-component"&gt;&lt;p class="duet--article--dangerously-set-cms-markup duet--article--standard-paragraph mb-20 font-fkroman text-18 leading-160 -tracking-1 selection:bg-franklin-20 dark:text-white dark:selection:bg-blurple [&amp;amp;_a:hover]:shadow-highlight-franklin dark:[&amp;amp;_a:hover]:shadow-highlight-blurple [&amp;amp;_a]:shadow-underline-black dark:[&amp;amp;_a]:shadow-underline-white"&gt;「我一直在使用&lt;a href="https://www.beeper.com/"&gt;&lt;strong&gt;蜂鳴器&lt;/strong&gt;&lt;/a&gt;我的 Pixel 8 Pro 和 MacBook Pro 上有很多。&lt;a href="https://www.theverge.com/2024/4/9/24124179/beeper-app-automattic-acquisition-matrix-messaging"&gt;收購公告出爐&lt;/a&gt;但一個月前我確實取得了進步。&lt;/p&gt;&lt;/div&gt;&lt;div class="duet--article--article-body-component"&gt;&lt;p class="duet--article--dangerously-set-cms-markup duet--article--standard-paragraph mb-20 font-fkroman text-18 leading-160 -tracking-1 selection:bg-franklin-20 dark:text-white dark:selection:bg-blurple [&amp;amp;_a:hover]:shadow-highlight-franklin dark:[&amp;amp;_a:hover]:shadow-highlight-blurple [&amp;amp;_a]:shadow-underline-black dark:[&amp;amp;_a]:shadow-underline-white"&gt;「&lt;a href="https://go.skimresources.com/?id=1025X1701640&amp;amp;xs=1&amp;amp;url=https%3A%2F%2Fwww.youtube.com%2F%40patrickhwillems"&gt;&lt;strong&gt;帕特里克·威廉姆斯&lt;/strong&gt;&lt;/a&gt;本週有一個新視頻關於&lt;a href="https://go.skimresources.com/?id=1025X1701640&amp;amp;xs=1&amp;amp;url=https%3A%2F%2Fwww.youtube.com%2Fwatch%3Fv%3DSW9b9VpVW0A"&gt;&lt;strong&gt;超級英雄電影之後接下來會發生什麼&lt;/strong&gt;&lt;/a&gt;所以過了一段時間我又回到了他的頻道。」 &lt;/p&gt;&lt;/div&gt;&lt;div class="duet--article--article-body-component"&gt;&lt;p class="duet--article--dangerously-set-cms-markup duet--article--standard-paragraph mb-20 font-fkroman text-18 leading-160 -tracking-1 selection:bg-franklin-20 dark:text-white dark:selection:bg-blurple [&amp;amp;_a:hover]:shadow-highlight-franklin dark:[&amp;amp;_a:hover]:shadow-highlight-blurple [&amp;amp;_a]:shadow-underline-black dark:[&amp;amp;_a]:shadow-underline-white"&gt;「一位朋友向我介紹&lt;a href="https://www.guildwars2.com/en/"&gt;&lt;em&gt;&lt;strong&gt;激戰 2&lt;/strong&gt;&lt;/em&gt;&lt;/a&gt;幾個月前。&lt;/p&gt;&lt;/div&gt;&lt;div class="duet--article--article-body-component"&gt;&lt;p class="duet--article--dangerously-set-cms-markup duet--article--standard-paragraph mb-20 font-fkroman text-18 leading-160 -tracking-1 selection:bg-franklin-20 dark:text-white dark:selection:bg-blurple [&amp;amp;_a:hover]:shadow-highlight-franklin dark:[&amp;amp;_a:hover]:shadow-highlight-blurple [&amp;amp;_a]:shadow-underline-black dark:[&amp;amp;_a]:shadow-underline-white"&gt;「我聽説了微軟的召回，這讓我感到疲憊和乏味。&lt;a href="https://bazzite.gg/"&gt;&lt;strong&gt;鋰鋁石&lt;/strong&gt;&lt;/a&gt;我的遊戲 PC 上安裝了 Linux 發行版，並且一直用這種方式玩我所有的 Steam 和 Epic 遊戲。&lt;/p&gt;&lt;/div&gt;&lt;div class="duet--article--article-body-component"&gt;&lt;p class="duet--article--dangerously-set-cms-markup duet--article--standard-paragraph mb-20 font-fkroman text-18 leading-160 -tracking-1 selection:bg-franklin-20 dark:text-white dark:selection:bg-blurple [&amp;amp;_a:hover]:shadow-highlight-franklin dark:[&amp;amp;_a:hover]:shadow-highlight-blurple [&amp;amp;_a]:shadow-underline-black dark:[&amp;amp;_a]:shadow-underline-white"&gt;「這&lt;em&gt;指環王&lt;/em&gt;電影終於&lt;strong&gt; &lt;/strong&gt;&lt;a href="https://www.fathomevents.com/series/the-lord-of-the-rings-trilogy/"&gt;&lt;strong&gt;回到劇院&lt;/strong&gt;&lt;/a&gt;。&lt;/p&gt;&lt;/div&gt;&lt;div class="duet--article--article-body-component"&gt;&lt;p class="duet--article--dangerously-set-cms-markup duet--article--standard-paragraph mb-20 font-fkroman text-18 leading-160 -tracking-1 selection:bg-franklin-20 dark:text-white dark:selection:bg-blurple [&amp;amp;_a:hover]:shadow-highlight-franklin dark:[&amp;amp;_a:hover]:shadow-highlight-blurple [&amp;amp;_a]:shadow-underline-black dark:[&amp;amp;_a]:shadow-underline-white"&gt;「觀看&lt;a href="https://www.themoviedb.org/tv/253268-who-killed-wcw"&gt;&lt;em&gt;&lt;strong&gt;誰殺死了 WCW？&lt;/strong&gt;&lt;/em&gt;&lt;/a&gt;從&lt;em&gt;副&lt;/em&gt;。&lt;/p&gt;&lt;/div&gt;&lt;div class="duet--article--article-body-component"&gt;&lt;p class="duet--article--dangerously-set-cms-markup duet--article--standard-paragraph mb-20 font-fkroman text-18 leading-160 -tracking-1 selection:bg-franklin-20 dark:text-white dark:selection:bg-blurple [&amp;amp;_a:hover]:shadow-highlight-franklin dark:[&amp;amp;_a:hover]:shadow-highlight-blurple [&amp;amp;_a]:shadow-underline-black dark:[&amp;amp;_a]:shadow-underline-white"&gt;「新節目&lt;a href="https://www.dropout.tv/thousandaires"&gt;&lt;em&gt;&lt;strong&gt;千富翁&lt;/strong&gt;&lt;/em&gt;&lt;/a&gt;&lt;em&gt; &lt;/em&gt;從輟學和&lt;a href="https://watch.2ndtry.tv/trolley-problems"&gt;&lt;em&gt;&lt;strong&gt;電車難題&lt;/strong&gt;&lt;/em&gt;&lt;/a&gt;&lt;em&gt; &lt;/em&gt;from 2nd Try 於本週首播，是現代媒體公司和創建自己的流媒體平台趨勢的搞笑和偉大的例子。」 &lt;/p&gt;&lt;/div&gt;&lt;div class="duet--article--article-body-component"&gt;&lt;p class="duet--article--dangerously-set-cms-markup duet--article--standard-paragraph mb-20 font-fkroman text-18 leading-160 -tracking-1 selection:bg-franklin-20 dark:text-white dark:selection:bg-blurple [&amp;amp;_a:hover]:shadow-highlight-franklin dark:[&amp;amp;_a:hover]:shadow-highlight-blurple [&amp;amp;_a]:shadow-underline-black dark:[&amp;amp;_a]:shadow-underline-white"&gt;「關於動畫觀看。&lt;a href="https://www.themoviedb.org/tv/207784?language=en-US"&gt;&lt;em&gt;&lt;strong&gt;地牢裏的美味&lt;/strong&gt;&lt;/em&gt;&lt;/a&gt;。&lt;/p&gt;&lt;/div&gt;&lt;div class="duet--article--article-body-component"&gt;&lt;hr class="duet--layout--standard-divider my-36 border-0 border-b border-gray-94"/&gt;&lt;/div&gt;&lt;div class="duet--article--article-body-component"&gt;&lt;h3 class="duet--article--dangerously-set-cms-markup duet--article--standard-heading mb-20 mt-40 font-polysans text-26 font-medium leading-110 selection:bg-franklin-20 dark:text-white dark:selection:bg-blurple md:text-30 [&amp;amp;&amp;gt;a:hover]:shadow-highlight-franklin dark:[&amp;amp;&amp;gt;a:hover]:shadow-highlight-franklin [&amp;amp;&amp;gt;a]:shadow-underline-black dark:[&amp;amp;&amp;gt;a]:shadow-underline-white"&gt;註銷&lt;/h3&gt;&lt;/div&gt;&lt;div class="duet--article--article-body-component"&gt;&lt;p class="duet--article--dangerously-set-cms-markup duet--article--standard-paragraph mb-20 font-fkroman text-18 leading-160 -tracking-1 selection:bg-franklin-20 dark:text-white dark:selection:bg-blurple [&amp;amp;_a:hover]:shadow-highlight-franklin dark:[&amp;amp;_a:hover]:shadow-highlight-blurple [&amp;amp;_a]:shadow-underline-black dark:[&amp;amp;_a]:shadow-underline-white"&gt;這周我想了很多&lt;a href="https://boz.com/articles/inbox-ten"&gt;&lt;strong&gt;一篇博文&lt;/strong&gt;&lt;/a&gt;Meta 的首席技術官 Andrew Bosworth 最近寫道。&lt;em&gt;沒有什麼&lt;/em&gt;而是試圖在生活中找到更易於管理的信息流。 &lt;/p&gt;&lt;/div&gt;&lt;div class="duet--article--article-body-component"&gt;&lt;p class="duet--article--dangerously-set-cms-markup duet--article--standard-paragraph mb-20 font-fkroman text-18 leading-160 -tracking-1 selection:bg-franklin-20 dark:text-white dark:selection:bg-blurple [&amp;amp;_a:hover]:shadow-highlight-franklin dark:[&amp;amp;_a:hover]:shadow-highlight-blurple [&amp;amp;_a]:shadow-underline-black dark:[&amp;amp;_a]:shadow-underline-white"&gt;下週見！&lt;/p&gt;&lt;/div&gt;&lt;/div&gt;&lt;div class="mb-40 mt-30"&gt;&lt;button class="duet--article--comments-button group inline-flex h-40 w-full items-center justify-center rounded-[2px] border-[1px] border-solid border-blurple font-polysans-mono text-11 font-light uppercase tracking-12 text-blurple hover:bg-blurple hover:text-white md:w-auto md:px-30"&gt;&lt;svg class="mr-10 inline pt-2" fill="none" height="14" stroke-width="1px" viewbox="0 0 12 12" width="12"
            xmlns="http://www.w3.org/2000/svg"&gt;&lt;title&gt;Comments&lt;/title&gt;&lt;path d="M2.4 9.1h-.207l-.147.146L.5 10.793V1.2c0-.384.316-.7.7-.7h9.6c.384 0 .7.316.7.7v7.2c0 .384-.316.7-.7.7H2.4Z" stroke="currentColor"&gt;&lt;/path&gt;&lt;/svg&gt;&lt;span class="coral-count"&gt;&lt;/span&gt;&lt;/button&gt;&lt;/div&gt;
        </summary>
        <published>2024-06-09T12:00:00+00:00</published>
    </entry>
    <entry>
        <id>https://www.theverge.com/2024/6/6/24173202/apple-password-manager-rumor-1password-lastpass</id>
        <title>蘋果可能會在下週推出新的「密碼」應用程序</title>
        <updated>2024-06-06T21:07:44+00:00</updated>
        <author>
            <name>Emma Roth</name>
        </author>
        <link href="https://www.theverge.com/2024/6/6/24173202/apple-password-manager-rumor-1password-lastpass"/>
        <summary type="html">&lt;h2 class="inline selection:bg-franklin-20"&gt;據彭博社報道，蘋果準備推出一款獨立的密碼和密鑰管理器，可在 iPhone、iPad、Mac、Vision Pro 和 Windows PC 上運行。&lt;/h2&gt;&lt;img src="https://cdn.vox-cdn.com/thumbor/4LNrvISWOzpoG9hF68SCMFgOuvI=/0x0:2040x1334/1200x628/filters:focal(1020x667:1021x668)/cdn.vox-cdn.com/uploads/chorus_asset/file/25299201/STK453_PRIVACY_B_CVirginia.jpg"/&gt;&lt;div&gt;&lt;div class="duet--article--article-body-component"&gt;&lt;p class="duet--article--dangerously-set-cms-markup duet--article--standard-paragraph mb-20 font-fkroman text-18 leading-160 -tracking-1 selection:bg-franklin-20 dark:text-white dark:selection:bg-blurple [&amp;amp;_a:hover]:shadow-highlight-franklin dark:[&amp;amp;_a:hover]:shadow-highlight-blurple [&amp;amp;_a]:shadow-underline-black dark:[&amp;amp;_a]:shadow-underline-white"&gt;據報道，蘋果計劃推出一款名為「Passwords」的新應用程序，幫助用户管理登錄信息。&lt;a href="https://www.bloomberg.com/news/articles/2024-06-06/apple-to-debut-passwords-app-in-challenge-to-1password-lastpass"&gt;一份報告來自&lt;em&gt;彭博社&lt;/em&gt;&lt;/a&gt;。&lt;/p&gt;&lt;/div&gt;&lt;div class="duet--article--article-body-component"&gt;&lt;p class="duet--article--dangerously-set-cms-markup duet--article--standard-paragraph mb-20 font-fkroman text-18 leading-160 -tracking-1 selection:bg-franklin-20 dark:text-white dark:selection:bg-blurple [&amp;amp;_a:hover]:shadow-highlight-franklin dark:[&amp;amp;_a:hover]:shadow-highlight-blurple [&amp;amp;_a]:shadow-underline-black dark:[&amp;amp;_a]:shadow-underline-white"&gt;Apple 已經允許您使用 iCloud 鑰匙串在 iPhone、iPad 或 Vision Pro 上保存密碼。&lt;em&gt;彭博社&lt;/em&gt;表示新的密碼應用程序還將擴展對 Windows 的支持 - 沒有關於對 Android 的支持的消息。&lt;/p&gt;&lt;/div&gt;&lt;div class="duet--article--article-body-component"&gt;&lt;p class="duet--article--dangerously-set-cms-markup duet--article--standard-paragraph mb-20 font-fkroman text-18 leading-160 -tracking-1 selection:bg-franklin-20 dark:text-white dark:selection:bg-blurple [&amp;amp;_a:hover]:shadow-highlight-franklin dark:[&amp;amp;_a:hover]:shadow-highlight-blurple [&amp;amp;_a]:shadow-underline-black dark:[&amp;amp;_a]:shadow-underline-white"&gt;這款新應用預計將在 iOS 18、iPadOS 18 和 macOS 15 中首次亮相。&lt;em&gt;彭博社&lt;/em&gt;，Passwords 將能夠生成和存儲密碼，類似於 LastPass 和 1Password 等密碼管理器。&lt;/p&gt;&lt;/div&gt;&lt;div class="duet--article--article-body-component clear-both block md:float-left md:mr-30 md:w-[320px] lg:-ml-100"&gt;&lt;/div&gt;&lt;div class="duet--article--article-body-component"&gt;&lt;p class="duet--article--dangerously-set-cms-markup duet--article--standard-paragraph mb-20 font-fkroman text-18 leading-160 -tracking-1 selection:bg-franklin-20 dark:text-white dark:selection:bg-blurple [&amp;amp;_a:hover]:shadow-highlight-franklin dark:[&amp;amp;_a:hover]:shadow-highlight-blurple [&amp;amp;_a]:shadow-underline-black dark:[&amp;amp;_a]:shadow-underline-white"&gt;突出顯示的其他功能&lt;em&gt;彭博社&lt;/em&gt;包括自動填充用户名和密碼，以及創建身份驗證代碼的功能，例如 Google Authenticator。&lt;/p&gt;&lt;/div&gt;&lt;div class="duet--article--article-body-component"&gt;&lt;p class="duet--article--dangerously-set-cms-markup duet--article--standard-paragraph mb-20 font-fkroman text-18 leading-160 -tracking-1 selection:bg-franklin-20 dark:text-white dark:selection:bg-blurple [&amp;amp;_a:hover]:shadow-highlight-franklin dark:[&amp;amp;_a:hover]:shadow-highlight-blurple [&amp;amp;_a]:shadow-underline-black dark:[&amp;amp;_a]:shadow-underline-white"&gt;蘋果預計將在 6 月 10 日的 WWDC 上公佈一系列新功能，有傳言稱&lt;a href="https://www.theverge.com/2024/5/3/24148282/apple-ai-iphone-ios-18-plans-ajax"&gt;iOS 18 中 iPhone 的新 AI 功能&lt;/a&gt;，以及一個&lt;a href="https://www.theverge.com/2024/5/30/24168175/ios-18-ai-siri-apple-apps"&gt;Siri 的重大調整&lt;/a&gt;.&lt;/p&gt;&lt;/div&gt;&lt;/div&gt;&lt;div class="mb-40 mt-30"&gt;&lt;button class="duet--article--comments-button group inline-flex h-40 w-full items-center justify-center rounded-[2px] border-[1px] border-solid border-blurple font-polysans-mono text-11 font-light uppercase tracking-12 text-blurple hover:bg-blurple hover:text-white md:w-auto md:px-30"&gt;&lt;svg class="mr-10 inline pt-2" fill="none" height="14" stroke-width="1px" viewbox="0 0 12 12" width="12"
            xmlns="http://www.w3.org/2000/svg"&gt;&lt;title&gt;Comments&lt;/title&gt;&lt;path d="M2.4 9.1h-.207l-.147.146L.5 10.793V1.2c0-.384.316-.7.7-.7h9.6c.384 0 .7.316.7.7v7.2c0 .384-.316.7-.7.7H2.4Z" stroke="currentColor"&gt;&lt;/path&gt;&lt;/svg&gt;&lt;span class="coral-count"&gt;&lt;/span&gt;&lt;/button&gt;&lt;/div&gt;
        </summary>
        <published>2024-06-06T21:07:44+00:00</published>
    </entry>
    <entry>
        <id>https://www.theverge.com/2024/6/6/24173108/ebay-american-express-payment-fees</id>
        <title>eBay 將不再接受美國運通卡，因為費用「高得令人難以接受」</title>
        <updated>2024-06-06T20:16:12+00:00</updated>
        <author>
            <name>Emma Roth</name>
        </author>
        <link href="https://www.theverge.com/2024/6/6/24173108/ebay-american-express-payment-fees"/>
        <summary type="html">&lt;h2 class="inline selection:bg-franklin-20"&gt;從 8 月 17 日開始，Amex 將不再支持該服務。&lt;/h2&gt;&lt;img src="https://cdn.vox-cdn.com/thumbor/z441JIFByTlL0Mt4Gi5FfQMAWtE=/0x0:2040x1360/1200x628/filters:focal(1020x680:1021x681)/cdn.vox-cdn.com/uploads/chorus_asset/file/25229472/STK252_ebay_stock_CVirginia_6.jpg"/&gt;&lt;div&gt;&lt;div class="duet--article--article-body-component"&gt;&lt;p class="duet--article--dangerously-set-cms-markup duet--article--standard-paragraph mb-20 font-fkroman text-18 leading-160 -tracking-1 selection:bg-franklin-20 dark:text-white dark:selection:bg-blurple [&amp;amp;_a:hover]:shadow-highlight-franklin dark:[&amp;amp;_a:hover]:shadow-highlight-blurple [&amp;amp;_a]:shadow-underline-black dark:[&amp;amp;_a]:shadow-underline-white"&gt;eBay 自 8 月 17 日起將不再接受美國運通卡付款&lt;a href="https://www.ebayinc.com/stories/news/neebay-to-discontinue-acceptance-of-american-express-payments-starting-august-17-2024/"&gt;公司宣佈&lt;/a&gt;週三。&lt;/p&gt;&lt;/div&gt;&lt;div class="duet--article--article-body-component"&gt;&lt;p class="duet--article--dangerously-set-cms-markup duet--article--standard-paragraph mb-20 font-fkroman text-18 leading-160 -tracking-1 selection:bg-franklin-20 dark:text-white dark:selection:bg-blurple [&amp;amp;_a:hover]:shadow-highlight-franklin dark:[&amp;amp;_a:hover]:shadow-highlight-blurple [&amp;amp;_a]:shadow-underline-black dark:[&amp;amp;_a]:shadow-underline-white"&gt;「由於缺乏有意義的競爭，信用卡交易費用繼續有增無減」，eBay 在給客户的通知中寫道。 &lt;a href="https://go.skimresources.com/?id=1025X1701640&amp;amp;xs=1&amp;amp;url=https%3A%2F%2Fwww.ebay.com%2Fhelp%2Fbuying%2Fpaying-items%2Fpaying-items-credit-debit-card%3Fid%3D4038%23%3A~%3Atext%3DYou%2520can%2520pay%2520for%2520your%2Call%2520of%2520these%2520payment%2520methods."&gt;仍然接受&lt;/a&gt;Visa、萬事達卡、Discover 和&lt;a href="https://go.skimresources.com/?id=1025X1701640&amp;amp;xs=1&amp;amp;url=https%3A%2F%2Fwww.ebay.com%2Fhelp%2Fpolicies%2Fpayment-policies%2Fpayment-methods-policy%3Fid%3D4269"&gt;其他付款方式&lt;/a&gt;，例如 PayPal、Apple Pay、Google Pay 和 Venmo。&lt;/p&gt;&lt;/div&gt;&lt;div class="duet--article--article-body-component"&gt;&lt;p class="duet--article--dangerously-set-cms-markup duet--article--standard-paragraph mb-20 font-fkroman text-18 leading-160 -tracking-1 selection:bg-franklin-20 dark:text-white dark:selection:bg-blurple [&amp;amp;_a:hover]:shadow-highlight-franklin dark:[&amp;amp;_a:hover]:shadow-highlight-blurple [&amp;amp;_a]:shadow-underline-black dark:[&amp;amp;_a]:shadow-underline-white"&gt;美國運通公司不同意 eBay 的舉動，&lt;a href="https://www.americanexpress.com/en-us/newsroom/articles/company-statements/american-express-statement-on-ebay-acceptance.html"&gt;在其網站上聲明&lt;/a&gt;其費用與 eBay 接受的其他卡類似。&lt;/p&gt;&lt;/div&gt;&lt;div class="duet--article--article-body-component"&gt;&lt;p class="duet--article--dangerously-set-cms-markup duet--article--standard-paragraph mb-20 font-fkroman text-18 leading-160 -tracking-1 selection:bg-franklin-20 dark:text-white dark:selection:bg-blurple [&amp;amp;_a:hover]:shadow-highlight-franklin dark:[&amp;amp;_a:hover]:shadow-highlight-blurple [&amp;amp;_a]:shadow-underline-black dark:[&amp;amp;_a]:shadow-underline-white"&gt;我們過去也看到過零售商和信用卡公司之間發生的其他糾紛，&lt;a href="https://www.theverge.com/2022/2/17/22938726/amazon-visa-payment-transaction-fee-deal"&gt;亞馬遜幾乎放棄支持&lt;/a&gt;2022 年在英國申請簽證。&lt;/p&gt;&lt;/div&gt;&lt;/div&gt;&lt;div class="mb-40 mt-30"&gt;&lt;button class="duet--article--comments-button group inline-flex h-40 w-full items-center justify-center rounded-[2px] border-[1px] border-solid border-blurple font-polysans-mono text-11 font-light uppercase tracking-12 text-blurple hover:bg-blurple hover:text-white md:w-auto md:px-30"&gt;&lt;svg class="mr-10 inline pt-2" fill="none" height="14" stroke-width="1px" viewbox="0 0 12 12" width="12"
            xmlns="http://www.w3.org/2000/svg"&gt;&lt;title&gt;Comments&lt;/title&gt;&lt;path d="M2.4 9.1h-.207l-.147.146L.5 10.793V1.2c0-.384.316-.7.7-.7h9.6c.384 0 .7.316.7.7v7.2c0 .384-.316.7-.7.7H2.4Z" stroke="currentColor"&gt;&lt;/path&gt;&lt;/svg&gt;&lt;span class="coral-count"&gt;&lt;/span&gt;&lt;/button&gt;&lt;/div&gt;
        </summary>
        <published>2024-06-06T20:16:12+00:00</published>
    </entry>
    <entry>
        <id>https://www.theverge.com/2024/6/6/24172351/netflix-redesign-homepage-experience-test</id>
        <title>Netflix 最新的重新設計旨在簡化您的主頁</title>
        <updated>2024-06-06T17:00:00+00:00</updated>
        <author>
            <name>Emma Roth</name>
        </author>
        <link href="https://www.theverge.com/2024/6/6/24172351/netflix-redesign-homepage-experience-test"/>
        <summary type="html">&lt;h2 class="inline selection:bg-franklin-20"&gt;一項新測試使標題的預告片和描述在屏幕上更加突出。&lt;/h2&gt;&lt;img src="https://cdn.vox-cdn.com/thumbor/qgKP0yiqM5ngd7WIhhEztSLwaAo=/0x0:1920x1080/1200x628/filters:focal(960x540:961x541)/cdn.vox-cdn.com/uploads/chorus_asset/file/25479433/netflix_homepage_1.jpg"/&gt;&lt;div&gt;&lt;div class="duet--article--article-body-component"&gt;&lt;p class="duet--article--dangerously-set-cms-markup duet--article--standard-paragraph mb-20 font-fkroman text-18 leading-160 -tracking-1 selection:bg-franklin-20 dark:text-white dark:selection:bg-blurple [&amp;amp;_a:hover]:shadow-highlight-franklin dark:[&amp;amp;_a:hover]:shadow-highlight-blurple [&amp;amp;_a]:shadow-underline-black dark:[&amp;amp;_a]:shadow-underline-white"&gt;Netflix 正在測試其電視應用程序的大規模主頁重新設計。&lt;/p&gt;&lt;/div&gt;&lt;div class="duet--article--article-body-component"&gt;&lt;p class="duet--article--dangerously-set-cms-markup duet--article--standard-paragraph mb-20 font-fkroman text-18 leading-160 -tracking-1 selection:bg-franklin-20 dark:text-white dark:selection:bg-blurple [&amp;amp;_a:hover]:shadow-highlight-franklin dark:[&amp;amp;_a:hover]:shadow-highlight-blurple [&amp;amp;_a]:shadow-underline-black dark:[&amp;amp;_a]:shadow-underline-white"&gt;這與 Netflix 現有主頁的工作方式有所不同，目前，當您滾動鼠標時，該主頁會在其界面的最頂部顯示影片的預告片和其他信息。&lt;/p&gt;&lt;/div&gt;&lt;div class="duet--article--article-body-component"&gt;&lt;p class="duet--article--dangerously-set-cms-markup duet--article--standard-paragraph mb-20 font-fkroman text-18 leading-160 -tracking-1 selection:bg-franklin-20 dark:text-white dark:selection:bg-blurple [&amp;amp;_a:hover]:shadow-highlight-franklin dark:[&amp;amp;_a:hover]:shadow-highlight-blurple [&amp;amp;_a]:shadow-underline-black dark:[&amp;amp;_a]:shadow-underline-white"&gt;將鼠標懸停在電視節目或電影上足夠長的時間，Netflix 將開始直接在圖塊內播放簡短的預覽。&lt;/p&gt;&lt;/div&gt;&lt;div class="duet--article--article-body-component clear-both block"&gt;&lt;div class="my-9"&gt;&lt;div class="transition-all duration-300 ease-in-out"&gt;&lt;div class="fixed inset-0 h-[110vh] w-full bg-white transition-all duration-300 ease-in-out z-[-1] cursor-default opacity-0" tabindex="0"&gt;&lt;/div&gt;&lt;div class="visible z-30 w-full origin-center transition-all duration-300 ease-in-out cursor-zoom-in" tabindex="0"&gt;&lt;figure class="transition-all duration-300 ease-in-out lg:mx-0"&gt;&lt;div&gt;&lt;div class="duet--media--content-warning relative"&gt;&lt;span style="display: block; overflow: hidden; width: initial; height: initial; background: none; border: 0; margin: 0; padding: 0;"&gt;&lt;img alt="Your eyes no longer have to travel to the top of Netflix to watch a trailer." src="data:image/gif;base64,R0lGODlhAQABAIAAAAAAAP///yH5BAEAAAAALAAAAAABAAEAAAIBRAA7" style="padding: 0; border: none; margin: auto; display: block; width: 0; height: 0;"/&gt;&lt;noscript&gt;&lt;img alt="Your eyes no longer have to travel to the top of Netflix to watch a trailer." src="https://duet-cdn.vox-cdn.com/thumbor/0x0:600x338/2400x1352/filters:focal(300x169:301x170):no_upscale():format(webp)/cdn.vox-cdn.com/uploads/chorus_asset/file/25480393/netflix_new_homepage_layout.gif" style="padding: 0; border: none; margin: auto; display: block; width: 0; height: 0;"/&gt;&lt;/noscript&gt;&lt;/span&gt;&lt;/div&gt;&lt;/div&gt;&lt;/figure&gt;&lt;/div&gt;&lt;div class="z-1 w-full hidden"&gt;&lt;figure class="transition-all duration-300 ease-in-out lg:mx-0"&gt;&lt;div&gt;&lt;div class="duet--media--content-warning relative"&gt;&lt;span style="display: block; overflow: hidden; width: initial; height: initial; background: none; border: 0; margin: 0; padding: 0;"&gt;&lt;img alt="Your eyes no longer have to travel to the top of Netflix to watch a trailer." src="data:image/gif;base64,R0lGODlhAQABAIAAAAAAAP///yH5BAEAAAAALAAAAAABAAEAAAIBRAA7" style="padding: 0; border: none; margin: auto; display: block; width: 0; height: 0;"/&gt;&lt;noscript&gt;&lt;img alt="Your eyes no longer have to travel to the top of Netflix to watch a trailer." src="https://duet-cdn.vox-cdn.com/thumbor/0x0:600x338/2400x1352/filters:focal(300x169:301x170):no_upscale():format(webp)/cdn.vox-cdn.com/uploads/chorus_asset/file/25480393/netflix_new_homepage_layout.gif" style="padding: 0; border: none; margin: auto; display: block; width: 0; height: 0;"/&gt;&lt;/noscript&gt;&lt;/span&gt;&lt;/div&gt;&lt;/div&gt;&lt;/figure&gt;&lt;/div&gt;&lt;/div&gt;&lt;div class="duet--media--caption pt-6 font-polysans-mono text-12 font-light leading-130 tracking-1"&gt;&lt;figcaption class="duet--article--dangerously-set-cms-markup inline text-gray-13 dark:text-gray-e9 [&amp;amp;&amp;gt;a:hover]:text-black [&amp;amp;&amp;gt;a:hover]:shadow-underline-black dark:[&amp;amp;&amp;gt;a:hover]:text-gray-e9 dark:[&amp;amp;&amp;gt;a:hover]:shadow-underline-gray-63 [&amp;amp;&amp;gt;a]:shadow-underline-gray-13 dark:[&amp;amp;&amp;gt;a]:shadow-underline-gray-63"&gt;&lt;em&gt;您的眼睛不再需要跑到 Netflix 的頂部才能觀看預告片。&lt;/em&gt;&lt;/figcaption&gt; &lt;cite class="duet--article--dangerously-set-cms-markup inline not-italic text-gray-63 dark:text-gray-bd [&amp;amp;&amp;gt;a:hover]:text-gray-63 [&amp;amp;&amp;gt;a:hover]:shadow-underline-black dark:[&amp;amp;&amp;gt;a:hover]:text-gray-bd dark:[&amp;amp;&amp;gt;a:hover]:shadow-underline-gray [&amp;amp;&amp;gt;a]:shadow-underline-gray-63 dark:[&amp;amp;&amp;gt;a]:text-gray-bd dark:[&amp;amp;&amp;gt;a]:shadow-underline-gray"&gt;GIF：Netflix&lt;/cite&gt;&lt;/div&gt;&lt;/div&gt;&lt;/div&gt;&lt;div class="duet--article--article-body-component"&gt;&lt;p class="duet--article--dangerously-set-cms-markup duet--article--standard-paragraph mb-20 font-fkroman text-18 leading-160 -tracking-1 selection:bg-franklin-20 dark:text-white dark:selection:bg-blurple [&amp;amp;_a:hover]:shadow-highlight-franklin dark:[&amp;amp;_a:hover]:shadow-highlight-blurple [&amp;amp;_a]:shadow-underline-black dark:[&amp;amp;_a]:shadow-underline-white"&gt;「我們經常看到會員在審視家庭體驗時用眼睛做體操」，Netflix 高級產品總監帕特·弗萊明 (Pat Flemming) 告訴我們&lt;em&gt;The Verge&lt;/em&gt;。 &lt;/p&gt;&lt;/div&gt;&lt;div class="duet--article--article-body-component"&gt;&lt;p class="duet--article--dangerously-set-cms-markup duet--article--standard-paragraph mb-20 font-fkroman text-18 leading-160 -tracking-1 selection:bg-franklin-20 dark:text-white dark:selection:bg-blurple [&amp;amp;_a:hover]:shadow-highlight-franklin dark:[&amp;amp;_a:hover]:shadow-highlight-blurple [&amp;amp;_a]:shadow-underline-black dark:[&amp;amp;_a]:shadow-underline-white"&gt;這並不是 Netflix 對其外觀進行的唯一改變。&lt;/p&gt;&lt;/div&gt;&lt;div class="duet--article--article-body-component"&gt;&lt;p class="duet--article--dangerously-set-cms-markup duet--article--standard-paragraph mb-20 font-fkroman text-18 leading-160 -tracking-1 selection:bg-franklin-20 dark:text-white dark:selection:bg-blurple [&amp;amp;_a:hover]:shadow-highlight-franklin dark:[&amp;amp;_a:hover]:shadow-highlight-blurple [&amp;amp;_a]:shadow-underline-black dark:[&amp;amp;_a]:shadow-underline-white"&gt;新菜單還減少了左側菜單中以前可用的一些選項，包括「類別」、「新的和流行的」和「我的列表」選項卡。&lt;em&gt;做&lt;/em&gt;添加「我的 Netflix」，「Netflix」選項卡&lt;a href="https://www.theverge.com/2023/7/24/23805752/netflix-my-tab-ios-android-find-things-to-watch"&gt;第一卷&lt;/a&gt;去年在其移動應用程序上，該應用程序提供內容推薦和快速訪問您最近觀看或保存的標題。&lt;/p&gt;&lt;/div&gt;&lt;div class="duet--article--article-body-component clear-both block"&gt;&lt;div class="my-9"&gt;&lt;div class="transition-all duration-300 ease-in-out"&gt;&lt;div class="fixed inset-0 h-[110vh] w-full bg-white transition-all duration-300 ease-in-out z-[-1] cursor-default opacity-0" tabindex="0"&gt;&lt;/div&gt;&lt;div class="visible z-30 w-full origin-center transition-all duration-300 ease-in-out cursor-zoom-in" tabindex="0"&gt;&lt;figure class="transition-all duration-300 ease-in-out lg:mx-0"&gt;&lt;div&gt;&lt;div class="duet--media--content-warning relative" style="padding-top: 56.25%;"&gt;&lt;span style="display: block; overflow: hidden; width: initial; height: initial; background: none; border: 0; margin: 0; padding: 0;"&gt;&lt;img alt="The My Netflix tab rolled out on mobile first." src="data:image/gif;base64,R0lGODlhAQABAIAAAAAAAP///yH5BAEAAAAALAAAAAABAAEAAAIBRAA7" style="padding: 0; border: none; margin: auto; display: block; width: 0; height: 0;"/&gt;&lt;noscript&gt;&lt;img alt="The My Netflix tab rolled out on mobile first." src="https://duet-cdn.vox-cdn.com/thumbor/0x0:1920x1080/2400x1350/filters:focal(960x540:961x541):format(webp)/cdn.vox-cdn.com/uploads/chorus_asset/file/25479488/netflix_homepage_2.jpg" style="padding: 0; border: none; margin: auto; display: block; width: 0; height: 0;"/&gt;&lt;/noscript&gt;&lt;/span&gt;&lt;/div&gt;&lt;/div&gt;&lt;/figure&gt;&lt;/div&gt;&lt;div class="z-1 w-full hidden"&gt;&lt;figure class="transition-all duration-300 ease-in-out lg:mx-0"&gt;&lt;div&gt;&lt;div class="duet--media--content-warning relative" style="padding-top: 56.25%;"&gt;&lt;span style="display: block; overflow: hidden; width: initial; height: initial; background: none; border: 0; margin: 0; padding: 0;"&gt;&lt;img alt="The My Netflix tab rolled out on mobile first." src="data:image/gif;base64,R0lGODlhAQABAIAAAAAAAP///yH5BAEAAAAALAAAAAABAAEAAAIBRAA7" style="padding: 0; border: none; margin: auto; display: block; width: 0; height: 0;"/&gt;&lt;noscript&gt;&lt;img alt="The My Netflix tab rolled out on mobile first." src="https://duet-cdn.vox-cdn.com/thumbor/0x0:1920x1080/2400x1350/filters:focal(960x540:961x541):format(webp)/cdn.vox-cdn.com/uploads/chorus_asset/file/25479488/netflix_homepage_2.jpg" style="padding: 0; border: none; margin: auto; display: block; width: 0; height: 0;"/&gt;&lt;/noscript&gt;&lt;/span&gt;&lt;/div&gt;&lt;/div&gt;&lt;/figure&gt;&lt;/div&gt;&lt;/div&gt;&lt;div class="duet--media--caption pt-6 font-polysans-mono text-12 font-light leading-130 tracking-1"&gt;&lt;figcaption class="duet--article--dangerously-set-cms-markup inline text-gray-13 dark:text-gray-e9 [&amp;amp;&amp;gt;a:hover]:text-black [&amp;amp;&amp;gt;a:hover]:shadow-underline-black dark:[&amp;amp;&amp;gt;a:hover]:text-gray-e9 dark:[&amp;amp;&amp;gt;a:hover]:shadow-underline-gray-63 [&amp;amp;&amp;gt;a]:shadow-underline-gray-13 dark:[&amp;amp;&amp;gt;a]:shadow-underline-gray-63"&gt;&lt;em&gt;「我的 Netflix」標籤首先在移動設備上推出。&lt;/em&gt;&lt;/figcaption&gt; &lt;cite class="duet--article--dangerously-set-cms-markup inline not-italic text-gray-63 dark:text-gray-bd [&amp;amp;&amp;gt;a:hover]:text-gray-63 [&amp;amp;&amp;gt;a:hover]:shadow-underline-black dark:[&amp;amp;&amp;gt;a:hover]:text-gray-bd dark:[&amp;amp;&amp;gt;a:hover]:shadow-underline-gray [&amp;amp;&amp;gt;a]:shadow-underline-gray-63 dark:[&amp;amp;&amp;gt;a]:text-gray-bd dark:[&amp;amp;&amp;gt;a]:shadow-underline-gray"&gt;圖片：Netflix&lt;/cite&gt;&lt;/div&gt;&lt;/div&gt;&lt;/div&gt;&lt;div class="duet--article--article-body-component"&gt;&lt;p class="duet--article--dangerously-set-cms-markup duet--article--standard-paragraph mb-20 font-fkroman text-18 leading-160 -tracking-1 selection:bg-franklin-20 dark:text-white dark:selection:bg-blurple [&amp;amp;_a:hover]:shadow-highlight-franklin dark:[&amp;amp;_a:hover]:shadow-highlight-blurple [&amp;amp;_a]:shadow-underline-black dark:[&amp;amp;_a]:shadow-underline-white"&gt;「將此視為我們的第一次努力，我們最好的初始搖擺，我們認為這是一次很棒的新電視體驗」，弗萊明説。&lt;a href="https://www.theverge.com/2024/5/31/24169091/netflix-mike-tyson-jake-paul-boxing-rescheduled"&gt;傑克·保羅和邁克·泰森之間&lt;/a&gt;， 這&lt;a href="https://www.theverge.com/2024/5/15/24157289/netflix-nfl-game-streaming-global-christmas-day"&gt;NFL 比賽將於今年晚些時候舉行&lt;/a&gt;，以及&lt;a href="https://www.theverge.com/2024/1/23/24047785/netflix-monday-night-raw-exclusive-live-streaming-leaving-cable"&gt;WWE 的&lt;em&gt;週一晚上生&lt;/em&gt;&lt;/a&gt;.&lt;/p&gt;&lt;/div&gt;&lt;div class="duet--article--article-body-component"&gt;&lt;p class="duet--article--dangerously-set-cms-markup duet--article--standard-paragraph mb-20 font-fkroman text-18 leading-160 -tracking-1 selection:bg-franklin-20 dark:text-white dark:selection:bg-blurple [&amp;amp;_a:hover]:shadow-highlight-franklin dark:[&amp;amp;_a:hover]:shadow-highlight-blurple [&amp;amp;_a]:shadow-underline-black dark:[&amp;amp;_a]:shadow-underline-white"&gt;該公司將首先在一小羣使用智能電視和其他流媒體設備的用户中測試新主頁，但弗萊明表示&lt;em&gt;The Verge&lt;/em&gt;如果成功的話，它可以擴展到更多成員。 &lt;/p&gt;&lt;/div&gt;&lt;/div&gt;&lt;div class="mb-40 mt-30"&gt;&lt;button class="duet--article--comments-button group inline-flex h-40 w-full items-center justify-center rounded-[2px] border-[1px] border-solid border-blurple font-polysans-mono text-11 font-light uppercase tracking-12 text-blurple hover:bg-blurple hover:text-white md:w-auto md:px-30"&gt;&lt;svg class="mr-10 inline pt-2" fill="none" height="14" stroke-width="1px" viewbox="0 0 12 12" width="12"
            xmlns="http://www.w3.org/2000/svg"&gt;&lt;title&gt;Comments&lt;/title&gt;&lt;path d="M2.4 9.1h-.207l-.147.146L.5 10.793V1.2c0-.384.316-.7.7-.7h9.6c.384 0 .7.316.7.7v7.2c0 .384-.316.7-.7.7H2.4Z" stroke="currentColor"&gt;&lt;/path&gt;&lt;/svg&gt;&lt;span class="coral-count"&gt;&lt;/span&gt;&lt;/button&gt;&lt;/div&gt;
        </summary>
        <published>2024-06-06T17:00:00+00:00</published>
    </entry>
    <entry>
        <id>https://www.theverge.com/2024/6/6/24172863/grubhub-starbucks-food-delivery-apps</id>
        <title>Grubhub 現在也提供星巴克服務</title>
        <updated>2024-06-06T16:23:46+00:00</updated>
        <author>
            <name>Sheena Vasani</name>
        </author>
        <link href="https://www.theverge.com/2024/6/6/24172863/grubhub-starbucks-food-delivery-apps"/>
        <summary type="html">&lt;h2 class="inline selection:bg-franklin-20"&gt;星巴克外賣服務與 Grubhub 將於 6 月開始在部分市場推出，然後於今年夏天在全國範圍內推廣。&lt;/h2&gt;&lt;img src="https://cdn.vox-cdn.com/thumbor/z3BAubfOG60cEAYGkhEUZ8pROhg=/0x0:906x517/1200x628/filters:focal(453x259:454x260)/cdn.vox-cdn.com/uploads/chorus_asset/file/25480482/Screenshot_2024_06_06_at_9.02.14_AM.png"/&gt;&lt;div&gt;&lt;div class="duet--article--article-body-component"&gt;&lt;p class="duet--article--dangerously-set-cms-markup duet--article--standard-paragraph mb-20 font-fkroman text-18 leading-160 -tracking-1 selection:bg-franklin-20 dark:text-white dark:selection:bg-blurple [&amp;amp;_a:hover]:shadow-highlight-franklin dark:[&amp;amp;_a:hover]:shadow-highlight-blurple [&amp;amp;_a]:shadow-underline-black dark:[&amp;amp;_a]:shadow-underline-white"&gt;食品配送應用程序 Grubhub 將與星巴克合作，從本月開始向美國顧客配送飲料和食品&lt;a href="https://about.grubhub.com/news/starbucks-and-grubhub-launch-delivery-partnership/"&gt;宣佈&lt;/a&gt;6 月 6 日。&lt;/p&gt;&lt;/div&gt;&lt;div class="duet--article--article-body-component"&gt;&lt;p class="duet--article--dangerously-set-cms-markup duet--article--standard-paragraph mb-20 font-fkroman text-18 leading-160 -tracking-1 selection:bg-franklin-20 dark:text-white dark:selection:bg-blurple [&amp;amp;_a:hover]:shadow-highlight-franklin dark:[&amp;amp;_a:hover]:shadow-highlight-blurple [&amp;amp;_a]:shadow-underline-black dark:[&amp;amp;_a]:shadow-underline-white"&gt;從本月開始，星巴克將首先在賓夕法尼亞州、科羅拉多州和伊利諾伊州通過 Grubhub 移動應用程序和網站進行訪問，然後在 8 月份擴展到全國範圍內。&lt;/p&gt;&lt;/div&gt;&lt;div class="duet--article--article-body-component"&gt;&lt;p class="duet--article--dangerously-set-cms-markup duet--article--standard-paragraph mb-20 font-fkroman text-18 leading-160 -tracking-1 selection:bg-franklin-20 dark:text-white dark:selection:bg-blurple [&amp;amp;_a:hover]:shadow-highlight-franklin dark:[&amp;amp;_a:hover]:shadow-highlight-blurple [&amp;amp;_a]:shadow-underline-black dark:[&amp;amp;_a]:shadow-underline-white"&gt;根據 Grubhub 的數據，星巴克是其市場上尚未提供的搜索次數最多的企業。&lt;a href="https://www.theverge.com/2023/1/17/23559108/doordash-starbucks-delivery-us-expansion"&gt;去年開始在美國提供星巴克送貨服務&lt;/a&gt;。&lt;a href="https://www.theverge.com/2018/12/13/18139850/starbucks-expands-delivery-us-locations-uber-eats"&gt;優食&lt;/a&gt;和郵友。&lt;/p&gt;&lt;/div&gt;&lt;div class="duet--article--article-body-component clear-both block md:float-left md:mr-30 md:w-[320px] lg:-ml-100"&gt;&lt;/div&gt;&lt;div class="duet--article--article-body-component"&gt;&lt;p class="duet--article--dangerously-set-cms-markup duet--article--standard-paragraph mb-20 font-fkroman text-18 leading-160 -tracking-1 selection:bg-franklin-20 dark:text-white dark:selection:bg-blurple [&amp;amp;_a:hover]:shadow-highlight-franklin dark:[&amp;amp;_a:hover]:shadow-highlight-blurple [&amp;amp;_a]:shadow-underline-black dark:[&amp;amp;_a]:shadow-underline-white"&gt;這也不是 Grubhub 最近建立的唯一可以給該公司帶來優勢的主要合作伙伴關係。&lt;a href="https://www.theverge.com/2024/5/30/24167678/amazon-prime-grubhub-plus-free-food-delivery"&gt;亞馬遜添加&lt;/a&gt;Grubhub 發佈到其網站和應用程序，並使其 Prime 會員永久免費使用 GrubHub Plus。 &lt;/p&gt;&lt;/div&gt;&lt;div class="duet--article--article-body-component"&gt;&lt;p class="duet--article--dangerously-set-cms-markup duet--article--standard-paragraph mb-20 font-fkroman text-18 leading-160 -tracking-1 selection:bg-franklin-20 dark:text-white dark:selection:bg-blurple [&amp;amp;_a:hover]:shadow-highlight-franklin dark:[&amp;amp;_a:hover]:shadow-highlight-blurple [&amp;amp;_a]:shadow-underline-black dark:[&amp;amp;_a]:shadow-underline-white"&gt;與此同時，這一消息也是繼星巴克之後發佈的。&lt;a href="https://www.foxbusiness.com/lifestyle/starbucks-teams-up-grubhub-expand-delivery-services"&gt;報道&lt;/a&gt;4 月份同店銷售額自 2020 年以來首次出現下滑。與此同時，該公司上個季度的美國配送業務實現了兩位數增長，&lt;a href="https://www.foxbusiness.com/lifestyle/starbucks-fall-from-grace-howard-schultz-says-company-needs-fix-us-operations"&gt;提示&lt;/a&gt;星巴克前首席執行官霍華德·舒爾茨呼籲進行戰略改革並「重塑」其移動訂購和支付平台。 &lt;/p&gt;&lt;/div&gt;&lt;div class="duet--article--article-body-component"&gt;&lt;p class="duet--article--dangerously-set-cms-markup duet--article--standard-paragraph mb-20 font-fkroman text-18 leading-160 -tracking-1 selection:bg-franklin-20 dark:text-white dark:selection:bg-blurple [&amp;amp;_a:hover]:shadow-highlight-franklin dark:[&amp;amp;_a:hover]:shadow-highlight-blurple [&amp;amp;_a]:shadow-underline-black dark:[&amp;amp;_a]:shadow-underline-white"&gt;星巴克數字體驗副總裁 Meg Mathes 表示：「我們與 Grubhub 的新合作伙伴關係將通過增加 Grubhub 數千萬客户的星巴克產品可用性來幫助推動這一增長。」&lt;/p&gt;&lt;/div&gt;&lt;/div&gt;&lt;div class="mb-40 mt-30"&gt;&lt;button class="duet--article--comments-button group inline-flex h-40 w-full items-center justify-center rounded-[2px] border-[1px] border-solid border-blurple font-polysans-mono text-11 font-light uppercase tracking-12 text-blurple hover:bg-blurple hover:text-white md:w-auto md:px-30"&gt;&lt;svg class="mr-10 inline pt-2" fill="none" height="14" stroke-width="1px" viewbox="0 0 12 12" width="12"
            xmlns="http://www.w3.org/2000/svg"&gt;&lt;title&gt;Comments&lt;/title&gt;&lt;path d="M2.4 9.1h-.207l-.147.146L.5 10.793V1.2c0-.384.316-.7.7-.7h9.6c.384 0 .7.316.7.7v7.2c0 .384-.316.7-.7.7H2.4Z" stroke="currentColor"&gt;&lt;/path&gt;&lt;/svg&gt;&lt;span class="coral-count"&gt;&lt;/span&gt;&lt;/button&gt;&lt;/div&gt;
        </summary>
        <published>2024-06-06T16:23:46+00:00</published>
    </entry>
    <entry>
        <id>https://www.theverge.com/2024/6/6/24172836/discord-monetization-updates-subscriptions-developers</id>
        <title>Discord 讓應用程序開發者更容易賺錢</title>
        <updated>2024-06-06T15:00:00+00:00</updated>
        <author>
            <name>Jess Weatherbed</name>
        </author>
        <link href="https://www.theverge.com/2024/6/6/24172836/discord-monetization-updates-subscriptions-developers"/>
        <summary type="html">&lt;h2 class="inline selection:bg-franklin-20"&gt;Discord 正在推出新的貨幣化功能，並將開發者賺取的前 100 萬美元的平台費用降低至 15%。&lt;/h2&gt;&lt;img src="https://cdn.vox-cdn.com/thumbor/B8utF6QHqyIqRCgEFc4uhhBNiwM=/0x0:2040x1360/1200x628/filters:focal(1020x680:1021x681)/cdn.vox-cdn.com/uploads/chorus_asset/file/25480287/Discord_monetization_features.jpg"/&gt;&lt;div&gt;&lt;div class="duet--article--article-body-component"&gt;&lt;p class="duet--article--dangerously-set-cms-markup duet--article--standard-paragraph mb-20 font-fkroman text-18 leading-160 -tracking-1 selection:bg-franklin-20 dark:text-white dark:selection:bg-blurple [&amp;amp;_a:hover]:shadow-highlight-franklin dark:[&amp;amp;_a:hover]:shadow-highlight-blurple [&amp;amp;_a]:shadow-underline-black dark:[&amp;amp;_a]:shadow-underline-white"&gt;Discord 正在推出新的工具和貨幣化功能，旨在讓應用程序開發人員更輕鬆地通過平台上的店面銷售高級福利來賺錢。&lt;a href="https://discord.com/developers/docs/monetization/app-subscriptions"&gt;高級應用程序訂閲&lt;/a&gt;去年，Discord 現在將開發者累計總銷售額前 100 萬美元的 30% 平台費用減半。&lt;/p&gt;&lt;/div&gt;&lt;div class="duet--article--article-body-component"&gt;&lt;p class="duet--article--dangerously-set-cms-markup duet--article--standard-paragraph mb-20 font-fkroman text-18 leading-160 -tracking-1 selection:bg-franklin-20 dark:text-white dark:selection:bg-blurple [&amp;amp;_a:hover]:shadow-highlight-franklin dark:[&amp;amp;_a:hover]:shadow-highlight-blurple [&amp;amp;_a]:shadow-underline-black dark:[&amp;amp;_a]:shadow-underline-white"&gt;在其公告博客中被描述為 Discord 的新「增長」層&lt;a href="https://support.discord.com/hc/en-us/articles/5330075836311-Monetization-Terms"&gt;貨幣化條款&lt;/a&gt;，15% 的費用將從 6 月 6 日開始收取。&lt;a href="https://discord.com/developers/docs/monetization/one-time-purchases"&gt;一次性購買&lt;/a&gt;，允許開發者無需訂閲即可銷售遊戲、化妝品皮膚和其他優質資產等產品。&lt;/p&gt;&lt;/div&gt;&lt;div class="duet--article--article-body-component"&gt;&lt;p class="duet--article--dangerously-set-cms-markup duet--article--standard-paragraph mb-20 font-fkroman text-18 leading-160 -tracking-1 selection:bg-franklin-20 dark:text-white dark:selection:bg-blurple [&amp;amp;_a:hover]:shadow-highlight-franklin dark:[&amp;amp;_a:hover]:shadow-highlight-blurple [&amp;amp;_a]:shadow-underline-black dark:[&amp;amp;_a]:shadow-underline-white"&gt;這些可以作為「耐用」的一次性購買 SKU（提供永久的好處）或可以過期或用完的消耗品提供。&lt;a href="https://discord.com/developers/docs/monetization/managing-your-store#managing-your-store"&gt;新的商店表面&lt;/a&gt;，可以通過 Discord 上的應用程序目錄或個人資料找到。&lt;a href="https://www.theverge.com/2024/5/29/24167147/discord-gaming-focus-redesign"&gt;將其應用程序引導迴遊戲&lt;/a&gt;此前在新冠疫情期間曾嘗試將自己開發為一款更通用的聊天應用程序。&lt;/p&gt;&lt;/div&gt;&lt;div class="duet--article--article-body-component"&gt;&lt;p class="duet--article--dangerously-set-cms-markup duet--article--standard-paragraph mb-20 font-fkroman text-18 leading-160 -tracking-1 selection:bg-franklin-20 dark:text-white dark:selection:bg-blurple [&amp;amp;_a:hover]:shadow-highlight-franklin dark:[&amp;amp;_a:hover]:shadow-highlight-blurple [&amp;amp;_a]:shadow-underline-black dark:[&amp;amp;_a]:shadow-underline-white"&gt;所有這些新工具目前正在美國、英國和歐盟推出，但「稍後」將擴展到其他地區。&lt;/p&gt;&lt;/div&gt;&lt;/div&gt;&lt;div class="mb-40 mt-30"&gt;&lt;button class="duet--article--comments-button group inline-flex h-40 w-full items-center justify-center rounded-[2px] border-[1px] border-solid border-blurple font-polysans-mono text-11 font-light uppercase tracking-12 text-blurple hover:bg-blurple hover:text-white md:w-auto md:px-30"&gt;&lt;svg class="mr-10 inline pt-2" fill="none" height="14" stroke-width="1px" viewbox="0 0 12 12" width="12"
            xmlns="http://www.w3.org/2000/svg"&gt;&lt;title&gt;Comments&lt;/title&gt;&lt;path d="M2.4 9.1h-.207l-.147.146L.5 10.793V1.2c0-.384.316-.7.7-.7h9.6c.384 0 .7.316.7.7v7.2c0 .384-.316.7-.7.7H2.4Z" stroke="currentColor"&gt;&lt;/path&gt;&lt;/svg&gt;&lt;span class="coral-count"&gt;&lt;/span&gt;&lt;/button&gt;&lt;/div&gt;
        </summary>
        <published>2024-06-06T15:00:00+00:00</published>
    </entry>
</feed>
